Workbook

Sheet Overview

Sheet Assumptions ( Driver)
B2: Assumptions of Titagarh Rail Systems
B3: All figures are in Rs. ( Crores)
B4: Financial Year | C4: 2023A | D4: 2024A | E4: 2025A | F4: 2026E | G4: 2027E | H4: 2028E | I4: 2029E | J4: 2030E
B5: Income Statement Assumptions
B6: Revenue | C6: ='(IS)'!K4 -> 2780 | D6: ='(IS)'!L4 -> 3853 | E6: ='(IS)'!M4 -> 3868 | F6: =E6*(1+F7) -> 4621.9975 | G6: =F6*(1+G7) -> 5522.9734 | H6: =G6*(1+H7) -> 6599.5785 | I6: =H6*(1+I7) -> 7886.0485 | J6: =I6*(1+J7) -> 9423.2929
B7: Revenue growth ( Y.O.Y) | D7: =D6/C6-1 -> 0.38597122 | E7: =E6/D6-1 -> 0.0038930703 | F7: =AVERAGE(D7:E7) -> 0.19493215 | G7: =F7 -> 0.19493215 | H7: =AVERAGE(F7:G7) -> 0.19493215 | I7: =AVERAGE(G7:H7) -> 0.19493215 | J7: =AVERAGE(H7:I7) -> 0.19493215
B9: Cost of Goods Sold | C9: ='(IS)'!V5+'(IS)'!V7+'(IS)'!V8-'(IS)'!V6 -> 2382.62 | D9: ='(IS)'!W5+'(IS)'!W7+'(IS)'!W8-'(IS)'!W6 -> 3253.82 | E9: ='(IS)'!X5+'(IS)'!X7+'(IS)'!X8-'(IS)'!X6 -> 3248.97 | F9: =F6*F10 -> 3915.6158 | G9: =G6*G10 -> 4678.8952 | H9: =H6*H10 -> 5590.9623 | I9: =I6*I10 -> 6680.8205 | J9: =J6*J10 -> 7983.1272
B10: As a % of Revenue | C10: =C9/C6 -> 0.85705755 | D10: =D9/D6 -> 0.84449001 | E10: =E9/E6 -> 0.83996122 | F10: =AVERAGE(C10:E10) -> 0.84716959 | G10: =F10 -> 0.84716959 | H10: =G10 -> 0.84716959 | I10: =H10 -> 0.84716959 | J10: =I10 -> 0.84716959
B12: Operating Expenditure | C12: ='(IS)'!V9+'(IS)'!V10+'(IS)'!V11 -> 146.2 | D12: ='(IS)'!W9+'(IS)'!W10+'(IS)'!W11 -> 150.17 | E12: ='(IS)'!X9+'(IS)'!X10+'(IS)'!X11 -> 209.66 | F12: =F6*F13 -> 224.58051 | G12: =G6*G13 -> 268.35847 | H12: =H6*H13 -> 320.67017 | I12: =I6*I13 -> 383.17909 | J12: =J6*J13 -> 451.59013
B13: As a % of Revenue | C13: =C12/C6 -> 0.052589928 | D13: =D12/D6 -> 0.038974825 | E13: =E12/E6 -> 0.054203723 | F13: =AVERAGE(C13:E13) -> 0.048589492 | G13: =AVERAGE(C13:F13) -> 0.048589492 | H13: =AVERAGE(C13:G13) -> 0.048589492 | I13: =AVERAGE(C13:H13) -> 0.048589492 | J13: =AVERAGE(D13:I13) -> 0.047922753
B15: Interest Expenses | C15: ='(IS)'!V14 -> 80.75 | D15: ='(IS)'!W14 -> 73.45 | E15: ='(IS)'!X14 -> 73.15 | F15: =F18*F19 -> 147.796 | G15: =G18*G19 -> 145.58052 | H15: =H18*H19 -> 144.90032 | I15: =I18*I19 -> 146.09228 | J15: =J18*J19 -> 149.40147
B16: Short Term Burrowings | C16: ='(BS)'!K8 -> 200 | D16: ='(BS)'!L8 -> 29 | E16: ='(BS)'!M8 -> 504 | F16: =AVERAGE(C16:E16) -> 244.33333 | G16: =AVERAGE(C16:F16) -> 244.33333 | H16: =AVERAGE(C16:G16) -> 244.33333 | I16: =AVERAGE(C16:H16) -> 244.33333 | J16: =AVERAGE(D16:I16) -> 251.72222
B17: Long Term Burrowings | C17: ='(BS)'!K7 -> 50 | D17: ='(BS)'!L7 -> 37 | E17: ='(BS)'!M7 -> 25 | F17: =AVERAGE(C17:E17) -> 37.333333 | G17: =AVERAGE(D17:F17) -> 33.111111 | H17: =AVERAGE(E17:G17) -> 31.814815 | I17: =AVERAGE(F17:H17) -> 34.08642 | J17: =AVERAGE(G17:I17) -> 33.004115
B18: Total Burrowings | C18: =C16+C17 -> 250 | D18: =D16+D17 -> 66 | E18: =E16+E17 -> 529 | F18: =F16+F17 -> 281.66667 | G18: =G16+G17 -> 277.44444 | H18: =H16+H17 -> 276.14815 | I18: =I16+I17 -> 278.41975 | J18: =J16+J17 -> 284.72634
B19: Interest Rate | C19: =C15/C18 -> 0.323 | D19: =D15/D18 -> 1.1128788 | E19: =E15/E18 -> 0.13827977 | F19: =AVERAGE(C19:E19) -> 0.52471952 | G19: =F19 -> 0.52471952 | H19: =G19 -> 0.52471952 | I19: =H19 -> 0.52471952 | J19: =I19 -> 0.52471952
B21: Tax Expenses | C21: ='(IS)'!V16 -> 55.47 | D21: ='(IS)'!W16 -> 100.14 | E21: ='(IS)'!X16 -> 106.68
B22: As a % of EBT | C22: =C21/IS!C14 -> 0.30546836 | D22: =D21/IS!D14 -> 0.25944349 | E22: =E21/IS!E14 -> 0.27937672 | F22: =AVERAGE(C22:E22) -> 0.28142953 | G22: =F22 -> 0.28142953 | H22: =G22 -> 0.28142953 | I22: =H22 -> 0.28142953 | J22: =I22 -> 0.28142953
B24: Dividends Paid | C24: =IS!C17 -> 5.98 | D24: =IS!D17 -> 10.77 | E24: =IS!E17 -> 13.46
B25: As a % of PAT | C25: =C24/IS!C16 -> 0.04741516 | D25: =D24/IS!D16 -> 0.037678421 | E25: =E24/IS!E16 -> 0.048915216 | F25: =AVERAGE(C25:E25) -> 0.044669599 | G25: =F25 -> 0.044669599 | H25: =G25 -> 0.044669599 | I25: =H25 -> 0.044669599 | J25: =I25 -> 0.044669599
B27: Balance Sheet Assumptions
B28: Working Capital
B29: Current Investments ( % of revenue ) | C29: ='(BS)'!K31/IS!C5 -> 0.011510791 | D29: ='(BS)'!L31/IS!D5 -> 0.051388528 | E29: ='(BS)'!M31/IS!E5 -> 0.077300931 | F29: =AVERAGE(C29:E29) -> 0.046733417 | G29: =AVERAGE(D29:F29) -> 0.058474292 | H29: =AVERAGE(E29:G29) -> 0.060836213 | I29: =AVERAGE(F29:H29) -> 0.055347974 | J29: =AVERAGE(G29:I29) -> 0.058219493
B30: Inventories ( % of COGS) | C30: ='(BS)'!K33/IS!C6 -> 0.19348448 | D30: ='(BS)'!L33/IS!D6 -> 0.16104148 | E30: ='(BS)'!M33/IS!E6 -> 0.16097409 | F30: =AVERAGE(C30:E30) -> 0.17183335 | G30: =AVERAGE(D30:F30) -> 0.16461631 | H30: =AVERAGE(E30:G30) -> 0.16580792 | I30: =AVERAGE(F30:H30) -> 0.16741919 | J30: =AVERAGE(G30:I30) -> 0.16594781
B31: Trade Receivables( % of revenue ) | C31: ='(BS)'!K34/IS!C5 -> 0.10035971 | D31: ='(BS)'!L34/IS!D5 -> 0.13833377 | E31: ='(BS)'!M34/IS!E5 -> 0.17347466 | F31: =AVERAGE(C31:E31) -> 0.13738938 | G31: =AVERAGE(D31:F31) -> 0.1497326 | H31: =AVERAGE(E31:G31) -> 0.15353222 | I31: =AVERAGE(F31:H31) -> 0.14688473 | J31: =AVERAGE(G31:I31) -> 0.15004985
B32: Trade Payables( % of COGS) | C32: ='(BS)'!K13/IS!C6 -> 0.13556505 | D32: ='(BS)'!L13/IS!D6 -> 0.098038613 | E32: ='(BS)'!M13/IS!E6 -> 0.072330616 | F32: =AVERAGE(C32:E32) -> 0.10197809 | G32: =AVERAGE(D32:F32) -> 0.090782441 | H32: =AVERAGE(E32:G32) -> 0.088363716 | I32: =AVERAGE(F32:H32) -> 0.093708083 | J32: =AVERAGE(G32:I32) -> 0.090951413
B34: Reserve & Surplus ( Adjustment)
B35: Opening Reserve and Surplus | C35: ='(BS)'!J5 -> 818 | D35: =C38 -> 940 | E35: =D38 -> 2191 | F35: =E38 -> 2456 | G35: =F38 -> 2694.2261 | H35: =G38 -> 2998.5818 | I35: =H38 -> 3380.4013 | J35: =I38 -> 3845.5256
B36: Add Retained Earnings | C36: =IS!C18 -> 120.14 | D36: =IS!D18 -> 275.07 | E36: =IS!E18 -> 261.71 | F36: =IS!F18 -> 238.22613 | G36: =IS!G18 -> 304.35567 | H36: =IS!H18 -> 381.81946 | I36: =IS!I18 -> 465.12432 | J36: =IS!J18 -> 573.48166
B37: Adjustment Figure | C37: =C38-C36-C35 -> 1.86 | D37: =D38-D36-D35 -> 975.93 | E37: =E38-E36-E35 -> 3.29 | F37: 0 | G37: =F37 -> 0 | H37: =G37 -> 0 | I37: =H37 -> 0 | J37: =I37 -> 0
B38: Closing Reserve and Surplus | C38: =BS!D36 -> 940 | D38: =BS!E36 -> 2191 | E38: =BS!F36 -> 2456 | F38: =F35+F36 -> 2694.2261 | G38: =G35+G36 -> 2998.5818 | H38: =H35+H36 -> 3380.4013 | I38: =I35+I36 -> 3845.5256 | J38: =J35+J36 -> 4419.0072

Sheet Schedule 

Sheet Capex
B2: Capex Schedule
B3: All figures are in Rs. ( Crores)
B4: Financial Year | C4: 2023A | D4: 2024A | E4: 2025A | F4: 2026E | G4: 2027E | H4: 2028E | I4: 2029E | J4: 2030E
B5: Opening Tangible & Intangible Assets | D5: =C8 -> 691 | E5: =D8 -> 706 | F5: =E8 -> 882 | G5: =F8 -> 1001.5108 | H5: =G8 -> 1137.2152 | I5: =H8 -> 1291.3075 | J5: =I8 -> 1466.2794
B6: Add Capex ( for both Tangible & Intangible) | D6: =D8+D7-D5 -> 42.1 | E6: =E8+E7-E5 -> 205.58 | F6: =F5*F11 -> 155.28315 | G6: =G5*G11 -> 176.32398 | H6: =H5*H11 -> 200.21583 | I6: =I5*I11 -> 227.34502 | J6: =J5*J11 -> 258.15021
B7: Minus Depreciation & Amortisation | C7: =IS!C10 -> 22.5 | D7: =IS!D10 -> 27.1 | E7: =IS!E10 -> 29.58 | F7: =F5*F12 -> 35.772395 | G7: =G5*G12 -> 40.619544 | H7: =H5*H12 -> 46.123481 | I7: =I5*I12 -> 52.373201 | J7: =J5*J12 -> 59.469755
B8: Closing Tangible & Intangible Assets | C8: =SUM('(BS)'!K18:K26)-'(BS)'!K29 -> 691 | D8: =SUM('(BS)'!L18:L26)-'(BS)'!L29 -> 706 | E8: =SUM('(BS)'!M18:M26)-'(BS)'!M29 -> 882 | F8: =F5+F6-F7 -> 1001.5108 | G8: =G5+G6-G7 -> 1137.2152 | H8: =H5+H6-H7 -> 1291.3075 | I8: =I5+I6-I7 -> 1466.2794 | J8: =J5+J6-J7 -> 1664.9598
B11: Capex % | D11: =D6/D5 -> 0.060926194 | E11: =E6/E5 -> 0.2911898 | F11: =AVERAGE(C11:E11) -> 0.176058 | G11: =F11 -> 0.176058 | H11: =G11 -> 0.176058 | I11: =H11 -> 0.176058 | J11: =I11 -> 0.176058
B12: Dep % | D12: =D7/D5 -> 0.039218524 | E12: =E7/E5 -> 0.041898017 | F12: =AVERAGE(C12:E12) -> 0.04055827 | G12: =F12 -> 0.04055827 | H12: =G12 -> 0.04055827 | I12: =H12 -> 0.04055827 | J12: =I12 -> 0.04055827

Sheet IS
B2: Income Statement for Titagarh Rail Systems
B3: All figures are in Rs. ( Crores)
B4: Financial Year | C4: 2023A | D4: 2024A | E4: 2025A | F4: 2026E | G4: 2027E | H4: 2028E | I4: 2029E | J4: 2030E
B5: Total Revenue | C5: ='Assumptions ( Driver)'!C6 -> 2780 | D5: ='Assumptions ( Driver)'!D6 -> 3853 | E5: ='Assumptions ( Driver)'!E6 -> 3868 | F5: ='Assumptions ( Driver)'!F6 -> 4621.9975 | G5: ='Assumptions ( Driver)'!G6 -> 5522.9734 | H5: ='Assumptions ( Driver)'!H6 -> 6599.5785 | I5: ='Assumptions ( Driver)'!I6 -> 7886.0485 | J5: ='Assumptions ( Driver)'!J6 -> 9423.2929
B6: Cost of Goods Sold | C6: ='Assumptions ( Driver)'!C9 -> 2382.62 | D6: ='Assumptions ( Driver)'!D9 -> 3253.82 | E6: ='Assumptions ( Driver)'!E9 -> 3248.97 | F6: ='Assumptions ( Driver)'!F9 -> 3915.6158 | G6: ='Assumptions ( Driver)'!G9 -> 4678.8952 | H6: ='Assumptions ( Driver)'!H9 -> 5590.9623 | I6: ='Assumptions ( Driver)'!I9 -> 6680.8205 | J6: ='Assumptions ( Driver)'!J9 -> 7983.1272
B7: Gross Profit | C7: =C5-C6 -> 397.38 | D7: =D5-D6 -> 599.18 | E7: =E5-E6 -> 619.03 | F7: =F5-F6 -> 706.38176 | G7: =G5-G6 -> 844.07827 | H7: =H5-H6 -> 1008.6163 | I7: =I5-I6 -> 1205.228 | J7: =J5-J6 -> 1440.1657
B8: Operating Expenses | C8: ='Assumptions ( Driver)'!C12 -> 146.2 | D8: ='Assumptions ( Driver)'!D12 -> 150.17 | E8: ='Assumptions ( Driver)'!E12 -> 209.66 | F8: ='Assumptions ( Driver)'!F12 -> 224.58051 | G8: ='Assumptions ( Driver)'!G12 -> 268.35847 | H8: ='Assumptions ( Driver)'!H12 -> 320.67017 | I8: ='Assumptions ( Driver)'!I12 -> 383.17909 | J8: ='Assumptions ( Driver)'!J12 -> 451.59013
B9: EBITDA | C9: =C7-C8 -> 251.18 | D9: =D7-D8 -> 449.01 | E9: =E7-E8 -> 409.37 | F9: =F7-F8 -> 481.80125 | G9: =G7-G8 -> 575.7198 | H9: =H7-H8 -> 687.9461 | I9: =I7-I8 -> 822.04891 | J9: =J7-J8 -> 988.57554
B10: Depreciation & Amortisation | C10: ='(IS)'!V13 -> 22.5 | D10: ='(IS)'!W13 -> 27.1 | E10: ='(IS)'!X13 -> 29.58 | F10: =Capex!F7 -> 35.772395 | G10: =Capex!G7 -> 40.619544 | H10: =Capex!H7 -> 46.123481 | I10: =Capex!I7 -> 52.373201 | J10: =Capex!J7 -> 59.469755
B11: Other Income | C11: ='(IS)'!V12 -> 33.66 | D11: ='(IS)'!W12 -> 37.52 | E11: ='(IS)'!X12 -> 75.21 | F11: =AVERAGE(C11:E11) -> 48.796667 | G11: =AVERAGE(D11:F11) -> 53.842222 | H11: =AVERAGE(E11:G11) -> 59.282963 | I11: =AVERAGE(F11:H11) -> 53.973951 | J11: =AVERAGE(G11:I11) -> 55.699712
B12: EBIT | C12: =C9-C10+C11 -> 262.34 | D12: =D9-D10+D11 -> 459.43 | E12: =E9-E10+E11 -> 455 | F12: =F9-F10+F11 -> 494.82552 | G12: =G9-G10+G11 -> 588.94248 | H12: =H9-H10+H11 -> 701.10558 | I12: =I9-I10+I11 -> 823.64966 | J12: =J9-J10+J11 -> 984.8055
B13: Interest | C13: ='Assumptions ( Driver)'!C15 -> 80.75 | D13: ='Assumptions ( Driver)'!D15 -> 73.45 | E13: ='Assumptions ( Driver)'!E15 -> 73.15 | F13: ='Assumptions ( Driver)'!F15 -> 147.796 | G13: ='Assumptions ( Driver)'!G15 -> 145.58052 | H13: ='Assumptions ( Driver)'!H15 -> 144.90032 | I13: ='Assumptions ( Driver)'!I15 -> 146.09228 | J13: ='Assumptions ( Driver)'!J15 -> 149.40147
B14: EBT | C14: =C12-C13 -> 181.59 | D14: =D12-D13 -> 385.98 | E14: =E12-E13 -> 381.85 | F14: =F12-F13 -> 347.02952 | G14: =G12-G13 -> 443.36196 | H14: =H12-H13 -> 556.20525 | I14: =I12-I13 -> 677.55738 | J14: =J12-J13 -> 835.40403
B15: Tax | C15: ='(IS)'!V16 -> 55.47 | D15: ='(IS)'!W16 -> 100.14 | E15: ='(IS)'!X16 -> 106.68 | F15: =IS!F14*'Assumptions ( Driver)'!F22 -> 97.664354 | G15: =IS!G14*'Assumptions ( Driver)'!G22 -> 124.77515 | H15: =IS!H14*'Assumptions ( Driver)'!H22 -> 156.53258 | I15: =IS!I14*'Assumptions ( Driver)'!I22 -> 190.68465 | J15: =IS!J14*'Assumptions ( Driver)'!J22 -> 235.10736
B16: EAT | C16: =C14-C15 -> 126.12 | D16: =D14-D15 -> 285.84 | E16: =E14-E15 -> 275.17 | F16: =F14-F15 -> 249.36517 | G16: =G14-G15 -> 318.58682 | H16: =H14-H15 -> 399.67267 | I16: =I14-I15 -> 486.87273 | J16: =J14-J15 -> 600.29667
B17: Dividends | C17: ='(IS)'!V18 -> 5.98 | D17: ='(IS)'!W18 -> 10.77 | E17: ='(IS)'!X18 -> 13.46 | F17: =F16*'Assumptions ( Driver)'!F25 -> 11.139042 | G17: =G16*'Assumptions ( Driver)'!G25 -> 14.231145 | H17: =H16*'Assumptions ( Driver)'!H25 -> 17.853218 | I17: =I16*'Assumptions ( Driver)'!I25 -> 21.74841 | J17: =J16*'Assumptions ( Driver)'!J25 -> 26.815012
B18: Retained earnings | C18: =C16-C17 -> 120.14 | D18: =D16-D17 -> 275.07 | E18: =E16-E17 -> 261.71 | F18: =F16-F17 -> 238.22613 | G18: =G16-G17 -> 304.35567 | H18: =H16-H17 -> 381.81946 | I18: =I16-I17 -> 465.12432 | J18: =J16-J17 -> 573.48166

Sheet BS
B2: Balance Sheet of Titagarh Rail Systems
B3: All figures are in Rs. ( Crores)
B4: Financial Year | D4: 2023A | E4: 2024A | F4: 2025A | G4: 2026E | H4: 2027E | I4: 2028E | J4: 2029E | K4: 2030E
B5: Assets
B6: Current Assets
A7: IA | B7: Current Investments | C7: 0 | D7: ='(BS)'!K31 -> 32 | E7: ='(BS)'!L31 -> 198 | F7: ='(BS)'!M31 -> 299 | G7: ='Assumptions ( Driver)'!F29*IS!F5 -> 216.00174 | H7: ='Assumptions ( Driver)'!G29*IS!G5 -> 322.95196 | I7: ='Assumptions ( Driver)'!H29*IS!H5 -> 401.49337 | J7: ='Assumptions ( Driver)'!I29*IS!I5 -> 436.47681 | K7: ='Assumptions ( Driver)'!J29*IS!J5 -> 548.61934
A8: OA | B8: Inventories | C8: 0 | D8: ='(BS)'!K33 -> 461 | E8: ='(BS)'!L33 -> 524 | F8: ='(BS)'!M33 -> 523 | G8: ='Assumptions ( Driver)'!F30*IS!F6 -> 672.83339 | H8: ='Assumptions ( Driver)'!G30*IS!G6 -> 770.22246 | I8: ='Assumptions ( Driver)'!H30*IS!H6 -> 927.02582 | J8: ='Assumptions ( Driver)'!I30*IS!I6 -> 1118.4976 | K8: ='Assumptions ( Driver)'!J30*IS!J6 -> 1324.7825
A9: OA | B9: Trade Receivables | C9: 0 | D9: ='(BS)'!K34 -> 279 | E9: ='(BS)'!L34 -> 533 | F9: ='(BS)'!M34 -> 671 | G9: ='Assumptions ( Driver)'!F31*IS!F5 -> 635.01338 | H9: ='Assumptions ( Driver)'!G31*IS!G5 -> 826.96919 | I9: ='Assumptions ( Driver)'!H31*IS!H5 -> 1013.2479 | J9: ='Assumptions ( Driver)'!I31*IS!I5 -> 1158.3401 | K9: ='Assumptions ( Driver)'!J31*IS!J5 -> 1413.9637
A10: End of CFS | B10: Cash And Cash Equivalents | C10: 0 | D10: ='(BS)'!K35 -> 100 | E10: ='(BS)'!L35 -> 609 | F10: ='(BS)'!M35 -> 467 | G10: =F10+CFS!F34 -> 493.84056 | H10: =BS!G10+CFS!G34 -> 287.42896 | I10: =BS!H10+CFS!H34 -> 161.51296 | J10: =BS!I10+CFS!I34 -> 214.39831 | K10: =BS!J10+CFS!J34 -> 121.48497
A11: OA | B11: Short Term Loans And Advances | C11: 0 | D11: ='(BS)'!K36 -> 8 | E11: ='(BS)'!L36 -> 9 | F11: ='(BS)'!M36 -> 36 | G11: =AVERAGE(D11:F11) -> 17.666667 | H11: =G11 -> 17.666667 | I11: =H11 -> 17.666667 | J11: =I11 -> 17.666667 | K11: =J11 -> 17.666667
A12: OA | B12: Other Current Assets | C12: 0 | D12: ='(BS)'!K37 -> 623 | E12: ='(BS)'!L37 -> 423 | F12: ='(BS)'!M37 -> 650 | G12: =AVERAGE(D12:F12) -> 565.33333 | H12: =G12 -> 565.33333 | I12: =H12 -> 565.33333 | J12: =I12 -> 565.33333 | K12: =J12 -> 565.33333
B13: Total Current Assets | C13: 0 | D13: =SUM(D7:D12) -> 1503 | E13: =SUM(E7:E12) -> 2296 | F13: =SUM(F7:F12) -> 2646 | G13: =SUM(G7:G12) -> 2600.6891 | H13: =SUM(H7:H12) -> 2790.5726 | I13: =SUM(I7:I12) -> 3086.2801 | J13: =SUM(J7:J12) -> 3510.7128 | K13: =SUM(K7:K12) -> 3991.8505
B14: Non-Current Assets
A15: Adjst with Dep ( Capex ) | B15: Assets | C15: 0 | D15: ='(BS)'!K17-'(BS)'!K27 -> 692 | E15: ='(BS)'!L17-'(BS)'!L27 -> 707 | F15: ='(BS)'!M17-'(BS)'!M27 -> 882 | G15: =Capex!F8 -> 1001.5108 | H15: =Capex!G8 -> 1137.2152 | I15: =Capex!H8 -> 1291.3075 | J15: =Capex!I8 -> 1466.2794 | K15: =Capex!J8 -> 1664.9598
A16: IA | B16: Capital Work-In-Progress | C16: 0 | D16: ='(BS)'!K30 -> 14 | E16: ='(BS)'!L30 -> 171 | F16: ='(BS)'!M30 -> 122 | G16: =F16 -> 122 | H16: =G16 -> 122 | I16: =H16 -> 122 | J16: =I16 -> 122 | K16: =J16 -> 122
A17: IA | B17: Other Non-Current Assets | C17: 0 | D17: ='(BS)'!K27 -> 40 | E17: ='(BS)'!L27 -> 41 | F17: ='(BS)'!M27 -> 110 | G17: =F17 -> 110 | H17: =G17 -> 110 | I17: =H17 -> 110 | J17: =I17 -> 110 | K17: =J17 -> 110
B18: Total Non-Current Assets | D18: =SUM(D15:D17) -> 746 | E18: =SUM(E15:E17) -> 919 | F18: =SUM(F15:F17) -> 1114 | G18: =SUM(G15:G17) -> 1233.5108 | H18: =SUM(H15:H17) -> 1369.2152 | I18: =SUM(I15:I17) -> 1523.3075 | J18: =SUM(J15:J17) -> 1698.2794 | K18: =SUM(K15:K17) -> 1896.9598
B19: Total Assets | D19: =D13+D18 -> 2249 | E19: =E13+E18 -> 3215 | F19: =F13+F18 -> 3760 | G19: =G13+G18 -> 3834.1998 | H19: =H13+H18 -> 4159.7878 | I19: =I13+I18 -> 4609.5876 | J19: =J13+J18 -> 5208.9922 | K19: =K13+K18 -> 5888.8103
B20: Liabilities
B21: Current Liabilities
A22: FA | B22: Short Term Borrowings | C22: 0 | D22: ='Assumptions ( Driver)'!C16 -> 200 | E22: ='Assumptions ( Driver)'!D16 -> 29 | F22: ='Assumptions ( Driver)'!E16 -> 504 | G22: ='Assumptions ( Driver)'!F16 -> 244.33333 | H22: ='Assumptions ( Driver)'!G16 -> 244.33333 | I22: ='Assumptions ( Driver)'!H16 -> 244.33333 | J22: ='Assumptions ( Driver)'!I16 -> 244.33333 | K22: ='Assumptions ( Driver)'!J16 -> 251.72222
A23: OA | B23: Trade Payables | C23: 0 | D23: ='(BS)'!K13 -> 323 | E23: ='(BS)'!L13 -> 319 | F23: ='(BS)'!M13 -> 235 | G23: ='Assumptions ( Driver)'!F32*IS!F6 -> 399.30703 | H23: ='Assumptions ( Driver)'!G32*IS!G6 -> 424.76152 | I23: ='Assumptions ( Driver)'!H32*IS!H6 -> 494.0382 | J23: ='Assumptions ( Driver)'!I32*IS!I6 -> 626.04689 | K23: ='Assumptions ( Driver)'!J32*IS!J6 -> 726.0767
A24: OA | B24: Other Current Liabilities | C24: 0 | D24: ='(BS)'!K15 -> 72 | E24: ='(BS)'!L15 -> 513 | F24: ='(BS)'!M15 -> 414 | G24: =AVERAGE(D24:F24) -> 333 | H24: =G24 -> 333 | I24: =H24 -> 333 | J24: =I24 -> 333 | K24: =J24 -> 333
B25: Advance from Customers | C25: 0 | D25: ='(BS)'!K14 -> 536 | E25: ='(BS)'!L14 -> 0 | F25: ='(BS)'!M14 -> 0 | G25: =F25 -> 0 | H25: =G25 -> 0 | I25: =H25 -> 0 | J25: =I25 -> 0 | K25: =J25 -> 0
A26: OA | B26: Non controlling int | C26: 0 | D26: ='(BS)'!K12 -> 0 | E26: ='(BS)'!L12 -> 0 | F26: ='(BS)'!M12 -> 1 | G26: =F26 -> 1 | H26: =G26 -> 1 | I26: =H26 -> 1 | J26: =I26 -> 1 | K26: =J26 -> 1
B27: Total Current Liabilities | C27: 0 | D27: =SUM(D22:D26) -> 1131 | E27: =SUM(E22:E26) -> 861 | F27: =SUM(F22:F26) -> 1154 | G27: =SUM(G22:G26) -> 977.64036 | H27: =SUM(H22:H26) -> 1003.0949 | I27: =SUM(I22:I26) -> 1072.3715 | J27: =SUM(J22:J26) -> 1204.3802 | K27: =SUM(K22:K26) -> 1311.7989
B28: Non-Current Liability
A29: FA | B29: Long Term Borrowings | C29: 0 | D29: ='Assumptions ( Driver)'!C17 -> 50 | E29: ='Assumptions ( Driver)'!D17 -> 37 | F29: ='Assumptions ( Driver)'!E17 -> 25 | G29: ='Assumptions ( Driver)'!F17 -> 37.333333 | H29: ='Assumptions ( Driver)'!G17 -> 33.111111 | I29: ='Assumptions ( Driver)'!H17 -> 31.814815 | J29: ='Assumptions ( Driver)'!I17 -> 34.08642 | K29: ='Assumptions ( Driver)'!J17 -> 33.004115
A30: OA | B30: Lease Liabilities | C30: 0 | D30: ='(BS)'!K9 -> 104 | E30: ='(BS)'!L9 -> 99 | F30: ='(BS)'!M9 -> 98 | G30: =F30 -> 98 | H30: =G30 -> 98 | I30: =H30 -> 98 | J30: =I30 -> 98 | K30: =J30 -> 98
A31: FA | B31: Other Long Term Liabilities | C31: 0 | D31: ='(BS)'!K10 -> 0 | E31: ='(BS)'!L10 -> 0 | F31: ='(BS)'!M10 -> 0 | G31: =F31 -> 0 | H31: =G31 -> 0 | I31: =H31 -> 0 | J31: =I31 -> 0 | K31: =J31 -> 0
B32: Total Non-Current Liability | D32: =SUM(D29:D31) -> 154 | E32: =SUM(E29:E31) -> 136 | F32: =SUM(F29:F31) -> 123 | G32: =SUM(G29:G31) -> 135.33333 | H32: =SUM(H29:H31) -> 131.11111 | I32: =SUM(I29:I31) -> 129.81481 | J32: =SUM(J29:J31) -> 132.08642 | K32: =SUM(K29:K31) -> 131.00412
B33: Total Liability | D33: =D27+D32 -> 1285 | E33: =E27+E32 -> 997 | F33: =F27+F32 -> 1277 | G33: =G27+G32 -> 1112.9737 | H33: =H27+H32 -> 1134.206 | I33: =I27+I32 -> 1202.1864 | J33: =J27+J32 -> 1336.4666 | K33: =K27+K32 -> 1442.803
B34: Equity
A35: FA | B35: Equity Share Capital | C35: 0 | D35: ='(BS)'!K4 -> 24 | E35: ='(BS)'!L4 -> 27 | F35: ='(BS)'!M4 -> 27 | G35: =F35 -> 27 | H35: =G35 -> 27 | I35: =H35 -> 27 | J35: =I35 -> 27 | K35: =J35 -> 27
A36: FA ( adjustement ) | B36: Reserves and Surplus | C36: 0 | D36: ='(BS)'!K5 -> 940 | E36: ='(BS)'!L5 -> 2191 | F36: ='(BS)'!M5 -> 2456 | G36: ='Assumptions ( Driver)'!F38 -> 2694.2261 | H36: ='Assumptions ( Driver)'!G38 -> 2998.5818 | I36: ='Assumptions ( Driver)'!H38 -> 3380.4013 | J36: ='Assumptions ( Driver)'!I38 -> 3845.5256 | K36: ='Assumptions ( Driver)'!J38 -> 4419.0072
B37: Total Equity | D37: =SUM(D35:D36) -> 964 | E37: =SUM(E35:E36) -> 2218 | F37: =SUM(F35:F36) -> 2483 | G37: =SUM(G35:G36) -> 2721.2261 | H37: =SUM(H35:H36) -> 3025.5818 | I37: =SUM(I35:I36) -> 3407.4013 | J37: =SUM(J35:J36) -> 3872.5256 | K37: =SUM(K35:K36) -> 4446.0072
B38: Total Liabaility & Equity | D38: =D37+D33 -> 2249 | E38: =E37+E33 -> 3215 | F38: =F37+F33 -> 3760 | G38: =G37+G33 -> 3834.1998 | H38: =H37+H33 -> 4159.7878 | I38: =I37+I33 -> 4609.5876 | J38: =J37+J33 -> 5208.9922 | K38: =K37+K33 -> 5888.8103
B40: Balance Check | D40: =D38=D19 -> TRUE | E40: =E38=E19 -> TRUE | F40: =F38=F19 -> TRUE | G40: =G38=G19 -> TRUE | H40: =H38=H19 -> TRUE | I40: =I38=I19 -> TRUE | J40: =J38=J19 -> TRUE | K40: =K38=K19 -> TRUE

Sheet CFS
B2: Cash Flow Statement for Titagarh Rail Systems ( Indirect Method)
B3: All figures are in Rs. ( Crores)
B4: Financial Year | C4: 2023A | D4: 2024A | E4: 2025A | F4: 2026E | G4: 2027E | H4: 2028E | I4: 2029E | J4: 2030E
B5: Cash Flow from Operating Activity
A6: IS | B6: Net Profit | C6: =IS!C16 -> 126.12 | D6: =IS!D16 -> 285.84 | E6: =IS!E16 -> 275.17 | F6: =IS!F16 -> 249.36517 | G6: =IS!G16 -> 318.58682 | H6: =IS!H16 -> 399.67267 | I6: =IS!I16 -> 486.87273 | J6: =IS!J16 -> 600.29667
A7: IS | B7: (add ) Depreciation & Amortisation | C7: =IS!C10 -> 22.5 | D7: =IS!D10 -> 27.1 | E7: =IS!E10 -> 29.58 | F7: =IS!F10 -> 35.772395 | G7: =IS!G10 -> 40.619544 | H7: =IS!H10 -> 46.123481 | I7: =IS!I10 -> 52.373201 | J7: =IS!J10 -> 59.469755
B9: Cash Flow before Working Capital Changes ( Change in )
A10: CA | B10: Inventories | C10: =BS!C8-BS!D8 -> -461 | D10: =BS!D8-BS!E8 -> -63 | E10: =BS!E8-BS!F8 -> 1 | F10: =BS!F8-BS!G8 -> -149.83339 | G10: =BS!G8-BS!H8 -> -97.389068 | H10: =BS!H8-BS!I8 -> -156.80336 | I10: =BS!I8-BS!J8 -> -191.47177 | J10: =BS!J8-BS!K8 -> -206.28487
A11: CA | B11: Trade Receivables | C11: =BS!C9-BS!D9 -> -279 | D11: =BS!D9-BS!E9 -> -254 | E11: =BS!E9-BS!F9 -> -138 | F11: =BS!F9-BS!G9 -> 35.98662 | G11: =BS!G9-BS!H9 -> -191.95581 | H11: =BS!H9-BS!I9 -> -186.27872 | I11: =BS!I9-BS!J9 -> -145.09222 | J11: =BS!J9-BS!K9 -> -255.62356
A12: CA | B12: Short Term Loans And Advances | C12: =BS!C11-BS!D11 -> -8 | D12: =BS!D11-BS!E11 -> -1 | E12: =BS!E11-BS!F11 -> -27 | F12: =BS!F11-BS!G11 -> 18.333333 | G12: =BS!G11-BS!H11 -> 0 | H12: =BS!H11-BS!I11 -> 0 | I12: =BS!I11-BS!J11 -> 0 | J12: =BS!J11-BS!K11 -> 0
A13: CA | B13: Other Current Assets | C13: =BS!C12-BS!D12 -> -623 | D13: =BS!D12-BS!E12 -> 200 | E13: =BS!E12-BS!F12 -> -227 | F13: =BS!F12-BS!G12 -> 84.666667 | G13: =BS!G12-BS!H12 -> 0 | H13: =BS!H12-BS!I12 -> 0 | I13: =BS!I12-BS!J12 -> 0 | J13: =BS!J12-BS!K12 -> 0
A14: CL | B14: Trade Payables | C14: =BS!D23-BS!C23 -> 323 | D14: =BS!E23-BS!D23 -> -4 | E14: =BS!F23-BS!E23 -> -84 | F14: =BS!G23-BS!F23 -> 164.30703 | G14: =BS!H23-BS!G23 -> 25.454492 | H14: =BS!I23-BS!H23 -> 69.27668 | I14: =BS!J23-BS!I23 -> 132.00868 | J14: =BS!K23-BS!J23 -> 100.02982
A15: CL | B15: Other Current Liabilities | C15: =BS!D24-BS!C24 -> 72 | D15: =BS!E24-BS!D24 -> 441 | E15: =BS!F24-BS!E24 -> -99 | F15: =BS!G24-BS!F24 -> -81 | G15: =BS!H24-BS!G24 -> 0 | H15: =BS!I24-BS!H24 -> 0 | I15: =BS!J24-BS!I24 -> 0 | J15: =BS!K24-BS!J24 -> 0
B16: Advance from Customers | C16: =BS!D25-BS!C25 -> 536 | D16: =BS!E25-BS!D25 -> -536 | E16: =BS!F25-BS!E25 -> 0 | F16: =BS!G25-BS!F25 -> 0 | G16: =BS!H25-BS!G25 -> 0 | H16: =BS!I25-BS!H25 -> 0 | I16: =BS!J25-BS!I25 -> 0 | J16: =BS!K25-BS!J25 -> 0
A17: CL | B17: Non controlling int | C17: =BS!D26-BS!C26 -> 0 | D17: =BS!E26-BS!D26 -> 0 | E17: =BS!F26-BS!E26 -> 1 | F17: =BS!G26-BS!F26 -> 0 | G17: =BS!H26-BS!G26 -> 0 | H17: =BS!I26-BS!H26 -> 0 | I17: =BS!J26-BS!I26 -> 0 | J17: =BS!K26-BS!J26 -> 0
B18: Cash Inflow ( Outflow ) from Operations | C18: =SUM(C6:C17) -> -291.38 | D18: =SUM(D6:D17) -> 95.94 | E18: =SUM(E6:E17) -> -268.25 | F18: =SUM(F6:F17) -> 357.59782 | G18: =SUM(G6:G17) -> 95.315972 | H18: =SUM(H6:H17) -> 171.99076 | I18: =SUM(I6:I17) -> 334.69062 | J18: =SUM(J6:J17) -> 297.88782
B19: Cash Flow from Investing Activity
B20: Capex in both Tangible & Intangible Assets | C20: =-Capex!C6 -> 0 | D20: =-Capex!D6 -> -42.1 | E20: =-Capex!E6 -> -205.58 | F20: =-Capex!F6 -> -155.28315 | G20: =-Capex!G6 -> -176.32398 | H20: =-Capex!H6 -> -200.21583 | I20: =-Capex!I6 -> -227.34502 | J20: =-Capex!J6 -> -258.15021
B21: Current Investments | C21: =BS!C7-BS!D7 -> -32 | D21: =BS!D7-BS!E7 -> -166 | E21: =BS!E7-BS!F7 -> -101 | F21: =BS!F7-BS!G7 -> 82.998262 | G21: =BS!G7-BS!H7 -> -106.95022 | H21: =BS!H7-BS!I7 -> -78.541404 | I21: =BS!I7-BS!J7 -> -34.983443 | J21: =BS!J7-BS!K7 -> -112.14253
B22: Capital Work-In-Progress | C22: =BS!C16-BS!D16 -> -14 | D22: =BS!D16-BS!E16 -> -157 | E22: =BS!E16-BS!F16 -> 49 | F22: =BS!F16-BS!G16 -> 0 | G22: =BS!G16-BS!H16 -> 0 | H22: =BS!H16-BS!I16 -> 0 | I22: =BS!I16-BS!J16 -> 0 | J22: =BS!J16-BS!K16 -> 0
B23: Other Non-Current Assets | C23: =BS!C17-BS!D17 -> -40 | D23: =BS!D17-BS!E17 -> -1 | E23: =BS!E17-BS!F17 -> -69 | F23: =BS!F17-BS!G17 -> 0 | G23: =BS!G17-BS!H17 -> 0 | H23: =BS!H17-BS!I17 -> 0 | I23: =BS!I17-BS!J17 -> 0 | J23: =BS!J17-BS!K17 -> 0
B24: Cash Inflow ( Outflow ) from Investing Activity | C24: =SUM(C20:C23) -> -86 | D24: =SUM(D20:D23) -> -366.1 | E24: =SUM(E20:E23) -> -326.58 | F24: =SUM(F20:F23) -> -72.284892 | G24: =SUM(G20:G23) -> -283.2742 | H24: =SUM(H20:H23) -> -278.75723 | I24: =SUM(I20:I23) -> -262.32846 | J24: =SUM(J20:J23) -> -370.29274
B25: Cash Flow from Financing Activity
B26: Divident | C26: =-IS!C17 -> -5.98 | D26: =-IS!D17 -> -10.77 | E26: =-IS!E17 -> -13.46 | F26: =-IS!F17 -> -11.139042 | G26: =-IS!G17 -> -14.231145 | H26: =-IS!H17 -> -17.853218 | I26: =-IS!I17 -> -21.74841 | J26: =-IS!J17 -> -26.815012
B27: Short Term Borrowings | C27: =BS!D22-BS!C22 -> 200 | D27: =BS!E22-BS!D22 -> -171 | E27: =BS!F22-BS!E22 -> 475 | F27: =BS!G22-BS!F22 -> -259.66667 | G27: =BS!H22-BS!G22 -> 0 | H27: =BS!I22-BS!H22 -> 0 | I27: =BS!J22-BS!I22 -> 0 | J27: =BS!K22-BS!J22 -> 7.3888889
B28: Long Term Borrowings | C28: =BS!D29-BS!C29 -> 50 | D28: =BS!E29-BS!D29 -> -13 | E28: =BS!F29-BS!E29 -> -12 | F28: =BS!G29-BS!F29 -> 12.333333 | G28: =BS!H29-BS!G29 -> -4.2222222 | H28: =BS!I29-BS!H29 -> -1.2962963 | I28: =BS!J29-BS!I29 -> 2.2716049 | J28: =BS!K29-BS!J29 -> -1.0823045
B29: Other Long Term Liabilities | C29: =BS!D31-BS!C31 -> 0 | D29: =BS!E31-BS!D31 -> 0 | E29: =BS!F31-BS!E31 -> 0 | F29: =BS!G31-BS!F31 -> 0 | G29: =BS!H31-BS!G31 -> 0 | H29: =BS!I31-BS!H31 -> 0 | I29: =BS!J31-BS!I31 -> 0 | J29: =BS!K31-BS!J31 -> 0
B30: Equity Share Capital | C30: =BS!D35-BS!C35 -> 24 | D30: =BS!E35-BS!D35 -> 3 | E30: =BS!F35-BS!E35 -> 0 | F30: =BS!G35-BS!F35 -> 0 | G30: =BS!H35-BS!G35 -> 0 | H30: =BS!I35-BS!H35 -> 0 | I30: =BS!J35-BS!I35 -> 0 | J30: =BS!K35-BS!J35 -> 0
B31: Reserves and Surplus | C31: ='Assumptions ( Driver)'!C37 -> 1.86 | D31: ='Assumptions ( Driver)'!D37 -> 975.93 | E31: ='Assumptions ( Driver)'!E37 -> 3.29 | F31: ='Assumptions ( Driver)'!F37 -> 0 | G31: ='Assumptions ( Driver)'!G37 -> 0 | H31: ='Assumptions ( Driver)'!H37 -> 0 | I31: ='Assumptions ( Driver)'!I37 -> 0 | J31: ='Assumptions ( Driver)'!J37 -> 0
B32: Cash Inflow ( Outflow ) from Financing Activity | C32: =SUM(C26:C31) -> 269.88 | D32: =SUM(D26:D31) -> 784.16 | E32: =SUM(E26:E31) -> 452.83 | F32: =SUM(F26:F31) -> -258.47238 | G32: =SUM(G26:G31) -> -18.453368 | H32: =SUM(H26:H31) -> -19.149514 | I32: =SUM(I26:I31) -> -19.476805 | J32: =SUM(J26:J31) -> -20.508427
B34: Net Cash Flow from All Activities ( O+I+F) | C34: =C18+C24+C32 -> -107.5 | D34: =D18+D24+D32 -> 514 | E34: =E18+E24+E32 -> -142 | F34: =F18+F24+F32 -> 26.840556 | G34: =G18+G24+G32 -> -206.4116 | H34: =H18+H24+H32 -> -125.91599 | I34: =I18+I24+I32 -> 52.885349 | J34: =J18+J24+J32 -> -92.913347
B36: Cash & Cash Equivalents at Beginning of Year | C36: ='(BS)'!J35 -> 42 | D36: =C38 -> 100 | E36: =D38 -> 609 | F36: =E38 -> 467 | G36: =F38 -> 493.84056 | H36: =G38 -> 287.42896 | I36: =H38 -> 161.51296 | J36: =I38 -> 214.39831
C37: =C34+C36 -> -65.5 | D37: =D34+D36 -> 614 | E37: =E34+E36 -> 467 | F37: =F34+F36 -> 493.84056 | G37: =G34+G36 -> 287.42896 | H37: =H34+H36 -> 161.51296 | I37: =I34+I36 -> 214.39831 | J37: =J34+J36 -> 121.48497
B38: Closing Cash | C38: =BS!D10 -> 100 | D38: =BS!E10 -> 609 | E38: =BS!F10 -> 467 | F38: =F34+F36 -> 493.84056 | G38: =G34+G36 -> 287.42896 | H38: =H34+H36 -> 161.51296 | I38: =I34+I36 -> 214.39831 | J38: =J34+J36 -> 121.48497

Sheet Valuation

Sheet Beta
B2: Regression Beta 2 years Weekly
B4: Titagarh Rail Systems | F4: NIFTY
B6: Date | C6: Adj Close | D6: Growth Rate | F6: Adj Close | G6: Growth Rate
B7: Aug 4, 2026 | C7: 849.75 | F7: 24614.9
B8: Aug 3, 2026 | C8: 859.05 | D8: =C8/C7-1 -> 0.010944395 | F8: 24774.3 | G8: =F8/F7-1 -> 0.0064757525
B9: Jul 27, 2026 | C9: 825.2 | D9: =C9/C8-1 -> -0.039403993 | F9: 24383.6 | G9: =F9/F8-1 -> -0.015770375
B10: Jul 20, 2026 | C10: 819.45 | D10: =C10/C9-1 -> -0.0069680078 | F10: 23767.45 | G10: =F10/F9-1 -> -0.025269033 | I10: SUMMARY OUTPUT
B11: Jul 13, 2026 | C11: 859.85 | D11: =C11/C10-1 -> 0.049301361 | F11: 24334.3 | G11: =F11/F10-1 -> 0.023849845
B12: Jul 6, 2026 | C12: 835.8 | D12: =C12/C11-1 -> -0.027969995 | F12: 24206.9 | G12: =F12/F11-1 -> -0.0052354085 | I12: Regression Statistics
B13: Jun 29, 2026 | C13: 877.25 | D13: =C13/C12-1 -> 0.049593204 | F13: 24270.85 | G13: =F13/F12-1 -> 0.0026418087 | I13: Multiple R | J13: 0.55019663
B14: Jun 22, 2026 | C14: 888.45 | D14: =C14/C13-1 -> 0.01276717 | F14: 24056 | G14: =F14/F13-1 -> -0.0088521828 | I14: R Square | J14: 0.30271633
B15: Jun 15, 2026 | C15: 922.45 | D15: =C15/C14-1 -> 0.038268895 | F15: 24013.1 | G15: =F15/F14-1 -> -0.0017833389 | I15: Adjusted R Square | J15: 0.29594658
B16: Jun 8, 2026 | C16: 858.65 | D16: =C16/C15-1 -> -0.06916364 | F16: 23622.9 | G16: =F16/F15-1 -> -0.016249464 | I16: Standard Error | J16: 0.051094208
B17: Jun 1, 2026 | C17: 837.9 | D17: =C17/C16-1 -> -0.024165842 | F17: 23366.7 | G17: =F17/F16-1 -> -0.010845408 | I17: Observations | J17: 105
B18: May 25, 2026 | C18: 826.15 | D18: =C18/C17-1 -> -0.014023153 | F18: 23547.75 | G18: =F18/F17-1 -> 0.0077482058
B19: May 18, 2026 | C19: 757.3 | D19: =C19/C18-1 -> -0.083338377 | F19: 23719.3 | G19: =F19/F18-1 -> 0.0072851971 | I19: ANOVA
B20: May 11, 2026 | C20: 763.3 | D20: =C20/C19-1 -> 0.0079228839 | F20: 23643.5 | G20: =F20/F19-1 -> -0.0031957098 | J20: df | K20: SS | L20: MS | M20: F | N20: Significance F
B21: May 4, 2026 | C21: 839.95 | D21: =C21/C20-1 -> 0.10041923 | F21: 24176.15 | G21: =F21/F20-1 -> 0.02252839 | I21: Regression | J21: 1 | K21: 0.11673657 | L21: 0.11673657 | M21: 44.716065 | N21: 1.2035817e-09
B22: Apr 27, 2026 | C22: 768.4 | D22: =C22/C21-1 -> -0.085183642 | F22: 23997.55 | G22: =F22/F21-1 -> -0.0073874459 | I22: Residual | J22: 103 | K22: 0.26889366 | L22: 0.0026106181
B23: Apr 20, 2026 | C23: 756.65 | D23: =C23/C22-1 -> -0.015291515 | F23: 23897.95 | G23: =F23/F22-1 -> -0.0041504237 | I23: Total | J23: 104 | K23: 0.38563023
B24: Apr 13, 2026 | C24: 741.05 | D24: =C24/C23-1 -> -0.020617194 | F24: 24353.55 | G24: =F24/F23-1 -> 0.019064397
B25: Apr 6, 2026 | C25: 710.25 | D25: =C25/C24-1 -> -0.041562648 | F25: 24050.6 | G25: =F25/F24-1 -> -0.012439665 | J25: Coefficients | K25: Standard Error | L25: t Stat | M25: P-value | N25: Lower 95% | O25: Upper 95% | P25: Lower 95.0% | Q25: Upper 95.0%
B26: Mar 30, 2026 | C26: 614.9 | D26: =C26/C25-1 -> -0.1342485 | F26: 22713.1 | G26: =F26/F25-1 -> -0.055611918 | I26: Intercept | J26: 0.0061577159 | K26: 0.004986325 | L26: 1.2349207 | M26: 0.21966972 | N26: -0.0037314838 | O26: 0.016046916 | P26: -0.0037314838 | Q26: 0.016046916
B27: Mar 23, 2026 | C27: 595.6 | D27: =C27/C26-1 -> -0.031387217 | F27: 22819.6 | G27: =F27/F26-1 -> 0.004688924 | I27: X Variable 1 | J27: 1.8002309 | K27: 0.26921324 | L27: 6.6870072 | M27: 1.2035817e-09 | N27: 1.2663099 | O27: 2.3341518 | P27: 1.2663099 | Q27: 2.3341518
B28: Mar 16, 2026 | C28: 626.35 | D28: =C28/C27-1 -> 0.05162861 | F28: 23114.5 | G28: =F28/F27-1 -> 0.012923101
B29: Mar 9, 2026 | C29: 639.4 | D29: =C29/C28-1 -> 0.020834996 | F29: 23151.1 | G29: =F29/F28-1 -> 0.0015834217
B30: Mar 2, 2026 | C30: 680.3 | D30: =C30/C29-1 -> 0.063966218 | F30: 24450.45 | G30: =F30/F29-1 -> 0.056124763
B31: Feb 23, 2026 | C31: 700.95 | D31: =C31/C30-1 -> 0.030354255 | F31: 25178.65 | G31: =F31/F30-1 -> 0.029782683
B32: Feb 16, 2026 | C32: 743.5 | D32: =C32/C31-1 -> 0.060703331 | F32: 25571.25 | G32: =F32/F31-1 -> 0.015592575
B33: Feb 9, 2026 | C33: 764.8 | D33: =C33/C32-1 -> 0.028648285 | F33: 25471.1 | G33: =F33/F32-1 -> -0.0039165078
B34: Feb 2, 2026 | C34: 781.5 | D34: =C34/C33-1 -> 0.021835774 | F34: 25693.7 | G34: =F34/F33-1 -> 0.0087393163
B35: Jan 26, 2026 | C35: 785.4 | D35: =C35/C34-1 -> 0.0049904031 | F35: 24825.45 | G35: =F35/F34-1 -> -0.03379233
B36: Jan 19, 2026 | C36: 786.55 | D36: =C36/C35-1 -> 0.0014642221 | F36: 25048.65 | G36: =F36/F35-1 -> 0.0089907736
B37: Jan 12, 2026 | C37: 805.9 | D37: =C37/C36-1 -> 0.024601106 | F37: 25694.35 | G37: =F37/F36-1 -> 0.025777836
B38: Jan 5, 2026 | C38: 803.8 | D38: =C38/C37-1 -> -0.0026057824 | F38: 25683.3 | G38: =F38/F37-1 -> -0.00043005563
B39: Dec 29, 2025 | C39: 890.35 | D39: =C39/C38-1 -> 0.10767604 | F39: 26328.55 | G39: =F39/F38-1 -> 0.025123329
... B112: Aug 5, 2024 | C112: 1346.36 | D112: =C112/C111-1 -> -0.055504111 | F112: 24367.5 | G112: =F112/F111-1 -> -0.0070758705

Sheet WACC
B2: Weighted Average Cost Of Capital
B3: All figures are in Rs. ( Crores) | C3: 2025
B5: Debt | C5: ='Assumptions ( Driver)'!E18 -> 529
B6: Equity | C6: =BS!F37 -> 2483
B7: Total Capital | C7: =C5+C6 -> 3012
B8: Weight
B9: % of Debt | C9: =C5/C7 -> 0.17563081
B10: % of Equity | C10: =C6/C7 -> 0.82436919
B12: Cost of Debt
B13: Interest rate | C13: ='Assumptions ( Driver)'!E19 -> 0.13827977
B14: Tax Rate | C14: ='Assumptions ( Driver)'!G22 -> 0.28142953
B15: After tax cost of debt | C15: =C13*(1-C14) -> 0.099363762
B17: Cost of Equity
B18: Risk free rate (Rf) | C18: 0.065
B19: Beta (B) | C19: =Beta!J27 -> 1.8002309
B20: Market Return (Rm) | C20: 0.09
B21: Cost of Equity | C21: =C18+(C19*(C20-C18)) -> 0.11000577
B23: WACC | C23: =C15*C9+C21*C10 -> 0.10813671

Sheet DCF
B2: Discounted Cash Flow Model
B3: All figures are in Rs. ( Crores)
B4: Financial Year | C4: 2025A | E4: 2026E | F4: 2027E | G4: 2028E | H4: 2029E | I4: 2030E
B5: Free Cash Flow | C5: - | E5: =CFS!F18+CFS!F20 -> 202.31467 | F5: =CFS!G18+CFS!G20 -> -81.008008 | G5: =CFS!H18+CFS!H20 -> -28.225074 | H5: =CFS!I18+CFS!I20 -> 107.3456 | I5: =CFS!J18+CFS!J20 -> 39.737607
B6: Projection Year | E6: 1 | F6: 2 | G6: 3 | H6: 4 | I6: 5
B7: PV of free cash flow | E7: =PV($C$9,E6,0,-E5) -> 182.57194 | F7: =PV($C$9,F6,0,-F5) -> -65.969208 | G7: =PV($C$9,G6,0,-G5) -> -20.742212 | H7: =PV($C$9,H6,0,-H5) -> 71.188668 | I7: =PV($C$9,I6,0,-I5) -> 23.781268
B9: Discount rate (WACC) | C9: =WACC!C23 -> 0.10813671
B10: Sum of PV of FCF | C10: =SUM(E7:H7) -> 167.04919 | F10: Sensitivity Analysis
F11: WACC
B12: Terminal Growth Rate (g) | C12: 0.04 | E12: Rate | F12: =C23 -> 88.269082 | G12: =H12-1% -> 0.088137 | H12: =I12-1% -> 0.098137 | I12: 0.108137 | J12: =I12+1% -> 0.118137 | K12: =J12+1% -> 0.128137
B13: Terminal Value | C13: =H5*(1+C12)/(C9-C12) -> 1638.4622 | F13: =F14-1% -> 0.02 | G13: 93.065934 | H13: 79.34609 | I13: 68.807928 | J13: 60.475676 | K13: 53.734662
B14: PV of TV | C14: =C13/(1+C9)^H6 -> 1086.5834 | F14: =F15-1% -> 0.03 | G14: 108.64581 | H14: 90.624325 | I14: 77.292992 | J14: 67.051867 | K14: 58.953308
F15: 0.04 | G15: 130.69883 | H15: 105.78244 | I15: 88.268645 | J15: 75.311303 | K15: 65.356166
B16: Enterprise Value (EV) | C16: =C10+C14 -> 1253.6326 | F16: =F15+1% -> 0.05 | G16: 164.31701 | H16: 127.23847 | I16: 103.02009 | J16: 85.995101 | K16: 73.397904
F17: =F16+1% -> 0.06 | G17: 221.83126 | H17: 159.94657 | I17: 123.90047 | J17: 100.35429 | K17: 83.800104
B18: Cash & Equivalent | C18: =BS!F10 -> 467
B19: Debt | C19: =-WACC!C5 -> -529
B21: Equity Value | C21: =C16+C18+C19 -> 1191.6326
B22: No. of Equity Shares | C22: 13.5
B23: Value per Share | C23: =C21/C22 -> 88.269082

Sheet Source Data

Sheet (IS)
C3: 42064 | D3: 42430 | E3: 42795 | F3: 43160 | G3: 43525 | H3: 43891 | I3: 44256 | J3: 44621 | K3: 44986 | L3: 45352 | M3: 45717 | O3: Report Date | P3: 42825 | Q3: 43190 | R3: 43555 | S3: 43921 | T3: 44286 | U3: 44651 | V3: 45016 | W3: 45382 | X3: 45747
B4: Sales - | C4: 761 | D4: 959 | E4: 1714 | F4: 1268 | G4: 1559 | H4: 1766 | I4: 1521 | J4: 1468 | K4: 2780 | L4: 3853 | M4: 3868 | O4: Sales | P4: 1713.6 | Q4: 1268.19 | R4: 1559.29 | S4: 1766.32 | T4: 1520.64 | U4: 1467.5 | V4: 2779.59 | W4: 3853.3 | X4: 3867.75
B5: Sales Growth % | C5: 0.2195 | D5: 0.2602 | E5: 0.7865 | F5: -0.2599 | G5: 0.2295 | H5: 0.1328 | I5: -0.1391 | J5: -0.0349 | K5: 0.8941 | L5: 0.3863 | M5: 0.0038 | O5: Raw Material Cost | P5: 915.2 | Q5: 692.4 | R5: 999.77 | S5: 1192.3 | T5: 1045.66 | U5: 1037.26 | V5: 2165.3 | W5: 2951.7 | X5: 2964.91
B6: Expenses - | C6: 721 | D6: 929 | E6: 1605 | F6: 1365 | G6: 1550 | H6: 1645 | I6: 1440 | J6: 1303 | K6: 2529 | L6: 3404 | M6: 3459 | O6: Change in Inventory | P6: -164.6 | Q6: -64.84 | R6: 63.95 | S6: 40.81 | T6: 52.24 | U6: -10.32 | V6: 15.37 | W6: -36.38 | X6: 36.06
B7: Material Cost % + | C7: 0.61 | D7: 0.58 | E7: 0.63 | F7: 0.6 | G7: 0.6 | H7: 0.65 | I7: 0.65 | J7: 0.71 | K7: 0.77 | L7: 0.78 | M7: 0.76 | O7: Power and Fuel | P7: 28.59 | Q7: 27.68 | R7: 35.04 | S7: 45.58 | T7: 34.22 | U7: 33.26 | V7: 43.7 | W7: 50.46 | X7: 59.54
B8: Manufacturing Cost % | C8: 0.13 | D8: 0.11 | E8: 0.1 | F8: 0.13 | G8: 0.14 | H8: 0.14 | I8: 0.1 | J8: 0.1 | K8: 0.08 | L8: 0.07 | M8: 0.08 | O8: Other Mfr. Exp | P8: 134.58 | Q8: 139.9 | R8: 185.36 | S8: 207.74 | T8: 111.41 | U8: 111.39 | V8: 188.99 | W8: 215.28 | X8: 260.58
B9: COGS % | K9: =K7+K8 -> 0.85 | L9: =L7+L8 -> 0.85 | M9: =M7+M8 -> 0.84 | O9: Employee Cost | P9: 212.84 | Q9: 239.78 | R9: 176.56 | S9: 152.11 | T9: 211.05 | U9: 46.19 | V9: 57.33 | W9: 67.74 | X9: 88.04
B10: Employee Cost % | C10: 0.1 | D10: 0.18 | E10: 0.12 | F10: 0.19 | G10: 0.11 | H10: 0.09 | I10: 0.14 | J10: 0.03 | K10: 0.02 | L10: 0.02 | M10: 0.02 | O10: Selling and admin | P10: 71.16 | Q10: 88.66 | R10: 107.61 | S10: 56.1 | T10: 55.04 | U10: 23.69 | V10: 29.79 | W10: 43.19 | X10: 49.25
B11: Other Cost % | C11: 0.11 | D11: 0.1 | E11: 0.09 | F11: 0.16 | G11: 0.14 | H11: 0.05 | I11: 0.06 | J11: 0.04 | K11: 0.03 | L11: 0.02 | M11: 0.03 | O11: Other Expenses | P11: 78.47 | Q11: 112 | R11: 110 | S11: 32.46 | T11: 34.87 | U11: 40.47 | V11: 59.08 | W11: 39.24 | X11: 72.37
K12: =K10+K11 -> 0.05 | L12: =L10+L11 -> 0.04 | M12: =M10+M11 -> 0.05 | O12: Other Income | P12: 24.37 | Q12: 24.79 | R12: 24.75 | S12: -60.09 | T12: 24.86 | U12: -60.76 | V12: 33.66 | W12: 37.52 | X12: 75.21
B13: Operating Profit | C13: 40 | D13: 30 | E13: 108 | F13: -97 | G13: 9 | H13: 121 | I13: 81 | J13: 165 | K13: 251 | L13: 449 | M13: 409 | O13: Depreciation | P13: 51.52 | Q13: 50.84 | R13: 23.99 | S13: 29.13 | T13: 29.87 | U13: 18.38 | V13: 22.5 | W13: 27.1 | X13: 29.58
B14: OPM % | C14: 0.05 | D14: 0.032 | E14: 0.06 | F14: -0.08 | G14: 0.006 | H14: 0.07 | I14: 0.05 | J14: 0.11 | K14: 0.09 | L14: 0.12 | M14: 0.11 | O14: Interest | P14: 31.31 | Q14: 44.06 | R14: 65.18 | S14: 88.27 | T14: 81.2 | U14: 57.27 | V14: 80.75 | W14: 73.45 | X14: 73.15
B15: Other Income - | C15: 0 | D15: 20 | E15: 24 | F15: 25 | G15: 25 | H15: -60 | I15: 25 | J15: -61 | K15: 34 | L15: 38 | M15: 75 | O15: Profit before tax | P15: 49.7 | Q15: -167.18 | R15: -55.52 | S15: -56.65 | T15: -5.58 | U15: 28.51 | V15: 181.18 | W15: 386.28 | X15: 381.6
B16: Exceptional items | C16: -28 | D16: -21 | E16: -5 | F16: -1 | G16: -8 | H16: -92 | I16: 1 | J16: -75 | K16: -9 | L16: -2 | M16: 0 | O16: Tax | P16: 22.26 | Q16: -19.95 | R16: -33 | S16: -20.51 | T16: 13.21 | U16: 29.19 | V16: 55.47 | W16: 100.14 | X16: 106.68
B17: Other income normal | C17: 28 | D17: 41 | E17: 29 | F17: 26 | G17: 33 | H17: 31 | I17: 24 | J17: 15 | K17: 42 | L17: 40 | M17: 75 | O17: Net profit | P17: 26.9 | Q17: -143.62 | R17: -28.52 | S17: -34.19 | T17: -15 | U17: -0.33 | V17: 130.2 | W17: 286.14 | X17: 276.39
B18: Interest | C18: 18 | D18: 17 | E18: 31 | F18: 44 | G18: 65 | H18: 88 | I18: 81 | J18: 57 | K18: 81 | L18: 73 | M18: 73 | O18: Dividend Amount | P18: 9.23 | Q18: 3.46 | R18: 3.47 | V18: 5.98 | W18: 10.77 | X18: 13.46
B19: Depreciation | C19: 26 | D19: 46 | E19: 52 | F19: 51 | G19: 24 | H19: 29 | I19: 30 | J19: 18 | K19: 22 | L19: 27 | M19: 30
B20: Profit before tax | C20: -4 | D20: -13 | E20: 50 | F20: -167 | G20: -56 | H20: -57 | I20: -6 | J20: 29 | K20: 181 | L20: 386 | M20: 382
B21: Tax % | C21: 1.77 | D21: 0.52 | E21: 0.45 | F21: -0.12 | G21: -0.59 | H21: -0.36 | I21: 2.37 | J21: 1.02 | K21: 0.31 | L21: 0.26 | M21: 0.28
B22: Net Profit + | C22: -10 | D22: -20 | E22: 27 | F22: -147 | G22: -23 | H22: -36 | I22: -19 | J22: -1 | K22: 126 | L22: 286 | M22: 275
B23: EPS in Rs | C23: -0.33 | D23: -1.69 | E23: 2.33 | F23: -12.43 | G23: -2.47 | H23: -2.96 | I23: -1.26 | J23: -0.03 | K23: 10.89 | L23: 21.25 | M23: 20.52
B24: Dividend Payout % | C24: -0.48 | D24: -0.47 | E24: 0.34 | F24: -0.02 | G24: -0.12 | H24: 0 | I24: 0 | J24: 0 | K24: 0.05 | L24: 0.04 | M24: 0.05

Sheet (BS)
C3: 42064 | D3: 42430 | E3: 42795 | F3: 43160 | G3: 43525 | H3: 43891 | I3: 44256 | J3: 44621 | K3: 44986 | L3: 45352 | M3: 45717
B4: Equity Capital | C4: 20 | D4: 23 | E4: 23 | F4: 23 | G4: 23 | H4: 23 | I4: 24 | J4: 24 | K4: 24 | L4: 27 | M4: 27
B5: Reserves | C5: 669 | D5: 930 | E5: 944 | F5: 832 | G5: 793 | H5: 743 | I5: 817 | J5: 818 | K5: 940 | L5: 2191 | M5: 2456
B6: Borrowings - | C6: 125 | D6: 233 | E6: 372 | F6: 624 | G6: 896 | H6: 730 | I6: 847 | J6: 920 | K6: 353 | L6: 166 | M6: 627
B7: Long term Borrowings | C7: 43 | D7: 164 | E7: 160 | F7: 187 | G7: 576 | H7: 553 | I7: 537 | J7: 496 | K7: 50 | L7: 37 | M7: 25
B8: Short term Borrowings | C8: 54 | D8: 52 | E8: 182 | F8: 389 | G8: 294 | H8: 175 | I8: 308 | J8: 365 | K8: 200 | L8: 29 | M8: 504
B9: Lease Liabilities | C9: 0 | D9: 0 | E9: 0 | F9: 0 | G9: 0 | H9: 0 | I9: 1 | J9: 59 | K9: 104 | L9: 99 | M9: 98
B10: Other Borrowings | C10: 29 | D10: 16 | E10: 30 | F10: 48 | G10: 26 | H10: 1 | I10: 0 | J10: 0 | K10: 0 | L10: 0 | M10: 0
B11: Other Liabilities - | C11: 246 | D11: 1493 | E11: 1356 | F11: 1210 | G11: 975 | H11: 775 | I11: 775 | J11: 903 | K11: 931 | L11: 832 | M11: 651
B12: Non controlling int | C12: 36 | D12: 79 | E12: 79 | F12: 64 | G12: 73 | H12: 79 | I12: 0 | J12: 0 | K12: 0 | L12: 0 | M12: 1
B13: Trade Payables | C13: 96 | D13: 378 | E13: 442 | F13: 306 | G13: 535 | H13: 351 | I13: 398 | J13: 439 | K13: 323 | L13: 319 | M13: 235
B14: Advance from Customers | C14: 23 | D14: 632 | E14: 526 | F14: 503 | G14: 160 | H14: 59 | I14: 97 | J14: 337 | K14: 536 | L14: 0 | M14: 0
B15: Other liability items | C15: 91 | D15: 404 | E15: 309 | F15: 338 | G15: 207 | H15: 286 | I15: 280 | J15: 127 | K15: 72 | L15: 513 | M15: 414
... B24: Railway sidings | C24: 4 | D24: 3 | E24: 3 | F24: 3 | G24: 4 | H24: 4 | I24: 11 | J24: 10 | K24: 12 | L24: 12 | M24: 9
B25: Vehicles | C25: 15 | D25: 2 | E25: 2 | F25: 2 | G25: 3 | H25: 3 | I25: 3 | J25: 3 | K25: 4 | L25: 5 | M25: 8 | N25: =SUM(K18:K26)-K29+K27 -> 731
B26: Intangible Assets | C26: 60 | D26: 28 | E26: 29 | F26: 36 | G26: 34 | H26: 2 | I26: 2 | J26: 2 | K26: 2 | L26: 2 | M26: 2
B27: Other fixed assets | C27: 14 | D27: 12 | E27: 37 | F27: 39 | G27: 67 | H27: 81 | I27: 78 | J27: 79 | K27: 40 | L27: 41 | M27: 110 | N27: =SUM(M18:M26)-M29+M27 -> 992
B28: Gross Block | C28: 596 | D28: 1022 | E28: 1025 | F28: 1117 | G28: 1151 | H28: 1038 | I28: 1062 | J28: 1187 | K28: 869 | L28: 913 | M28: 1153
B29: Accumulated Depreciation | C29: 181 | D29: 45 | E29: 92 | F29: 159 | G29: 216 | H29: 166 | I29: 190 | J29: 221 | K29: 137 | L29: 164 | M29: 161
B30: CWIP | C30: 27 | D30: 13 | E30: 15 | F30: 27 | G30: 36 | H30: 0 | I30: 41 | J30: 61 | K30: =12+2 -> 14 | L30: =174-3 -> 171 | M30: 122
B31: Investments | C31: 1 | D31: 21 | E31: 82 | F31: 83 | G31: 87 | H31: 29 | I31: 31 | J31: 30 | K31: 32 | L31: 198 | M31: 299
B32: Other Assets - | C32: 616 | D32: 1666 | E32: 1665 | F32: 1621 | G32: 1630 | H32: 1371 | I32: 1518 | J32: 1607 | K32: 1472 | L32: 2097 | M32: 2348
B33: Inventories | C33: 224 | D33: 716 | E33: 537 | F33: 442 | G33: 521 | H33: 376 | I33: 385 | J33: 504 | K33: 461 | L33: 524 | M33: 523
B34: Trade receivables + | C34: 113 | D34: 230 | E34: 234 | F34: 276 | G34: 344 | H34: 252 | I34: 567 | J34: 233 | K34: 279 | L34: 533 | M34: 671
B35: Cash Equivalents | C35: 147 | D35: 204 | E35: 46 | F35: 74 | G35: 119 | H35: 56 | I35: 124 | J35: 42 | K35: 100 | L35: 609 | M35: 467
B36: Loans n Advances | C36: 5 | D36: 9 | E36: 10 | F36: 108 | G36: 120 | H36: 8 | I36: 5 | J36: 16 | K36: 8 | L36: 9 | M36: 36
B37: Other asset items | C37: 127 | D37: 507 | E37: 837 | F37: 722 | G37: 525 | H37: 678 | I37: 437 | J37: 813 | K37: 623 | L37: 423 | M37: 650
B38: Total Assets | C38: 1060 | D38: 2678 | E38: 2695 | F38: 2689 | G38: 2687 | H38: 2272 | I38: 2462 | J38: 2664 | K38: 2248 | L38: 3216 | M38: 3761

Sheet (CF)
C2: 42064 | D2: 42430 | E2: 42795 | F2: 43160 | G2: 43525 | H2: 43891 | I2: 44256 | J2: 44621 | K2: 44986 | L2: 45352 | M2: 45717
B3: Cash from Operating Activity - | C3: 102 | D3: -154 | E3: -177 | F3: -121 | G3: -124 | H3: 154 | I3: 68 | J3: 55 | K3: 41 | L3: 86 | M3: -97
B4: Profit from operations | C4: 25 | D4: 15 | E4: 114 | F4: -56 | G4: 59 | H4: 152 | I4: 101 | J4: 201 | K4: 260 | L4: 476 | M4: 457
B5: Receivables | C5: 35 | D5: -119 | E5: -7 | F5: -47 | G5: -81 | H5: 44 | I5: -72 | J5: -53 | K5: -103 | L5: -261 | M5: -140
B6: Inventory | C6: 94 | D6: -117 | E6: 179 | F6: 96 | G6: -79 | H6: 74 | I6: -27 | J6: -142 | K6: -173 | L6: -78 | M6: 0
B7: Payables | C7: 12 | D7: 0 | E7: 0 | F7: 0 | G7: 0 | H7: 0 | I7: 0 | J7: 39 | K7: 129 | L7: -2 | M7: -86
B8: Loans Advances | C8: 7 | D8: -271 | E8: 0 | F8: 0 | G8: 0 | H8: 0 | I8: 0 | J8: 0 | K8: 0 | L8: 0 | M8: 0
B9: Other WC items | C9: -62 | D9: 339 | E9: -452 | F9: -94 | G9: -3 | H9: -106 | I9: 64 | J9: 20 | K9: -7 | L9: 52 | M9: -234
B10: Working capital changes | C10: 87 | D10: -168 | E10: -280 | F10: -45 | G10: -163 | H10: 12 | I10: -35 | J10: -135 | K10: -153 | L10: -289 | M10: -459
B11: Direct taxes | C11: -10 | D11: -1 | E11: -11 | F11: -20 | G11: -21 | H11: -10 | I11: 1 | J11: -12 | K11: -66 | L11: -101 | M11: -96
B12: Cash from Investing Activity - | C12: -25 | D12: -50 | E12: 44 | F12: -45 | G12: -49 | H12: 4 | I12: -60 | J12: -73 | K12: -61 | L12: -537 | M12: -579
B13: Fixed assets purchased | C13: -41 | D13: -22 | E13: -22 | F13: -37 | G13: -63 | H13: -36 | I13: -60 | J13: -102 | K13: -37 | L13: -164 | M13: -236
B14: Fixed assets sold | C14: 0 | D14: 0 | E14: 0 | F14: 9 | G14: 0 | H14: 11 | I14: 1 | J14: 6 | K14: 0 | L14: 0 | M14: 6
... B32: CFO/OP | C32: 2.8 | D32: -5.01 | E32: -1.54 | F32: 1.04 | G32: -11.61 | H32: 1.36 | I32: 0.82 | J32: 0.4 | K32: 0.43 | L32: 0.41 | M32: 0
