Workbook

Sheet Index
G3: Valuation Model of UltraTech Cement Ltd.
D11: Company Name | F11: UltraTech Cement Ltd. | G11: Blue | H11: Hard Coded Numbers
D12: Parent Organization | F12: Aditya Birla Group | G12: Black | H12: Formulas
D13: Headquarter | F13: Mumbai | G13: Green | H13: Link to other worksheets
D14: Founder | F14: Kumar Mangalam Birla | G14: Red | H14: External File Links
D17: Sheet No. | F17: Sheet Name | G17: Link to the Sheet
D18: 1 | F18: Index (this sheet) | G18: Index
D19: 2 | F19: Overview | G19: Overview
D20: 3 | F20: Comparative Company Analysis | G20: Comparative
D21: 4 | F21: Ratios | G21: Ratios
D22: 5 | F22: Drivers of the Model | G22: Drivers
D23: 6 | F23: Income Statement | G23: P&L
D24: 7 | F24: Balance Sheet | G24: Balance Sheet
D25: 8 | F25: Cash Flow Statement | G25: Cash Flow
D26: 9 | F26: Property, Plant & Equipments | G26: PPE
D27: 10 | F27: Working Capital | G27: WC
D28: 11 | F28: Weighted Average Cost of Capital | G28: WACC
D29: 12 | F29: Discounted Cash Flow Model | G29: DCF
... D32: 15 | F32: Cash Flow Statement (Source) | G32: (CFS)

Sheet Dashboard

Sheet Overview
B2: Overview
C5: Company Data | H5: Financial Snapshot (Rs. Cr) | I5: 2024 | J5: 2025 | K5: 2026 | L5: 2027 | P5: Ratios | Q5: 2024 | R5: 2025 | S5: 2026 | T5: 2027
C6: Market Cap (Rs. Cr) | D6: =Comparative!D6 -> 341088.21 | H6: Sales | I6: ='P&L'!G5 -> 70908.14 | J6: ='P&L'!H5 -> 82749.799 | K6: ='P&L'!I5 -> 96569.016 | L6: ='P&L'!J5 -> 111730.35 | P6: EBITDAM (%) | Q6: 0.19 | R6: 0.23 | S6: 0.23 | T6: 0.22
C7: Outstanding Shares (Cr) | D7: =Comparative!O25 -> 29.467919 | H7: EBITDA | I7: ='P&L'!G13 -> 13535.52 | J7: ='P&L'!H13 -> 18672.221 | K7: ='P&L'!I13 -> 21823.313 | L7: ='P&L'!J13 -> 24989.081 | P7: NPM (%) | Q7: 0.1 | R7: 0.13 | S7: 0.13 | T7: 0.13
C8: Current Market Price | D8: =D6/D7 -> 11574.9 | H8: PAT | I8: ='P&L'!G19 -> 7003.96 | J8: ='P&L'!H19 -> 10691.038 | K8: ='P&L'!I19 -> 12884.871 | L8: ='P&L'!J19 -> 15022.942 | P8: Debt:Equity (x) | Q8: 0.09 | R8: 0.08 | S8: 0.07 | T8: 0.06
C9: 52 Week High - Low (Rs) | D9: 13,110 / 10,325 | H9: EPS | P9: RoE (%) | Q9: 0.12 | R9: 0.16 | S9: 0.16 | T9: 0.17
C10: Enterprise Value (Rs. Cr) | D10: =Comparative!I6 -> 363458.95 | P10: RoCE (%) | Q10: 0.16 | R10: 0.2 | S10: 0.22 | T10: 0.22
C11: Book Valua (Rs. Cr) | D11: 2600 | P11: P/E (x) | Q11: 43.6 | R11: 29.5 | S11: 24.5 | T11: 21
C12: Beta | D12: 0.56 | P12: P/BV (x) | Q12: 5.1 | R12: 4.6 | S12: 4 | T12: 3.5
C13: Face Value (Rs) | D13: 10 | H13: Share Price Movement (Nifty Vs UltaTech | P13: EV/EBITDA (x) | Q13: 24 | R13: 17.4 | S13: 14.9 | T13: 13
P16: Shareholders Pattern
C17: Product Segments
C18: Segment | D18: Share
C19: Grey Cement - Domestic | D19: 0.8
C20: Ready-Mix Concrete | D20: 0.09
C21: Overseas Business | D21: 0.05
C22: White Cement | D22: 0.03
C23: Other | D23: 0.02
P30: Promoters | Q30: 0.5999
P31: Flls | Q31: 0.1795
P32: Dlls | Q32: 0.1408
P33: Public | Q33: 0.0798

Sheet Comparative
B2: Comparable Companies Analysis | Q2: Index
B3: All figures in Rs. Crore (Unless Specified)
C4: Market Data | K4: Financials | O4: Valuation
B5: Company | C5: Share Price (Rs./Share) | D5: Equity Value (Market Cap) | E5: No of Share Outstanding | F5: Debt | G5: Cash Equi | H5: Net Debt | I5: Enterprise Value | K5: Revenue | L5: EBITDA | M5: Net Income | O5: EV/Revenue | P5: EV/EBITDA | Q5: P/E
B6: UltraTech Cem. | C6: 11574.9 | D6: 341088.21 | E6: =D6/C6 -> 29.467919 | F6: 23755.09 | G6: 1384.35 | H6: =F6-G6 -> 22370.74 | I6: =D6+H6 -> 363458.95 | K6: 88511.53 | L6: 17581.91 | M6: 8188.35 | O6: =I6/K6 -> 4.1063458 | P6: =I6/L6 -> 20.672325 | Q6: =D6/M6 -> 41.655304
B7: Grasim Inds | C7: 3147.7 | D7: 214208.08 | E7: =D7/C7 -> 68.052254 | F7: 227853.06 | G7: 6188.26 | H7: =F7-G7 -> 221664.8 | I7: =D7+H7 -> 435872.88 | K7: 175430.74 | L7: 37665.48 | M7: 10300.29 | O7: =I7/K7 -> 2.4845867 | P7: =I7/L7 -> 11.572211 | Q7: =D7/M7 -> 20.796315
B8: Ambuja Cements | C8: 436.35 | D8: 108425.03 | E8: =D8/C8 -> 248.48179 | F8: 865.93 | G8: 958.6 | H8: =F8-G8 -> -92.67 | I8: =D8+H8 -> 108332.36 | K8: 40655.68 | L8: 7393.33 | M8: 5637.08 | O8: =I8/K8 -> 2.6646304 | P8: =I8/L8 -> 14.652715 | Q8: =D8/M8 -> 19.234254
B9: Shree Cement | C9: 24751 | D9: 89303.45 | E9: =D9/C9 -> 3.6080744 | F9: 1868.14 | G9: 341.79 | H9: =F9-G9 -> 1526.35 | I9: =D9+H9 -> 90829.8 | K9: 20943.47 | L9: 5298.69 | M9: 1748.66 | O9: =I9/K9 -> 4.3369031 | P9: =I9/L9 -> 17.141935 | Q9: =D9/M9 -> 51.069648
B10: J K Cements | C10: 5553 | D10: 42907.06 | E10: =D10/C10 -> 7.7268251 | F10: 6509.83 | G10: 1369.67 | H10: =F10-G10 -> 5140.16 | I10: =D10+H10 -> 48047.22 | K10: 11879.15 | L10: 2206.87 | M10: 872.17 | O10: =I10/K10 -> 4.0446682 | P10: =I10/L10 -> 21.771659 | Q10: =D10/M10 -> 49.195753
B11: Dalmia BharatLtd | C11: 1789.5 | D11: 33564.85 | E11: =D11/C11 -> 18.756552 | F11: 7406 | G11: 224 | H11: =F11-G11 -> 7182 | I11: =D11+H11 -> 40746.85 | K11: 14804 | L11: 3305 | M11: 1157 | O11: =I11/K11 -> 2.7524216 | P11: =I11/L11 -> 12.32885 | Q11: =D11/M11 -> 29.010242
B12: ACC | C12: 1359 | D12: 25520.28 | E12: =D12/C12 -> 18.77872 | F12: 428.61 | G12: 557.73 | H12: =F12-G12 -> -129.12 | I12: =D12+H12 -> 25391.16 | K12: 25961.85 | L12: 3358.99 | M12: 2137.23 | O12: =I12/K12 -> 0.97801813 | P12: =I12/L12 -> 7.5591651 | Q12: =D12/M12 -> 11.940821
B14: High | O14: =MAX(O7:O12) -> 4.3369031 | P14: =MAX(P7:P12) -> 21.771659 | Q14: =MAX(Q7:Q12) -> 51.069648
B15: 75th Percentile | O15: =QUARTILE(O7:O12,3) -> 3.7216065 | P15: =QUARTILE(P7:P12,3) -> 16.51963 | Q15: =QUARTILE(Q7:Q12,3) -> 44.149375
B16: Average | O16: =AVERAGE(O7:O12) -> 2.8768714 | P16: =AVERAGE(P7:P12) -> 14.171089 | Q16: =AVERAGE(Q7:Q12) -> 30.207839
B17: Median | O17: =MEDIAN(O7:O12) -> 2.708526 | P17: =MEDIAN(P7:P12) -> 13.490783 | Q17: =MEDIAN(Q7:Q12) -> 24.903279
B18: 25th Percentile | O18: =QUARTILE(O7:O12,1) -> 2.5295976 | P18: =QUARTILE(P7:P12,1) -> 11.761371 | Q18: =QUARTILE(Q7:Q12,1) -> 19.62477
B19: Low | O19: =MIN(O7:O12) -> 0.97801813 | P19: =MIN(P7:P12) -> 7.5591651 | Q19: =MIN(Q7:Q12) -> 11.940821
B21: Enjoy Lemon Valuation | O21: EV/Revenue | P21: EV/EBITDA | Q21: P/E
B22: Implied Enterprise Value | O22: =O16*K6 -> 254636.29 | P22: =P16*L6 -> 249154.81 | Q22: =Q24+Q23 -> 226287.5
B23: Net Debt | O23: =H6 -> 22370.74 | P23: =O23 -> 22370.74 | Q23: =P23 -> 22370.74
B24: Implied Market Value | O24: =O22-O23 -> 232265.55 | P24: =P22-P23 -> 226784.07 | Q24: =Q17*M6 -> 203916.76
B25: Shares Outstanding | O25: =E6 -> 29.467919 | P25: =O25 -> 29.467919 | Q25: =P25 -> 29.467919
B26: Implied Value Per Share | O26: =O24/O25 -> 7881.98 | P26: =P24/P25 -> 7695.9652 | Q26: =Q24/Q25 -> 6919.9581

Sheet Sheet1
B2: S.No. | C2: Name | D2: CMP Rs. | E2: Debt Rs.Cr. | F2: Cash End Rs.Cr. | G2: Sales Ann Rs.Cr. | H2: EBIDT Ann Rs.Cr. | I2: Mar Cap Rs.Cr. | J2: NP Ann Rs.Cr.
B3: 1 | C3: UltraTech Cem. | D3: 11574.9 | E3: 23755.09 | F3: 1384.35 | G3: 88511.53 | H3: 17581.91 | I3: 341088.21 | J3: 8188.35
B4: 2 | C4: Grasim Inds | D4: 3147.7 | E4: 227853.06 | F4: 6188.26 | G4: 175430.74 | H4: 37665.48 | I4: 214208.08 | J4: 10300.29
B5: 3 | C5: Ambuja Cements | D5: 436.35 | E5: 865.93 | F5: 958.6 | G5: 40655.68 | H5: 7393.33 | I5: 108425.03 | J5: 5637.08
B6: 4 | C6: Shree Cement | D6: 24751 | E6: 1868.14 | F6: 341.79 | G6: 20943.47 | H6: 5298.69 | I6: 89303.45 | J6: 1748.66
B7: 5 | C7: J K Cements | D7: 5553 | E7: 6509.83 | F7: 1369.67 | G7: 11879.15 | H7: 2206.87 | I7: 42907.06 | J7: 872.17
B8: 6 | C8: Dalmia BharatLtd | D8: 1789.5 | E8: 7406 | F8: 224 | G8: 14804 | H8: 3305 | I8: 33564.85 | J8: 1157
B9: 7 | C9: ACC | D9: 1359 | E9: 428.61 | F9: 557.73 | G9: 25961.85 | H9: 3358.99 | I9: 25520.28 | J9: 2137.23

Sheet Ratios
O1: Index
B2: Ratios
B3: Ratios | C3: 2020 | D3: 2021 | E3: 2022 | F3: 2023 | G3: 2024 | H3: 2025 | I3: 2026 | J3: 2027 | K3: 2028 | L3: 2029 | M3: Trend | N3: Mean | O3: Median
B4: Sales Growth (%) | C4: - | D4: ='P&L'!D5/'P&L'!C5-1 -> 0.054110675 | E4: ='P&L'!E5/'P&L'!D5-1 -> 0.17602882 | F4: ='P&L'!F5/'P&L'!E5-1 -> 0.20230773 | G4: ='P&L'!G5/'P&L'!F5-1 -> 0.12125494 | H4: ='P&L'!H5/'P&L'!G5-1 -> 0.167 | I4: ='P&L'!I5/'P&L'!H5-1 -> 0.167 | J4: ='P&L'!J5/'P&L'!I5-1 -> 0.157 | K4: ='P&L'!K5/'P&L'!J5-1 -> 0.147 | L4: ='P&L'!L5/'P&L'!K5-1 -> 0.137 | N4: =AVERAGE(C4:L4) -> 0.14763357 | O4: =MEDIAN(C4:L4) -> 0.157
B5: EBITDA Growth (%) | C5: - | D5: ='P&L'!D13/'P&L'!C13-1 -> 0.23132192 | E5: ='P&L'!E13/'P&L'!D13-1 -> -0.00021745499 | F5: ='P&L'!F13/'P&L'!E13-1 -> -0.086739912 | G5: ='P&L'!G13/'P&L'!F13-1 -> 0.21646164 | H5: ='P&L'!H13/'P&L'!G13-1 -> 0.37949786 | I5: ='P&L'!I13/'P&L'!H13-1 -> 0.16875827 | J5: ='P&L'!J13/'P&L'!I13-1 -> 0.14506359 | K5: ='P&L'!K13/'P&L'!J13-1 -> 0.12010874 | L5: ='P&L'!L13/'P&L'!K13-1 -> 0.095248714 | N5: =AVERAGE(C5:L5) -> 0.14105593 | O5: =MEDIAN(C5:L5) -> 0.14506359
B6: EBIT Growth (%) | C6: - | D6: ='P&L'!D15/'P&L'!C15-1 -> 0.32223457 | E6: ='P&L'!E15/'P&L'!D15-1 -> -0.0018099977 | F6: ='P&L'!F15/'P&L'!E15-1 -> -0.12990349 | G6: ='P&L'!G15/'P&L'!F15-1 -> 0.26110667 | H6: ='P&L'!H15/'P&L'!G15-1 -> 0.459161 | I6: ='P&L'!I15/'P&L'!H15-1 -> 0.19330273 | J6: ='P&L'!J15/'P&L'!I15-1 -> 0.15748369 | K6: ='P&L'!K15/'P&L'!J15-1 -> 0.12606618 | L6: ='P&L'!L15/'P&L'!K15-1 -> 0.096780125 | N6: =AVERAGE(C6:L6) -> 0.16493572 | O6: =MEDIAN(C6:L6) -> 0.15748369
B7: PAT Growth (%) | C7: - | D7: ='P&L'!D19/'P&L'!C19-1 -> -0.050258395 | E7: ='P&L'!E19/'P&L'!D19-1 -> 0.34281608 | F7: ='P&L'!F19/'P&L'!E19-1 -> -0.30826014 | G7: ='P&L'!G19/'P&L'!F19-1 -> 0.38052588 | H7: ='P&L'!H19/'P&L'!G19-1 -> 0.52642762 | I7: ='P&L'!I19/'P&L'!H19-1 -> 0.20520301 | J7: ='P&L'!J19/'P&L'!I19-1 -> 0.16593651 | K7: ='P&L'!K19/'P&L'!J19-1 -> 0.13214073 | L7: ='P&L'!L19/'P&L'!K19-1 -> 0.099878056 | N7: =AVERAGE(C7:L7) -> 0.16604549 | O7: =MEDIAN(C7:L7) -> 0.16593651
B9: Gross Margin (%) | C9: ='P&L'!C7/'P&L'!C5 -> 0.77465508 | D9: ='P&L'!D7/'P&L'!D5 -> 0.77299031 | E9: ='P&L'!E7/'P&L'!E5 -> 0.77462122 | F9: ='P&L'!F7/'P&L'!F5 -> 0.77768336 | G9: ='P&L'!G7/'P&L'!G5 -> 0.76305837 | H9: ='P&L'!H7/'P&L'!H5 -> 0.77260167 | I9: ='P&L'!I7/'P&L'!I5 -> 0.77260167 | J9: ='P&L'!J7/'P&L'!J5 -> 0.77260167 | ... L9: ='P&L'!L7/'P&L'!L5 -> 0.77260167 | N9: =AVERAGE(C9:L9) -> 0.77260167 | O9: =MEDIAN(C9:L9) -> 0.77260167
B10: EBITDA Margin (%) | C10: ='P&L'!C13/'P&L'!C5 -> 0.23325608 | D10: ='P&L'!D13/'P&L'!D5 -> 0.2724698 | E10: ='P&L'!E13/'P&L'!E5 -> 0.23163595 | F10: ='P&L'!F13/'P&L'!F5 -> 0.17594819 | G10: ='P&L'!G13/'P&L'!G5 -> 0.1908881 | H10: ='P&L'!H13/'P&L'!H5 -> 0.22564672 | I10: ='P&L'!I13/'P&L'!I5 -> 0.22598669 | J10: ='P&L'!J13/'P&L'!J5 -> 0.22365526 | ... L10: ='P&L'!L13/'P&L'!L5 -> 0.21039149 | N10: =AVERAGE(C10:L10) -> 0.220829 | O10: =MEDIAN(C10:L10) -> 0.22465099
B11: EBIT Margin (%) | C11: ='P&L'!C15/'P&L'!C5 -> 0.16908764 | D11: ='P&L'!D15/'P&L'!D5 -> 0.21209682 | E11: ='P&L'!E15/'P&L'!E5 -> 0.18002359 | F11: ='P&L'!F15/'P&L'!F5 -> 0.13028103 | G11: ='P&L'!G15/'P&L'!G5 -> 0.14653071 | H11: ='P&L'!H15/'P&L'!H5 -> 0.18321499 | I11: ='P&L'!I15/'P&L'!I5 -> 0.18734443 | J11: ='P&L'!J15/'P&L'!J5 -> 0.18742275 | ... L11: ='P&L'!L15/'P&L'!L5 -> 0.17749328 | N11: =AVERAGE(C11:L11) -> 0.17574973 | O11: =MEDIAN(C11:L11) -> 0.18161929
B12: EBT Margin (%) | C12: ='P&L'!C17/'P&L'!C5 -> 0.12214785 | D12: ='P&L'!D17/'P&L'!D5 -> 0.17887998 | E12: ='P&L'!E17/'P&L'!E5 -> 0.16206292 | F12: ='P&L'!F17/'P&L'!F5 -> 0.11727154 | G12: ='P&L'!G17/'P&L'!G5 -> 0.13287924 | H12: ='P&L'!H17/'P&L'!H5 -> 0.17226286 | I12: ='P&L'!I17/'P&L'!I5 -> 0.17790208 | J12: ='P&L'!J17/'P&L'!J5 -> 0.17927617 | ... L12: ='P&L'!L17/'P&L'!L5 -> 0.1711763 | N12: =AVERAGE(C12:L12) -> 0.15908126 | O12: =MEDIAN(C12:L12) -> 0.17171958
B13: Net Profit Margin (%) | C13: ='P&L'!C19/'P&L'!C5 -> 0.13553841 | D13: ='P&L'!D19/'P&L'!D5 -> 0.12211855 | E13: ='P&L'!E19/'P&L'!E5 -> 0.1394377 | F13: ='P&L'!F19/'P&L'!F5 -> 0.080224567 | G13: ='P&L'!G19/'P&L'!G5 -> 0.098775119 | H13: ='P&L'!H19/'P&L'!H5 -> 0.12919715 | I13: ='P&L'!I19/'P&L'!I5 -> 0.13342656 | J13: ='P&L'!J19/'P&L'!J5 -> 0.13445713 | ... L13: ='P&L'!L19/'P&L'!L5 -> 0.12838222 | N13: =AVERAGE(C13:L13) -> 0.12342727 | O13: =MEDIAN(C13:L13) -> 0.1309562
B15: ROA (%) | C15: ='P&L'!C19/'Balance Sheet'!C19 -> 0.072597455 | D15: ='P&L'!D19/'Balance Sheet'!D19 -> 0.063380175 | E15: ='P&L'!E19/'Balance Sheet'!E19 -> 0.087507427 | F15: ='P&L'!F19/'Balance Sheet'!F19 -> 0.055520415 | G15: ='P&L'!G19/'Balance Sheet'!G19 -> 0.069485798 | H15: ='P&L'!H19/'Balance Sheet'!H19 -> 0.097426113 | I15: ='P&L'!I19/'Balance Sheet'!I19 -> 0.10595894 | J15: ='P&L'!J19/'Balance Sheet'!J19 -> 0.11169242 | ... L15: ='P&L'!L19/'Balance Sheet'!L19 -> 0.11274049 | N15: =AVERAGE(C15:L15) -> 0.089019002 | O15: =MEDIAN(C15:L15) -> 0.09246677
B16: ROE (%) | C16: ='P&L'!C19/'Balance Sheet'!C36 -> 0.14725457 | D16: ='P&L'!D19/'Balance Sheet'!D36 -> 0.12362441 | E16: ='P&L'!E19/'Balance Sheet'!E36 -> 0.14542581 | F16: ='P&L'!F19/'Balance Sheet'!F36 -> 0.093295329 | G16: ='P&L'!G19/'Balance Sheet'!G36 -> 0.11618274 | H16: ='P&L'!H19/'Balance Sheet'!H36 -> 0.15561111 | I16: ='P&L'!I19/'Balance Sheet'!I36 -> 0.16352121 | J16: ='P&L'!J19/'Balance Sheet'!J36 -> 0.16634543 | ... L16: ='P&L'!L19/'Balance Sheet'!L36 -> 0.15884038 | N16: =AVERAGE(C16:L16) -> 0.14347876 | O16: =MEDIAN(C16:L16) -> 0.15143284
B17: ROCE (%) | C17: ='P&L'!C15/('Balance Sheet'!C36+'Balance Sheet'!C27) -> 0.12715554 | D17: ='P&L'!D15/('Balance Sheet'!D36+'Balance Sheet'!D27) -> 0.16432296 | E17: ='P&L'!E15/('Balance Sheet'!E36+'Balance Sheet'!E27) -> 0.16989073 | F17: ='P&L'!F15/('Balance Sheet'!F36+'Balance Sheet'!F27) -> 0.13792303 | G17: ='P&L'!G15/('Balance Sheet'!G36+'Balance Sheet'!G27) -> 0.15840682 | H17: ='P&L'!H15/('Balance Sheet'!H36+'Balance Sheet'!H27) -> 0.20480675 | I17: ='P&L'!I15/('Balance Sheet'!I36+'Balance Sheet'!I27) -> 0.21505669 | J17: ='P&L'!J15/('Balance Sheet'!J36+'Balance Sheet'!J27) -> 0.21897415 | ... L17: ='P&L'!L15/('Balance Sheet'!L36+'Balance Sheet'!L27) -> 0.21010472 | N17: =AVERAGE(C17:L17) -> 0.18237772 | O17: =MEDIAN(C17:L17) -> 0.18734874
B19: Debt Equity Ratio (x) | C19: ='Balance Sheet'!C27/'Balance Sheet'!C36 -> 0.44471757 | D19: ='Balance Sheet'!D27/'Balance Sheet'!D36 -> 0.30664765 | E19: ='Balance Sheet'!E27/'Balance Sheet'!E36 -> 0.10514941 | F19: ='Balance Sheet'!F27/'Balance Sheet'!F36 -> 0.098492093 | G19: ='Balance Sheet'!G27/'Balance Sheet'!G36 -> 0.088049897 | H19: ='Balance Sheet'!H27/'Balance Sheet'!H36 -> 0.077468079 | I19: ='Balance Sheet'!I27/'Balance Sheet'!I36 -> 0.067627233 | J19: ='Balance Sheet'!J27/'Balance Sheet'!J36 -> 0.058903801 | ... L19: ='Balance Sheet'!L27/'Balance Sheet'!L36 -> 0.045206551 | N19: =AVERAGE(C19:L19) -> 0.13438099 | O19: =MEDIAN(C19:L19) -> 0.082758988
B20: Interest Coverage Ratio (x) | C20: ='P&L'!C15/'P&L'!C16 -> 3.6022243 | D20: ='P&L'!D15/'P&L'!D16 -> 6.3852186 | E20: ='P&L'!E15/'P&L'!E16 -> 10.023213 | F20: ='P&L'!F15/'P&L'!F16 -> 10.014306 | G20: ='P&L'!G15/'P&L'!G16 -> 10.733698 | H20: ='P&L'!H15/'P&L'!H16 -> 16.728711 | I20: ='P&L'!I15/'P&L'!I16 -> 19.840859 | J20: ='P&L'!J15/'P&L'!J16 -> 23.006303 | ... L20: ='P&L'!L15/'P&L'!L16 -> 28.097808 | N20: =AVERAGE(C20:L20) -> 15.453769 | O20: =MEDIAN(C20:L20) -> 13.731205
B22: Current Ratio (x) | C22: ='Balance Sheet'!C10/'Balance Sheet'!C25 -> 0.71598663 | D22: ='Balance Sheet'!D10/'Balance Sheet'!D25 -> 0.62098108 | E22: ='Balance Sheet'!E10/'Balance Sheet'!E25 -> 0.63763389 | F22: ='Balance Sheet'!F10/'Balance Sheet'!F25 -> 0.67129174 | G22: ='Balance Sheet'!G10/'Balance Sheet'!G25 -> 0.67031259 | H22: ='Balance Sheet'!H10/'Balance Sheet'!H25 -> 0.78243597 | I22: ='Balance Sheet'!I10/'Balance Sheet'!I25 -> 0.90160237 | J22: ='Balance Sheet'!J10/'Balance Sheet'!J25 -> 1.0149752 | ... L22: ='Balance Sheet'!L10/'Balance Sheet'!L25 -> 1.3065943 | N22: =AVERAGE(C22:L22) -> 0.8474487 | O22: =MEDIAN(C22:L22) -> 0.7492113
B23: Quick Ratio (x) | C23: =('Balance Sheet'!C10-'Balance Sheet'!C5)/'Balance Sheet'!C25 -> 0.51913031 | D23: =('Balance Sheet'!D10-'Balance Sheet'!D5)/'Balance Sheet'!D25 -> 0.47334191 | E23: =('Balance Sheet'!E10-'Balance Sheet'!E5)/'Balance Sheet'!E25 -> 0.43022868 | F23: =('Balance Sheet'!F10-'Balance Sheet'!F5)/'Balance Sheet'!F25 -> 0.4544053 | G23: =('Balance Sheet'!G10-'Balance Sheet'!G5)/'Balance Sheet'!G25 -> 0.42604539 | H23: =('Balance Sheet'!H10-'Balance Sheet'!H5)/'Balance Sheet'!H25 -> 0.53542161 | I23: =('Balance Sheet'!I10-'Balance Sheet'!I5)/'Balance Sheet'!I25 -> 0.62735157 | J23: =('Balance Sheet'!J10-'Balance Sheet'!J5)/'Balance Sheet'!J25 -> 0.70937844 | ... L23: =('Balance Sheet'!L10-'Balance Sheet'!L5)/'Balance Sheet'!L25 -> 0.94588844 | N23: =AVERAGE(C23:L23) -> 0.59399618 | O23: =MEDIAN(C23:L23) -> 0.52727596
B24: Cash Ratio (x) | C24: ='Balance Sheet'!C7/'Balance Sheet'!C25 -> 0.025412961 | D24: ='Balance Sheet'!D7/'Balance Sheet'!D25 -> 0.07378284 | E24: ='Balance Sheet'!E7/'Balance Sheet'!E25 -> 0.01330566 | F24: ='Balance Sheet'!F7/'Balance Sheet'!F25 -> 0.037722233 | G24: ='Balance Sheet'!G7/'Balance Sheet'!G25 -> 0.02296053 | H24: ='Balance Sheet'!H7/'Balance Sheet'!H25 -> 0.13399739 | I24: ='Balance Sheet'!I7/'Balance Sheet'!I25 -> 0.21486084 | J24: ='Balance Sheet'!J7/'Balance Sheet'!J25 -> 0.28131973 | ... L24: ='Balance Sheet'!L7/'Balance Sheet'!L25 -> 0.49490652 | N24: =AVERAGE(C24:L24) -> 0.16756933 | O24: =MEDIAN(C24:L24) -> 0.10389012
B26: Debtor Turnover Ratio (x) | C26: - | D26: ='P&L'!D5/AVERAGE('Balance Sheet'!C6:D6) -> 18.052795 | E26: ='P&L'!E5/AVERAGE('Balance Sheet'!D6:E6) -> 18.638848 | F26: ='P&L'!F5/AVERAGE('Balance Sheet'!E6:F6) -> 18.227405 | G26: ='P&L'!G5/AVERAGE('Balance Sheet'!F6:G6) -> 17.411452 | H26: ='P&L'!H5/AVERAGE('Balance Sheet'!G6:H6) -> 18.114525 | I26: ='P&L'!I5/AVERAGE('Balance Sheet'!H6:I6) -> 18.345317 | J26: ='P&L'!J5/AVERAGE('Balance Sheet'!I6:J6) -> 18.272437 | K26: ='P&L'!K5/AVERAGE('Balance Sheet'!J6:K6) -> 18.198879 | L26: ='P&L'!L5/AVERAGE('Balance Sheet'!K6:L6) -> 18.124632 | N26: =AVERAGE(C26:L26) -> 18.154032 | O26: =MEDIAN(C26:L26) -> 18.198879
B27: Creditor Turnover Ratio (x) | C27: - | D27: ='P&L'!D6/AVERAGE('Balance Sheet'!C21:D21) -> 2.5668537 | E27: ='P&L'!E6/AVERAGE('Balance Sheet'!D21:E21) -> 2.2773336 | F27: ='P&L'!F6/AVERAGE('Balance Sheet'!E21:F21) -> 2.1510557 | G27: ='P&L'!G6/AVERAGE('Balance Sheet'!F21:G21) -> 2.1420399 | H27: ='P&L'!H6/AVERAGE('Balance Sheet'!G21:H21) -> 2.1908988 | I27: ='P&L'!I6/AVERAGE('Balance Sheet'!H21:I21) -> 2.3296895 | J27: ='P&L'!J6/AVERAGE('Balance Sheet'!I21:J21) -> 2.3204345 | K27: ='P&L'!K6/AVERAGE('Balance Sheet'!J21:K21) -> 2.3110933 | L27: ='P&L'!L6/AVERAGE('Balance Sheet'!K21:L21) -> 2.3016646 | N27: =AVERAGE(C27:L27) -> 2.287896 | O27: =MEDIAN(C27:L27) -> 2.3016646
B28: Inventory Turnover (x) | C28: - | D28: ='P&L'!D6/AVERAGE('Balance Sheet'!C5:D5) -> 2.4760858 | E28: ='P&L'!E6/AVERAGE('Balance Sheet'!D5:E5) -> 2.4661244 | F28: ='P&L'!F6/AVERAGE('Balance Sheet'!E5:F5) -> 2.3032929 | G28: ='P&L'!G6/AVERAGE('Balance Sheet'!F5:G5) -> 2.2488409 | H28: ='P&L'!H6/AVERAGE('Balance Sheet'!G5:H5) -> 2.2297649 | I28: ='P&L'!I6/AVERAGE('Balance Sheet'!H5:I5) -> 2.3709557 | J28: ='P&L'!J6/AVERAGE('Balance Sheet'!I5:J5) -> 2.3615367 | K28: ='P&L'!K6/AVERAGE('Balance Sheet'!J5:K5) -> 2.35203 | L28: ='P&L'!L6/AVERAGE('Balance Sheet'!K5:L5) -> 2.3424344 | N28: =AVERAGE(C28:L28) -> 2.3501184 | O28: =MEDIAN(C28:L28) -> 2.35203
B29: Fixed Asset Turnover (x) | C29: - | D29: ='P&L'!D5/AVERAGE(PPE!C8:D8) -> 0.82358097 | E29: ='P&L'!E5/AVERAGE(PPE!D8:E8) -> 0.94028906 | F29: ='P&L'!F5/AVERAGE(PPE!E8:F8) -> 1.0454099 | G29: ='P&L'!G5/AVERAGE(PPE!F8:G8) -> 1.0589706 | H29: ='P&L'!H5/AVERAGE(PPE!G8:H8) -> 1.1405926 | I29: ='P&L'!I5/AVERAGE(PPE!H8:I8) -> 1.2373333 | J29: ='P&L'!J5/AVERAGE(PPE!I8:J8) -> 1.3168911 | K29: ='P&L'!K5/AVERAGE(PPE!J8:K8) -> 1.3878331 | L29: ='P&L'!L5/AVERAGE(PPE!K8:L8) -> 1.4560621 | N29: =AVERAGE(C29:L29) -> 1.1563292 | O29: =MEDIAN(C29:L29) -> 1.1405926
B30: Capital Turnover Ratio (x) | C30: ='P&L'!C5/('Balance Sheet'!C36+'Balance Sheet'!C27) -> 0.75200968 | D30: ='P&L'!D5/('Balance Sheet'!D36+'Balance Sheet'!D27) -> 0.77475446 | E30: ='P&L'!E5/('Balance Sheet'!E36+'Balance Sheet'!E27) -> 0.94371376 | F30: ='P&L'!F5/('Balance Sheet'!F36+'Balance Sheet'!F27) -> 1.0586578 | G30: ='P&L'!G5/('Balance Sheet'!G36+'Balance Sheet'!G27) -> 1.0810486 | H30: ='P&L'!H5/('Balance Sheet'!H36+'Balance Sheet'!H27) -> 1.1178493 | I30: ='P&L'!I5/('Balance Sheet'!I36+'Balance Sheet'!I27) -> 1.1479215 | J30: ='P&L'!J5/('Balance Sheet'!J36+'Balance Sheet'!J27) -> 1.1683435 | ... L30: ='P&L'!L5/('Balance Sheet'!L36+'Balance Sheet'!L27) -> 1.1837334 | N30: =AVERAGE(C30:L30) -> 1.0408104 | O30: =MEDIAN(C30:L30) -> 1.0994489
B32: Debtor Days | D32: =365/D26 -> 20.218476 | E32: =365/E26 -> 19.582755 | F32: =365/F26 -> 20.024793 | G32: =365/G26 -> 20.963214 | H32: =365/H26 -> 20.149577 | I32: =365/I26 -> 19.896086 | J32: =365/J26 -> 19.975441 | K32: =365/K26 -> 20.05618 | L32: =365/L26 -> 20.138339 | N32: =AVERAGE(C32:L32) -> 20.111651 | O32: =MEDIAN(C32:L32) -> 20.05618
B33: Payable Days | D33: =365/D27 -> 142.19743 | E33: =365/E27 -> 160.27516 | F33: =365/F27 -> 169.68412 | G33: =365/G27 -> 170.39832 | H33: =365/H27 -> 166.59829 | I33: =365/I27 -> 156.67324 | J33: =365/J27 -> 157.29813 | K33: =365/K27 -> 157.93391 | L33: =365/L27 -> 158.58088 | N33: =AVERAGE(C33:L33) -> 159.95994 | O33: =MEDIAN(C33:L33) -> 158.58088
B34: Inventory Days | D34: =365/D28 -> 147.41008 | E34: =365/E28 -> 148.00551 | F34: =365/F28 -> 158.46877 | G34: =365/G28 -> 162.30584 | H34: =365/H28 -> 163.69439 | I34: =365/I28 -> 153.94636 | J34: =365/J28 -> 154.56037 | K34: =365/K28 -> 155.18509 | L34: =365/L28 -> 155.8208 | N34: =AVERAGE(C34:L34) -> 155.48858 | O34: =MEDIAN(C34:L34) -> 155.18509
B35: Cash Conversion Cycle (in days) | D35: =D32+D34-D33 -> 25.431123 | E35: =E32+E34-E33 -> 7.3131074 | F35: =F32+F34-F33 -> 8.8094407 | G35: =G32+G34-G33 -> 12.870733 | H35: =H32+H34-H33 -> 17.245673 | I35: =I32+I34-I33 -> 17.169208 | J35: =J32+J34-J33 -> 17.237687 | K35: =K32+K34-K33 -> 17.30736 | L35: =L32+L34-L33 -> 17.378259 | N35: =AVERAGE(C35:L35) -> 15.640288 | O35: =MEDIAN(C35:L35) -> 17.237687

Sheet Drivers
B2: Drivers | C2: 2 | D2: Scenario | L2: Index
B3: All figures in Rs. Crore (unless specified)
B4: Financial Year | C4: 2020 | D4: 2021 | E4: 2022 | F4: 2023 | G4: 2024 | H4: 2025 | I4: 2026 | J4: 2027 | K4: 2028 | L4: 2029
B5: Income Statement Drivers
B7: Revenue | C7: ='P&L'!C5 -> 42429.89 | D7: ='P&L'!D5 -> 44725.8 | E7: ='P&L'!E5 -> 52598.83 | F7: ='P&L'!F5 -> 63239.98 | G7: ='P&L'!G5 -> 70908.14 | H7: =G7*(H8+1) -> 82749.799 | I7: =H7*(I8+1) -> 96569.016 | J7: =I7*(J8+1) -> 111730.35 | K7: =J7*(K8+1) -> 128154.71 | L7: =K7*(L8+1) -> 145711.91
B8: Revenue growth y-o-y | C8: - | D8: =D7/C7-1 -> 0.054110675 | E8: =E7/D7-1 -> 0.17602882 | F8: =F7/E7-1 -> 0.20230773 | G8: =G7/F7-1 -> 0.12125494 | H8: =CHOOSE($C$2,H9,H10,H11) -> 0.167 | I8: =CHOOSE($C$2,I9,I10,I11) -> 0.167 | J8: =CHOOSE($C$2,J9,J10,J11) -> 0.157 | K8: =CHOOSE($C$2,K9,K10,K11) -> 0.147 | L8: =CHOOSE($C$2,L9,L10,L11) -> 0.137
B9: Scenario 1 | H9: =H10-2% -> 0.147 | I9: =I10-2% -> 0.147 | J9: =J10-2% -> 0.137 | K9: =K10-2% -> 0.127 | L9: =L10-2% -> 0.117
B10: Scenario 2 | H10: ='(IS)'!E36 -> 0.167 | I10: =H10 -> 0.167 | J10: =I10-1% -> 0.157 | K10: =J10-1% -> 0.147 | L10: =K10-1% -> 0.137
B11: Scenario 3 | H11: =H10+2% -> 0.187 | I11: =I10+2% -> 0.187 | J11: =J10+2% -> 0.177 | K11: =K10+2% -> 0.167 | L11: =L10+2% -> 0.157
B13: Cost of Good Sold | C13: ='P&L'!C6 -> 9561.36 | D13: ='P&L'!D6 -> 10153.19 | E13: ='P&L'!E6 -> 11854.66 | F13: ='P&L'!F6 -> 14059.3 | G13: ='P&L'!G6 -> 16801.09 | H13: =H7*H14 -> 18817.166 | I13: =I7*I14 -> 21959.633 | J13: =J7*J14 -> 25407.295 | K13: =K7*K14 -> 29142.168 | L13: =L7*L14 -> 33134.645
B14: % of Revenue | C14: =C13/C7 -> 0.22534492 | D14: =D13/D7 -> 0.22700969 | E14: =E13/E7 -> 0.22537878 | F14: =F13/F7 -> 0.22231664 | G14: =G13/G7 -> 0.23694163 | H14: =CHOOSE($C$2,H15,H16,H17) -> 0.22739833 | I14: =CHOOSE($C$2,I15,I16,I17) -> 0.22739833 | J14: =CHOOSE($C$2,J15,J16,J17) -> 0.22739833 | K14: =CHOOSE($C$2,K15,K16,K17) -> 0.22739833 | L14: =CHOOSE($C$2,L15,L16,L17) -> 0.22739833
B15: Scenario 1 | H15: =H16+5% -> 0.27739833 | I15: =I16+5% -> 0.27739833 | J15: =J16+5% -> 0.27739833 | K15: =K16+5% -> 0.27739833 | L15: =L16+5% -> 0.27739833
B16: Scenario 2 | H16: =AVERAGE(C14:G14) -> 0.22739833 | I16: =H16 -> 0.22739833 | J16: =I16 -> 0.22739833 | K16: =J16 -> 0.22739833 | L16: =K16 -> 0.22739833
B17: Scenario 3 | H17: =H16-5% -> 0.17739833 | I17: =I16-5% -> 0.17739833 | J17: =J16-5% -> 0.17739833 | K17: =K16-5% -> 0.17739833 | L17: =L16-5% -> 0.17739833
B19: Power and Fuel (% of revenue) | C19: ='P&L'!C8/'P&L'!C5 -> 0.20072807 | D19: ='P&L'!D8/'P&L'!D5 -> 0.18627235 | E19: ='P&L'!E8/'P&L'!E5 -> 0.23075152 | F19: ='P&L'!F8/'P&L'!F5 -> 0.29239921 | G19: ='P&L'!G8/'P&L'!G5 -> 0.25784515 | H19: =AVERAGE(C19:G19) -> 0.23359926 | I19: =H19 -> 0.23359926 | J19: =I19 -> 0.23359926 | K19: =J19 -> 0.23359926 | L19: =K19 -> 0.23359926
B20: Employee Cost (Growth y-o-y) | D20: ='P&L'!D9/'P&L'!C9-1 -> -0.063152095 | E20: ='P&L'!E9/'P&L'!D9-1 -> 0.076870348 | F20: ='P&L'!F9/'P&L'!E9-1 -> 0.081064833 | G20: ='P&L'!G9/'P&L'!F9-1 -> 0.10928612 | H20: =AVERAGE(E20:G20) -> 0.089073768 | I20: =H20 -> 0.089073768 | J20: =I20 -> 0.089073768 | K20: =J20 -> 0.089073768 | L20: =K20 -> 0.089073768
B21: Selling and admin (Growth y-o-y) | D21: ='P&L'!D10/'P&L'!C10-1 -> 0.0025539897 | E21: ='P&L'!E10/'P&L'!D10-1 -> 0.17896293 | F21: ='P&L'!F10/'P&L'!E10-1 -> 0.19404738 | G21: ='P&L'!G10/'P&L'!F10-1 -> 0.13918069 | H21: =AVERAGE(E21:G21) -> 0.17073033 | I21: =H21 -> 0.17073033 | J21: =I21 -> 0.17073033 | K21: =J21 -> 0.17073033 | L21: =K21 -> 0.17073033
B22: Other Expenses (Growth y-o-y) | D22: ='P&L'!D11/'P&L'!C11-1 -> -0.22408656 | E22: ='P&L'!E11/'P&L'!D11-1 -> 0.21181417 | F22: ='P&L'!F11/'P&L'!E11-1 -> 0.15273365 | G22: ='P&L'!G11/'P&L'!F11-1 -> 0.19034005 | H22: =AVERAGE(E22:G22) -> 0.18496262 | I22: =H22 -> 0.18496262 | J22: =I22 -> 0.18496262 | K22: =J22 -> 0.18496262 | L22: =K22 -> 0.18496262
B23: Other Income
B25: Tax Expenses | C25: ='P&L'!C18 -> -568.16 | D25: ='P&L'!D18 -> 2538.7 | E25: ='P&L'!E18 -> 1190.06 | F25: ='P&L'!F18 -> 2342.85 | G25: ='P&L'!G18 -> 2418.26
B26: % of PBT | C26: =C25/'P&L'!C17 -> -0.10962583 | D26: =D25/'P&L'!D17 -> 0.31731568 | E26: =E25/'P&L'!E17 -> 0.13960762 | F26: =F25/'P&L'!F17 -> 0.31590764 | G26: =G25/'P&L'!G17 -> 0.25665501 | H26: =CHOOSE($C$2,H27,H28,H29) -> 0.25 | I26: =CHOOSE($C$2,I27,I28,I29) -> 0.25 | J26: =CHOOSE($C$2,J27,J28,J29) -> 0.25 | K26: =CHOOSE($C$2,K27,K28,K29) -> 0.25 | L26: =CHOOSE($C$2,L27,L28,L29) -> 0.25
B27: Scenario 1 | H27: =H28+2% -> 0.27 | I27: =H27 -> 0.27 | J27: =I27 -> 0.27 | K27: =J27 -> 0.27 | L27: =K27 -> 0.27
B28: Scenario 2 | H28: 0.25 | I28: =H28 -> 0.25 | J28: =I28 -> 0.25 | K28: =J28 -> 0.25 | L28: =K28 -> 0.25
B29: Scenario 3 | H29: =H28-2% -> 0.23 | I29: =H29 -> 0.23 | J29: =I29 -> 0.23 | K29: =J29 -> 0.23 | L29: =K29 -> 0.23
B31: Interest Expenses
B32: Short term Borrowings | C32: ='Balance Sheet'!C24 -> 4106 | D32: ='Balance Sheet'!D24 -> 6939 | E32: ='Balance Sheet'!E24 -> 4900 | F32: ='Balance Sheet'!F24 -> 4544 | G32: ='Balance Sheet'!G24 -> 4991 | H32: =AVERAGE(C32:G32) -> 5096 | I32: =AVERAGE(D32:H32) -> 5294 | J32: =AVERAGE(E32:I32) -> 4965 | K32: =AVERAGE(F32:J32) -> 4978 | L32: =AVERAGE(G32:K32) -> 5064.8
B33: Long term Borrowings | C33: ='Balance Sheet'!C27 -> 17368 | D33: ='Balance Sheet'!D27 -> 13548 | E33: ='Balance Sheet'!E27 -> 5303 | F33: ='Balance Sheet'!F27 -> 5356 | G33: ='Balance Sheet'!G27 -> 5308 | H33: =AVERAGE(E33:G33) -> 5322.3333 | I33: =AVERAGE(F33:H33) -> 5328.7778 | J33: =AVERAGE(G33:I33) -> 5319.7037 | K33: =AVERAGE(H33:J33) -> 5323.6049 | L33: =AVERAGE(I33:K33) -> 5324.0288
B34: Interest | C34: ='P&L'!C16 -> 1991.65 | D34: ='P&L'!D16 -> 1485.65 | E34: ='P&L'!E16 -> 944.71 | F34: ='P&L'!F16 -> 822.72 | G34: ='P&L'!G16 -> 968 | H34: =SUM(H32:H33)*H36 -> 906.28643 | I34: =SUM(I32:I33)*I36 -> 911.83891 | J34: =SUM(J32:J33)*J36 -> 910.22054 | K34: =SUM(K32:K33)*K36 -> 903.29162 | L34: =SUM(L32:L33)*L36 -> 920.45913
B36: Interest Rate | C36: =C34/SUM(C32:C33) -> 0.092747043 | D36: =D34/SUM(D32:D33) -> 0.072516718 | E36: =E34/SUM(E32:E33) -> 0.092591395 | F36: =F34/SUM(F32:F33) -> 0.08310303 | G36: =G34/SUM(G32:G33) -> 0.093989708 | H36: =AVERAGE(C36:G36) -> 0.086989579 | I36: =AVERAGE(D36:H36) -> 0.085838086 | J36: =AVERAGE(E36:I36) -> 0.088502359 | K36: =AVERAGE(F36:J36) -> 0.087684552 | L36: =AVERAGE(G36:K36) -> 0.088600857
B38: Divident Paid
B39: Net Income | C39: ='P&L'!C19 -> 5750.88 | D39: ='P&L'!D19 -> 5461.85 | E39: ='P&L'!E19 -> 7334.26 | F39: ='P&L'!F19 -> 5073.4 | G39: ='P&L'!G19 -> 7003.96 | H39: ='P&L'!H19 -> 10691.038 | I39: ='P&L'!I19 -> 12884.871 | J39: ='P&L'!J19 -> 15022.942 | ... L39: ='P&L'!L19 -> 18706.819
B40: Divident Paid | C40: ='P&L'!C20 -> 375.22 | D40: ='P&L'!D20 -> 1068 | E40: ='P&L'!E20 -> 1096.95 | F40: ='P&L'!F20 -> 1097.02 | G40: ='P&L'!G20 -> 2020.83 | H40: =H39*H41 -> 2271.471 | I40: =I39*I41 -> 2792.1087 | J40: =J39*J41 -> 3507.5495 | K40: =K39*K41 -> 4044.3862 | L40: =L39*L41 -> 4211.06
B41: Divident Payout Ratio (%) | C41: =C40/C39 -> 0.065245667 | D41: =D40/D39 -> 0.19553814 | E41: =E40/E39 -> 0.14956519 | F41: =F40/F39 -> 0.21622975 | G41: =G40/G39 -> 0.28852678 | H41: =AVERAGE(D41:G41) -> 0.21246496 | I41: =AVERAGE(E41:H41) -> 0.21669667 | J41: =AVERAGE(F41:I41) -> 0.23347954 | K41: =AVERAGE(G41:J41) -> 0.23779199 | L41: =AVERAGE(H41:K41) -> 0.22510829
B43: Balance Sheet Drivers
B45: Working Capital
B46: Inventories (% of COGS) | C46: ='Balance Sheet'!C5/Drivers!C53 -> 0.43749006 | D46: ='Balance Sheet'!D5/Drivers!D53 -> 0.39573769 | E46: ='Balance Sheet'!E5/Drivers!E53 -> 0.47205065 | F46: ='Balance Sheet'!F5/Drivers!F53 -> 0.47029368 | G46: ='Balance Sheet'!G5/Drivers!G53 -> 0.49580117 | H46: =AVERAGE(C46:G46) -> 0.45427465 | I46: =H46 -> 0.45427465 | J46: =I46 -> 0.45427465 | K46: =J46 -> 0.45427465 | L46: =K46 -> 0.45427465
B47: Trade receivables (% of revenue) | C47: ='Balance Sheet'!C6/Drivers!C52 -> 0.056163238 | D47: ='Balance Sheet'!D6/Drivers!D52 -> 0.057505959 | E47: ='Balance Sheet'!E6/Drivers!E52 -> 0.058404341 | F47: ='Balance Sheet'!F6/Drivers!F52 -> 0.061148027 | G47: ='Balance Sheet'!G6/Drivers!G52 -> 0.060331578 | H47: =AVERAGE(C47:G47) -> 0.058710628 | I47: =H47 -> 0.058710628 | J47: =I47 -> 0.058710628 | K47: =J47 -> 0.058710628 | L47: =K47 -> 0.058710628
B48: Loan n Advances (% of revenue) | C48: ='Balance Sheet'!C8/Drivers!C52 -> 0.01876036 | D48: ='Balance Sheet'!D8/Drivers!D52 -> 0.014756583 | E48: ='Balance Sheet'!E8/Drivers!E52 -> 0.016597327 | F48: ='Balance Sheet'!F8/Drivers!F52 -> 0.015037955 | G48: ='Balance Sheet'!G8/Drivers!G52 -> 0.013891212 | H48: =AVERAGE(C48:G48) -> 0.015808688 | I48: =H48 -> 0.015808688 | J48: =I48 -> 0.015808688 | K48: =J48 -> 0.015808688 | L48: =K48 -> 0.015808688
B49: Trade Payables (% of COGS) | C49: ='Balance Sheet'!C21/Drivers!C53 -> 0.35172821 | D49: ='Balance Sheet'!D21/Drivers!D53 -> 0.44793804 | E49: ='Balance Sheet'!E21/Drivers!E53 -> 0.49457344 | F49: ='Balance Sheet'!F21/Drivers!F53 -> 0.51275668 | G49: ='Balance Sheet'!G21/Drivers!G53 -> 0.50461012 | H49: =AVERAGE(C49:G49) -> 0.4623213 | I49: =H49 -> 0.4623213 | J49: =I49 -> 0.4623213 | K49: =J49 -> 0.4623213 | L49: =K49 -> 0.4623213
B50: Advance from Customers (% of revenue) | C50: ='Balance Sheet'!C22/Drivers!C52 -> 0.010935687 | D50: ='Balance Sheet'!D22/Drivers!D52 -> 0.0092787608 | E50: ='Balance Sheet'!E22/Drivers!E52 -> 0.0088405008 | F50: ='Balance Sheet'!F22/Drivers!F52 -> 0.0060721082 | G50: ='Balance Sheet'!G22/Drivers!G52 -> 0.0074321509 | H50: =AVERAGE(C50:G50) -> 0.0085118416 | I50: =H50 -> 0.0085118416 | J50: =I50 -> 0.0085118416 | K50: =J50 -> 0.0085118416 | L50: =K50 -> 0.0085118416
B52: Revenue | C52: ='P&L'!C5 -> 42429.89 | D52: ='P&L'!D5 -> 44725.8 | E52: ='P&L'!E5 -> 52598.83 | F52: ='P&L'!F5 -> 63239.98 | G52: ='P&L'!G5 -> 70908.14 | H52: ='P&L'!H5 -> 82749.799 | I52: ='P&L'!I5 -> 96569.016 | J52: ='P&L'!J5 -> 111730.35 | ... L52: ='P&L'!L5 -> 145711.91
B53: COGS | C53: ='P&L'!C6 -> 9561.36 | D53: ='P&L'!D6 -> 10153.19 | E53: ='P&L'!E6 -> 11854.66 | F53: ='P&L'!F6 -> 14059.3 | G53: ='P&L'!G6 -> 16801.09 | H53: ='P&L'!H6 -> 18817.166 | I53: ='P&L'!I6 -> 21959.633 | J53: ='P&L'!J6 -> 25407.295 | ... L53: ='P&L'!L6 -> 33134.645
B55: Reserves & Surplus
B56: Opening Balance of R&S | C56: - | D56: =C59 -> 38755 | E56: =D59 -> 43886 | F56: =E59 -> 50147 | G56: =F59 -> 54036
B57: Transfer to Reserve | C57: - | D57: ='P&L'!D21 -> 4393.85 | E57: ='P&L'!E21 -> 6237.31 | F57: ='P&L'!F21 -> 3976.38 | G57: ='P&L'!G21 -> 4983.13
B58: Adjustment | C58: - | D58: =D59-D56-D57 -> 737.15 | E58: =E59-E56-E57 -> 23.69 | F58: =F59-F56-F57 -> -87.38 | G58: =G59-G56-G57 -> 919.87
B59: Closing Balance of R&S | C59: ='Balance Sheet'!C34 -> 38755 | D59: ='Balance Sheet'!D34 -> 43886 | E59: ='Balance Sheet'!E34 -> 50147 | F59: ='Balance Sheet'!F34 -> 54036 | G59: ='Balance Sheet'!G34 -> 59939

Sheet 3 Statements >

Sheet P&L
B2: Income Statement | L2: Index
B3: All figures in Rs. Crore
B4: Financial Year | C4: 2020 | D4: 2021 | E4: 2022 | F4: 2023 | G4: 2024 | H4: 2025 | I4: 2026 | J4: 2027 | K4: 2028 | L4: 2029
B5: Total Revenue | C5: ='(IS)'!G3 -> 42429.89 | D5: ='(IS)'!H3 -> 44725.8 | E5: ='(IS)'!I3 -> 52598.83 | F5: ='(IS)'!J3 -> 63239.98 | G5: ='(IS)'!K3 -> 70908.14 | H5: =Drivers!H7 -> 82749.799 | I5: =Drivers!I7 -> 96569.016 | J5: =Drivers!J7 -> 111730.35 | K5: =Drivers!K7 -> 128154.71 | L5: =Drivers!L7 -> 145711.91
B6: COGS | C6: ='(IS)'!G4-'(IS)'!G5+'(IS)'!G7 -> 9561.36 | D6: ='(IS)'!H4-'(IS)'!H5+'(IS)'!H7 -> 10153.19 | E6: ='(IS)'!I4-'(IS)'!I5+'(IS)'!I7 -> 11854.66 | F6: ='(IS)'!J4-'(IS)'!J5+'(IS)'!J7 -> 14059.3 | G6: ='(IS)'!K4-'(IS)'!K5+'(IS)'!K7 -> 16801.09 | H6: =Drivers!H13 -> 18817.166 | I6: =Drivers!I13 -> 21959.633 | J6: =Drivers!J13 -> 25407.295 | K6: =Drivers!K13 -> 29142.168 | L6: =Drivers!L13 -> 33134.645
B7: Gross Profit | C7: =C5-C6 -> 32868.53 | D7: =D5-D6 -> 34572.61 | E7: =E5-E6 -> 40744.17 | F7: =F5-F6 -> 49180.68 | G7: =G5-G6 -> 54107.05 | H7: =H5-H6 -> 63932.633 | I7: =I5-I6 -> 74609.383 | J7: =J5-J6 -> 86323.056 | ... L7: =L5-L6 -> 112577.26
B8: Power and Fuel | C8: ='(IS)'!G6 -> 8516.87 | D8: ='(IS)'!H6 -> 8331.18 | E8: ='(IS)'!I6 -> 12137.26 | F8: ='(IS)'!J6 -> 18491.32 | G8: ='(IS)'!K6 -> 18283.32 | H8: =H5*Drivers!H19 -> 19330.292 | I8: =I5*Drivers!I19 -> 22558.451 | J8: =J5*Drivers!J19 -> 26100.127 | K8: =K5*Drivers!K19 -> 29936.846 | L8: =L5*Drivers!L19 -> 34038.194
B9: Employee Cost | C9: ='(IS)'!G8 -> 2522.64 | D9: ='(IS)'!H8 -> 2363.33 | E9: ='(IS)'!I8 -> 2545 | F9: ='(IS)'!J8 -> 2751.31 | G9: ='(IS)'!K8 -> 3051.99 | H9: =G9*(1+Drivers!H20) -> 3323.8422 | I9: =H9*(1+Drivers!I20) -> 3619.9094 | J9: =I9*(1+Drivers!J20) -> 3942.3484 | K9: =J9*(1+Drivers!K20) -> 4293.5082 | L9: =K9*(1+Drivers!L20) -> 4675.9471
B10: Selling and admin | C10: ='(IS)'!G9 -> 11237.32 | D10: ='(IS)'!H9 -> 11266.02 | E10: ='(IS)'!I9 -> 13282.22 | F10: ='(IS)'!J9 -> 15859.6 | G10: ='(IS)'!K9 -> 18066.95 | H10: =G10*(1+Drivers!H21) -> 21151.526 | I10: =H10*(1+Drivers!I21) -> 24762.734 | J10: =I10*(1+Drivers!J21) -> 28990.483 | K10: =J10*(1+Drivers!K21) -> 33940.038 | L10: =K10*(1+Drivers!L21) -> 39734.632
B11: Other Expenses | C11: ='(IS)'!G10 -> 1345.73 | D11: ='(IS)'!H10 -> 1044.17 | E11: ='(IS)'!I10 -> 1265.34 | F11: ='(IS)'!J10 -> 1458.6 | G11: ='(IS)'!K10 -> 1736.23 | H11: =G11*(1+Drivers!H22) -> 2057.3677 | I11: =H11*(1+Drivers!I22) -> 2437.9038 | J11: =I11*(1+Drivers!J22) -> 2888.8249 | K11: =J11*(1+Drivers!K22) -> 3423.1495 | L11: =K11*(1+Drivers!L22) -> 4056.3042
B12: Other Income | C12: ='(IS)'!G11 -> 651.06 | D12: ='(IS)'!H11 -> 618.52 | E12: ='(IS)'!I11 -> 669.43 | F12: ='(IS)'!J11 -> 507.11 | G12: ='(IS)'!K11 -> 566.96 | H12: =AVERAGE(C12:G12) -> 602.616 | I12: =AVERAGE(D12:H12) -> 592.9272 | J12: =AVERAGE(E12:I12) -> 587.80864 | K12: =AVERAGE(F12:J12) -> 571.48437 | L12: =AVERAGE(G12:K12) -> 584.35924
B13: EBITDA | C13: =C7-C8-C9-C10-C11+C12 -> 9897.03 | D13: =D7-D8-D9-D10-D11+D12 -> 12186.43 | E13: =E7-E8-E9-E10-E11+E12 -> 12183.78 | F13: =F7-F8-F9-F10-F11+F12 -> 11126.96 | G13: =G7-G8-G9-G10-G11+G12 -> 13535.52 | H13: =H7-H8-H9-H10-H11+H12 -> 18672.221 | I13: =I7-I8-I9-I10-I11+I12 -> 21823.313 | J13: =J7-J8-J9-J10-J11+J12 -> 24989.081 | ... L13: =L7-L8-L9-L10-L11+L12 -> 30656.545
B14: Depreciation & Amortization | C14: ='(IS)'!G12 -> 2722.66 | D14: ='(IS)'!H12 -> 2700.23 | E14: ='(IS)'!I12 -> 2714.75 | F14: ='(IS)'!J12 -> 2887.99 | G14: ='(IS)'!K12 -> 3145.3 | H14: =PPE!H16 -> 3511.2171 | I14: =PPE!I16 -> 3731.6454 | J14: =PPE!J16 -> 4048.271 | K14: =PPE!K16 -> 4409.7501 | L14: =PPE!L16 -> 4793.6613
B15: EBIT | C15: =C13-C14 -> 7174.37 | D15: =D13-D14 -> 9486.2 | E15: =E13-E14 -> 9469.03 | F15: =F13-F14 -> 8238.97 | G15: =G13-G14 -> 10390.22 | H15: =H13-H14 -> 15161.004 | I15: =I13-I14 -> 18091.667 | J15: =J13-J14 -> 20940.81 | ... L15: =L13-L14 -> 25862.884
B16: Interest | C16: ='(IS)'!G13 -> 1991.65 | D16: ='(IS)'!H13 -> 1485.65 | E16: ='(IS)'!I13 -> 944.71 | F16: ='(IS)'!J13 -> 822.72 | G16: ='(IS)'!K13 -> 968 | H16: =Drivers!H34 -> 906.28643 | I16: =Drivers!I34 -> 911.83891 | J16: =Drivers!J34 -> 910.22054 | K16: =Drivers!K34 -> 903.29162 | L16: =Drivers!L34 -> 920.45913
B17: EBT | C17: =C15-C16 -> 5182.72 | D17: =D15-D16 -> 8000.55 | E17: =E15-E16 -> 8524.32 | F17: =F15-F16 -> 7416.25 | G17: =G15-G16 -> 9422.22 | H17: =H15-H16 -> 14254.717 | I17: =I15-I16 -> 17179.828 | J17: =J15-J16 -> 20030.589 | ... L17: =L15-L16 -> 24942.425
B18: Taxes | C18: ='(IS)'!G15 -> -568.16 | D18: ='(IS)'!H15 -> 2538.7 | E18: ='(IS)'!I15 -> 1190.06 | F18: ='(IS)'!J15 -> 2342.85 | G18: ='(IS)'!K15 -> 2418.26 | H18: =H17*Drivers!H26 -> 3563.6793 | I18: =I17*Drivers!I26 -> 4294.9571 | J18: =J17*Drivers!J26 -> 5007.6473 | K18: =K17*Drivers!K26 -> 5669.3615 | L18: =L17*Drivers!L26 -> 6235.6063
B19: EAT/ Net Profit | C19: =C17-C18 -> 5750.88 | D19: =D17-D18 -> 5461.85 | E19: =E17-E18 -> 7334.26 | F19: =F17-F18 -> 5073.4 | G19: =G17-G18 -> 7003.96 | H19: =H17-H18 -> 10691.038 | I19: =I17-I18 -> 12884.871 | J19: =J17-J18 -> 15022.942 | ... L19: =L17-L18 -> 18706.819
B20: Divident Paid | C20: ='(IS)'!G17 -> 375.22 | D20: ='(IS)'!H17 -> 1068 | E20: ='(IS)'!I17 -> 1096.95 | F20: ='(IS)'!J17 -> 1097.02 | G20: ='(IS)'!K17 -> 2020.83 | H20: =Drivers!H40 -> 2271.471 | I20: =Drivers!I40 -> 2792.1087 | J20: =Drivers!J40 -> 3507.5495 | K20: =Drivers!K40 -> 4044.3862 | L20: =Drivers!L40 -> 4211.06
B21: Transfer to Reserve | C21: =C19-C20 -> 5375.66 | D21: =D19-D20 -> 4393.85 | E21: =E19-E20 -> 6237.31 | F21: =F19-F20 -> 3976.38 | G21: =G19-G20 -> 4983.13 | H21: =H19-H20 -> 8419.567 | I21: =I19-I20 -> 10092.763 | J21: =J19-J20 -> 11515.392 | ... L21: =L19-L20 -> 14495.759

Sheet Sheet3
C4: 2020
C5: 2021 | I5: 2020 | J5: 2021 | K5: 2022 | L5: 2023 | M5: 2024 | N5: 2025 | O5: 2026 | P5: 2027 | Q5: 2028 | R5: 2029
C6: 2022 | I6: ='(IS)'!M4 -> 0 | J6: ='(IS)'!N4 -> 0 | K6: ='(IS)'!O4 -> 0 | L6: ='(IS)'!P4 -> 0 | M6: ='(IS)'!Q4 -> 0 | N6: =Drivers!N8 -> 0 | O6: =Drivers!O8 -> 0 | P6: =Drivers!P8 -> 0 | Q6: =Drivers!Q8 -> 0 | R6: =Drivers!R8 -> 0
C7: 2023
C8: 2024
C9: 2025
C10: 2026
C11: 2027
C12: 2028
C13: 2029

Sheet Balance Sheet
B2: Balance Sheet | L2: Index
B3: All figures in Rs. Crore
B4: Financial Year | C4: 2020 | D4: 2021 | E4: 2022 | F4: 2023 | G4: 2024 | H4: 2025 | I4: 2026 | J4: 2027 | K4: 2028 | L4: 2029
B5: Inventories | C5: ='(BS)'!G36 -> 4183 | D5: ='(BS)'!H36 -> 4018 | E5: ='(BS)'!I36 -> 5596 | F5: ='(BS)'!J36 -> 6612 | G5: ='(BS)'!K36 -> 8330 | H5: =WC!H5 -> 8548.1616 | I5: =WC!I5 -> 9975.7046 | J5: =WC!J5 -> 11541.89 | K5: =WC!K5 -> 13238.548 | L5: =WC!L5 -> 15052.229
B6: Trade receivables | C6: ='(BS)'!G37 -> 2383 | D6: ='(BS)'!H37 -> 2572 | E6: ='(BS)'!I37 -> 3072 | F6: ='(BS)'!J37 -> 3867 | G6: ='(BS)'!K37 -> 4278 | H6: =WC!H6 -> 4858.2927 | I6: =WC!I6 -> 5669.6276 | J6: =WC!J6 -> 6559.7592 | K6: =WC!K6 -> 7524.0437 | L6: =WC!L6 -> 8554.8377
B7: Cash Equivalents | C7: ='(BS)'!G38 -> 540 | D7: ='(BS)'!H38 -> 2008 | E7: ='(BS)'!I38 -> 359 | F7: ='(BS)'!J38 -> 1150 | G7: ='(BS)'!K38 -> 783 | H7: =G7+'Cash Flow'!H30 -> 4637.1043 | I7: =H7+'Cash Flow'!I30 -> 7815.4311 | J7: =I7+'Cash Flow'!J30 -> 10624.986 | K7: =J7+'Cash Flow'!K30 -> 14964.086 | L7: =K7+'Cash Flow'!L30 -> 20652.414
B8: Loans n Advances | C8: ='(BS)'!G39 -> 796 | D8: ='(BS)'!H39 -> 660 | E8: ='(BS)'!I39 -> 873 | F8: ='(BS)'!J39 -> 951 | G8: ='(BS)'!K39 -> 985 | H8: =WC!H7 -> 1308.1657 | I8: =WC!I7 -> 1526.6294 | J8: =WC!J7 -> 1766.3102 | K8: =WC!K7 -> 2025.9578 | L8: =WC!L7 -> 2303.514
B9: Other asset items | C9: ='(BS)'!G40 -> 7312 | D9: ='(BS)'!H40 -> 7642 | E9: ='(BS)'!I40 -> 7304 | F9: ='(BS)'!J40 -> 7885 | G9: ='(BS)'!K40 -> 8483 | H9: =WC!H8 -> 7725.2 | I9: =WC!I8 -> 7807.84 | J9: =WC!J8 -> 7841.008 | K9: =WC!K8 -> 7948.4096 | L9: =WC!L8 -> 7961.0915
B10: Total Current Assets | C10: =SUM(C5:C9) -> 15214 | D10: =SUM(D5:D9) -> 16900 | E10: =SUM(E5:E9) -> 17204 | F10: =SUM(F5:F9) -> 20465 | G10: =SUM(G5:G9) -> 22859 | H10: =SUM(H5:H9) -> 27076.924 | I10: =SUM(I5:I9) -> 32795.233 | J10: =SUM(J5:J9) -> 38333.954 | ... L10: =SUM(L5:L9) -> 54524.086
B12: Property, Plant & Equipments | C12: =SUM('(BS)'!G20:G27) -> 53945 | D12: =SUM('(BS)'!H20:H27) -> 54668 | E12: =SUM('(BS)'!I20:I27) -> 57210 | F12: =SUM('(BS)'!J20:J27) -> 63776 | G12: =SUM('(BS)'!K20:K27) -> 70143 | H12: =G12+PPE!H6 -> 78236.247 | I12: =H12+PPE!I6 -> 87910.648 | J12: =I12+PPE!J6 -> 99114.132 | K12: =J12+PPE!K6 -> 110815.79 | L12: =K12+PPE!L6 -> 123184.82
B13: Capital Work in Progress | C13: ='(BS)'!G32 -> 920 | D13: ='(BS)'!H32 -> 1687 | E13: ='(BS)'!I32 -> 4785 | F13: ='(BS)'!J32 -> 4040 | G13: ='(BS)'!K32 -> 6811 | H13: =G13 -> 6811 | I13: =H13 -> 6811 | J13: =I13 -> 6811 | K13: =J13 -> 6811 | L13: =K13 -> 6811
B14: Intangible Assets | C14: ='(BS)'!G28 -> 6680 | D14: ='(BS)'!H28 -> 6375 | E14: ='(BS)'!I28 -> 6405 | F14: ='(BS)'!J28 -> 6484 | G14: ='(BS)'!K28 -> 6501 | H14: =G14+PPE!H24 -> 6638.8756 | I14: =H14+PPE!I24 -> 6845.4756 | J14: =I14+PPE!J24 -> 7051.8376 | K14: =J14+PPE!K24 -> 7239.9505 | L14: =K14+PPE!L24 -> 7419.7743
B15: Long Term Investment | C15: ='(BS)'!G33 -> 5929 | D15: ='(BS)'!H33 -> 12178 | E15: ='(BS)'!I33 -> 6336 | F15: ='(BS)'!J33 -> 7297 | G15: ='(BS)'!K33 -> 8249 | H15: =G15 -> 8249 | I15: =H15 -> 8249 | J15: =I15 -> 8249 | K15: =J15 -> 8249 | L15: =K15 -> 8249
B16: Other Fixed Assets | C16: ='(BS)'!G29 -> 5927 | D16: ='(BS)'!H29 -> 6289 | E16: ='(BS)'!I29 -> 6387 | F16: ='(BS)'!J29 -> 6695 | G16: ='(BS)'!K29 -> 6637 | H16: =G16 -> 6637 | I16: =H16 -> 6637 | J16: =I16 -> 6637 | K16: =J16 -> 6637 | L16: =K16 -> 6637
B17: Accumulated Depreciation | C17: ='(BS)'!G31 -> 9399 | D17: ='(BS)'!H31 -> 11921 | E17: ='(BS)'!I31 -> 14514 | F17: ='(BS)'!J31 -> 17378 | G17: ='(BS)'!K31 -> 20403 | H17: =G17+PPE!H16 -> 23914.217 | I17: =H17+PPE!I16 -> 27645.863 | J17: =I17+PPE!J16 -> 31694.134 | K17: =J17+PPE!K16 -> 36103.884 | L17: =K17+PPE!L16 -> 40897.545
B18: Total Non-Current Assets | C18: =SUM(C12:C16)-C17 -> 64002 | D18: =SUM(D12:D16)-D17 -> 69276 | E18: =SUM(E12:E16)-E17 -> 66609 | F18: =SUM(F12:F16)-F17 -> 70914 | G18: =SUM(G12:G16)-G17 -> 77938 | H18: =H12+H13+H14+H15+H16-H17 -> 82657.906 | I18: =I12+I13+I14+I15+I16-I17 -> 88807.261 | J18: =J12+J13+J14+J15+J16-J17 -> 96168.837 | K18: =K12+K13+K14+K15+K16-K17 -> 103648.86 | L18: =L12+L13+L14+L15+L16-L17 -> 111404.05
B19: Total Assets | C19: =C10+C18 -> 79216 | D19: =D10+D18 -> 86176 | E19: =E10+E18 -> 83813 | F19: =F10+F18 -> 91379 | G19: =G10+G18 -> 100797 | H19: =H10+H18 -> 109734.83 | I19: =I10+I18 -> 121602.49 | J19: =J10+J18 -> 134502.79 | ... L19: =L10+L18 -> 165928.14
B21: Trade Payables | C21: ='(BS)'!G14 -> 3363 | D21: ='(BS)'!H14 -> 4548 | E21: ='(BS)'!I14 -> 5863 | F21: ='(BS)'!J14 -> 7209 | G21: ='(BS)'!K14 -> 8478 | H21: =WC!H11 -> 8699.5767 | I21: =WC!I11 -> 10152.406 | J21: =WC!J11 -> 11746.334 | K21: =WC!K11 -> 13473.045 | L21: =WC!L11 -> 15318.852
B22: Advance from Customers | C22: ='(BS)'!G15 -> 464 | D22: ='(BS)'!H15 -> 415 | E22: ='(BS)'!I15 -> 465 | F22: ='(BS)'!J15 -> 384 | G22: ='(BS)'!K15 -> 527 | H22: =WC!H12 -> 704.35318 | I22: =WC!I12 -> 821.98016 | J22: =WC!J12 -> 951.03105 | K22: =WC!K12 -> 1090.8326 | L22: =WC!L12 -> 1240.2767
B23: Other liability items | C23: ='(BS)'!G16 -> 13316 | D23: ='(BS)'!H16 -> 15313 | E23: ='(BS)'!I16 -> 15753 | F23: ='(BS)'!J16 -> 18349 | G23: ='(BS)'!K16 -> 20106 | H23: =WC!H13 -> 20106 | I23: =WC!I13 -> 20106 | J23: =WC!J13 -> 20106 | K23: =WC!K13 -> 20106 | L23: =WC!L13 -> 20106
B24: Short term Borrowings | C24: ='(BS)'!G8 -> 4106 | D24: ='(BS)'!H8 -> 6939 | E24: ='(BS)'!I8 -> 4900 | F24: ='(BS)'!J8 -> 4544 | G24: ='(BS)'!K8 -> 4991 | H24: =Drivers!H32 -> 5096 | I24: =Drivers!I32 -> 5294 | J24: =Drivers!J32 -> 4965 | K24: =Drivers!K32 -> 4978 | L24: =Drivers!L32 -> 5064.8
B25: Total Current Liabilities | C25: =SUM(C21:C24) -> 21249 | D25: =SUM(D21:D24) -> 27215 | E25: =SUM(E21:E24) -> 26981 | F25: =SUM(F21:F24) -> 30486 | G25: =SUM(G21:G24) -> 34102 | H25: =SUM(H21:H24) -> 34605.93 | I25: =SUM(I21:I24) -> 36374.386 | J25: =SUM(J21:J24) -> 37768.365 | ... L25: =SUM(L21:L24) -> 41729.929
B27: Long term Borrowings | C27: ='(BS)'!G7 -> 17368 | D27: ='(BS)'!H7 -> 13548 | E27: ='(BS)'!I7 -> 5303 | F27: ='(BS)'!J7 -> 5356 | G27: ='(BS)'!K7 -> 5308 | H27: =Drivers!H33 -> 5322.3333 | I27: =Drivers!I33 -> 5328.7778 | J27: =Drivers!J33 -> 5319.7037 | K27: =Drivers!K33 -> 5323.6049 | L27: =Drivers!L33 -> 5324.0288
B28: Lease Liabilities | C28: ='(BS)'!G9 -> 0 | D28: ='(BS)'!H9 -> 1232 | E28: ='(BS)'!I9 -> 1096 | F28: ='(BS)'!J9 -> 1157 | G28: ='(BS)'!K9 -> 1103 | H28: =G28 -> 1103 | I28: =H28 -> 1103 | J28: =I28 -> 1103 | K28: =J28 -> 1103 | L28: =K28 -> 1103
B29: Other Borrowings | C29: ='(BS)'!G10 -> 1545 | D29: ='(BS)'!H10 -> 0 | E29: ='(BS)'!I10 -> 0 | F29: ='(BS)'!J10 -> 0 | G29: ='(BS)'!K10 -> 0 | H29: =G29 -> 0 | I29: =H29 -> 0 | J29: =I29 -> 0 | K29: =J29 -> 0 | L29: =K29 -> 0
B30: Total Non-Current Liabilities | C30: =SUM(C27:C29) -> 18913 | D30: =SUM(D27:D29) -> 14780 | E30: =SUM(E27:E29) -> 6399 | F30: =SUM(F27:F29) -> 6513 | G30: =SUM(G27:G29) -> 6411 | H30: =SUM(H27:H29) -> 6425.3333 | I30: =SUM(I27:I29) -> 6431.7778 | J30: =SUM(J27:J29) -> 6422.7037 | ... L30: =SUM(L27:L29) -> 6427.0288
B31: Total Liabilities | C31: =C30+C25 -> 40162 | D31: =D30+D25 -> 41995 | E31: =E30+E25 -> 33380 | F31: =F30+F25 -> 36999 | G31: =G30+G25 -> 40513 | H31: =H30+H25 -> 41031.263 | I31: =I30+I25 -> 42806.164 | J31: =J30+J25 -> 44191.068 | ... L31: =L30+L25 -> 48156.957
B33: Equity Capital | C33: ='(BS)'!G3 -> 289 | D33: ='(BS)'!H3 -> 289 | E33: ='(BS)'!I3 -> 289 | F33: ='(BS)'!J3 -> 289 | G33: ='(BS)'!K3 -> 289 | H33: =G33 -> 289 | I33: =H33 -> 289 | J33: =I33 -> 289 | K33: =J33 -> 289 | L33: =K33 -> 289
B34: Reserves | C34: ='(BS)'!G4 -> 38755 | D34: ='(BS)'!H4 -> 43886 | E34: ='(BS)'!I4 -> 50147 | F34: ='(BS)'!J4 -> 54036 | G34: ='(BS)'!K4 -> 59939 | H34: =G34+'P&L'!H21 -> 68358.567 | I34: =H34+'P&L'!I21 -> 78451.33 | J34: =I34+'P&L'!J21 -> 89966.722 | K34: =J34+'P&L'!K21 -> 102930.42 | L34: =K34+'P&L'!L21 -> 117426.18
B35: Minority Interest | C35: ='(BS)'!G13 -> 10 | D35: ='(BS)'!H13 -> 6 | E35: ='(BS)'!I13 -> -3 | F35: ='(BS)'!J13 -> 55 | G35: ='(BS)'!K13 -> 56 | H35: =G35 -> 56 | I35: =H35 -> 56 | J35: =I35 -> 56 | K35: =J35 -> 56 | L35: =K35 -> 56
B36: Total Equity | C36: =SUM(C33:C35) -> 39054 | D36: =SUM(D33:D35) -> 44181 | E36: =SUM(E33:E35) -> 50433 | F36: =SUM(F33:F35) -> 54380 | G36: =SUM(G33:G35) -> 60284 | H36: =SUM(H33:H35) -> 68703.567 | I36: =SUM(I33:I35) -> 78796.33 | J36: =SUM(J33:J35) -> 90311.722 | ... L36: =SUM(L33:L35) -> 117771.18
B37: Total Equity & Liabilities | C37: =C36+C31 -> 79216 | D37: =D36+D31 -> 86176 | E37: =E36+E31 -> 83813 | F37: =F36+F31 -> 91379 | G37: =G36+G31 -> 100797 | H37: =H36+H31 -> 109734.83 | I37: =I36+I31 -> 121602.49 | J37: =J36+J31 -> 134502.79 | ... L37: =L36+L31 -> 165928.14
B39: Balance Check | C39: =IF(C19=C37,"TRUE","FALSE") -> TRUE | D39: =IF(D19=D37,"TRUE","FALSE") -> TRUE | E39: =IF(E19=E37,"TRUE","FALSE") -> TRUE | F39: =IF(F19=F37,"TRUE","FALSE") -> TRUE | G39: =IF(G19=G37,"TRUE","FALSE") -> TRUE | H39: =IF(H19=H37,"TRUE","FALSE") -> TRUE | I39: =IF(I19=I37,"TRUE","FALSE") -> TRUE | J39: =IF(J19=J37,"TRUE","FALSE") -> TRUE | ... L39: =IF(L19=L37,"TRUE","FALSE") -> TRUE

Sheet Cash Flow
B2: Cash Flow Statement | L2: Index
B3: All figures in Rs. Crore
B4: Financial Year | C4: 2020 | D4: 2021 | E4: 2022 | F4: 2023 | G4: 2024 | H4: 2025 | I4: 2026 | J4: 2027 | K4: 2028 | L4: 2029
B5: Cash Flow from Operating Activities
B6: Profit from operations (EBITDA) | C6: ='(CFS)'!G4 -> 9348 | D6: ='(CFS)'!H4 -> 11465 | E6: ='(CFS)'!I4 -> 11311 | F6: ='(CFS)'!J4 -> 10530 | G6: ='(CFS)'!K4 -> 13029 | H6: ='P&L'!H13 -> 18672.221 | I6: ='P&L'!I13 -> 21823.313 | J6: ='P&L'!J13 -> 24989.081 | K6: ='P&L'!K13 -> 27990.488 | L6: ='P&L'!L13 -> 30656.545
B7: Receivables | C7: ='(CFS)'!G5 -> 473 | D7: ='(CFS)'!H5 -> -201 | E7: ='(CFS)'!I5 -> -495 | F7: ='(CFS)'!J5 -> -752 | G7: ='(CFS)'!K5 -> -421 | H7: ='Balance Sheet'!G6-'Balance Sheet'!H6 -> -580.29273 | I7: ='Balance Sheet'!H6-'Balance Sheet'!I6 -> -811.33489 | J7: ='Balance Sheet'!I6-'Balance Sheet'!J6 -> -890.13154 | K7: ='Balance Sheet'!J6-'Balance Sheet'!K6 -> -964.2846 | L7: ='Balance Sheet'!K6-'Balance Sheet'!L6 -> -1030.794
B8: Inventory | C8: ='(CFS)'!G6 -> -64 | D8: ='(CFS)'!H6 -> 165 | E8: ='(CFS)'!I6 -> -1579 | F8: ='(CFS)'!J6 -> -992 | G8: ='(CFS)'!K6 -> -1712 | H8: ='Balance Sheet'!G5-'Balance Sheet'!H5 -> -218.16164 | I8: ='Balance Sheet'!H5-'Balance Sheet'!I5 -> -1427.543 | J8: ='Balance Sheet'!I5-'Balance Sheet'!J5 -> -1566.1856 | K8: ='Balance Sheet'!J5-'Balance Sheet'!K5 -> -1696.6579 | L8: ='Balance Sheet'!K5-'Balance Sheet'!L5 -> -1813.6811
B9: Payables | C9: ='(CFS)'!G7 -> 279 | D9: ='(CFS)'!H7 -> 2868 | E9: ='(CFS)'!I7 -> 2077 | F9: ='(CFS)'!J7 -> 1869 | G9: ='(CFS)'!K7 -> 1959 | H9: ='Balance Sheet'!H21-'Balance Sheet'!G21 -> 221.57669 | I9: ='Balance Sheet'!I21-'Balance Sheet'!H21 -> 1452.8293 | J9: ='Balance Sheet'!J21-'Balance Sheet'!I21 -> 1593.9277 | K9: ='Balance Sheet'!K21-'Balance Sheet'!J21 -> 1726.7111 | L9: ='Balance Sheet'!L21-'Balance Sheet'!K21 -> 1845.8071
B10: Other WC items | C10: ='(CFS)'!G9 -> -172 | D10: ='(CFS)'!H9 -> -505 | E10: ='(CFS)'!I9 -> -476 | F10: ='(CFS)'!J9 -> -461 | G10: ='(CFS)'!K9 -> -308 | H10: =WC!H22 -> 611.98746 | I10: =WC!I22 -> -183.47669 | J10: =WC!J22 -> -143.79793 | K10: =WC!K22 -> -227.24764 | L10: =WC!L22 -> -140.79407
B11: Direct taxes | C11: ='(CFS)'!G11 -> -891 | D11: ='(CFS)'!H11 -> -1291 | E11: ='(CFS)'!I11 -> -1555 | F11: ='(CFS)'!J11 -> -1124 | G11: ='(CFS)'!K11 -> -1651 | H11: =-'P&L'!H18 -> -3563.6793 | I11: =-'P&L'!I18 -> -4294.9571 | J11: =-'P&L'!J18 -> -5007.6473 | K11: =-'P&L'!K18 -> -5669.3615 | L11: =-'P&L'!L18 -> -6235.6063
B12: Net cash inflow(outflow) from Operating Activities | C12: =SUM(C6:C11) -> 8973 | D12: =SUM(D6:D11) -> 12501 | E12: =SUM(E6:E11) -> 9283 | F12: =SUM(F6:F11) -> 9070 | G12: =SUM(G6:G11) -> 10896 | H12: =SUM(H6:H11) -> 15143.651 | I12: =SUM(I6:I11) -> 16558.83 | J12: =SUM(J6:J11) -> 18975.246 | ... L12: =SUM(L6:L11) -> 23281.477
B14: Cash Flow from Investing Activities
B15: Fixed assets purchased | C15: ='(CFS)'!G15 -> -1766 | D15: ='(CFS)'!H15 -> -1925 | E15: ='(CFS)'!I15 -> -5613 | F15: ='(CFS)'!J15 -> -6200 | G15: ='(CFS)'!K15 -> -9006 | H15: =-(PPE!H6+PPE!H24) -> -8231.1229 | I15: =-(PPE!I6+PPE!I24) -> -9881.0004 | J15: =-(PPE!J6+PPE!J24) -> -11409.847 | K15: =-(PPE!K6+PPE!K24) -> -11889.771 | L15: =-(PPE!L6+PPE!L24) -> -12548.854
B16: Fixed assets sold | C16: ='(CFS)'!G16 -> 79 | D16: ='(CFS)'!H16 -> 86 | E16: ='(CFS)'!I16 -> 73 | F16: ='(CFS)'!J16 -> 95 | G16: ='(CFS)'!K16 -> 122 | H16: =G16 -> 122 | I16: =H16 -> 122 | J16: =I16 -> 122 | K16: =J16 -> 122 | L16: =K16 -> 122
B17: Investments purchased | C17: ='(CFS)'!G17 -> -6086 | D17: ='(CFS)'!H17 -> -12689 | E17: ='(CFS)'!I17 -> -7795 | F17: ='(CFS)'!J17 -> -7260 | G17: ='(CFS)'!K17 -> -7750 | H17: =G17 -> -7750 | I17: =H17 -> -7750 | J17: =I17 -> -7750 | K17: =J17 -> -7750 | L17: =K17 -> -7750
B18: Investments sold | C18: ='(CFS)'!G18 -> 3443 | D18: ='(CFS)'!H18 -> 7101 | E18: ='(CFS)'!I18 -> 13965 | F18: ='(CFS)'!J18 -> 7156 | G18: ='(CFS)'!K18 -> 7164 | H18: =G18 -> 7164 | I18: =H18 -> 7164 | J18: =I18 -> 7164 | K18: =J18 -> 7164 | L18: =K18 -> 7164
B19: Other investing items | C19: =SUM('(CFS)'!G19:G25) -> 137 | D19: =SUM('(CFS)'!H19:H25) -> -1429 | E19: =SUM('(CFS)'!I19:I25) -> 1692 | F19: =SUM('(CFS)'!J19:J25) -> -978 | G19: =SUM('(CFS)'!K19:K25) -> 682 | H19: =G19 -> 682 | I19: =H19 -> 682 | J19: =I19 -> 682 | K19: =J19 -> 682 | L19: =K19 -> 682
B20: Net cash inflow(outflow) from Investing Activities | C20: =SUM(C15:C19) -> -4193 | D20: =SUM(D15:D19) -> -8856 | E20: =SUM(E15:E19) -> 2322 | F20: =SUM(F15:F19) -> -7187 | G20: =SUM(G15:G19) -> -8788 | H20: =SUM(H15:H19) -> -8013.1229 | I20: =SUM(I15:I19) -> -9663.0004 | J20: =SUM(J15:J19) -> -11191.847 | ... L20: =SUM(L15:L19) -> -12330.854
B22: Cash Flow from Financing Activities
B23: Proceeds from shares | C23: ='(CFS)'!G28 -> 3 | D23: ='(CFS)'!H28 -> 14 | E23: ='(CFS)'!I28 -> 13 | F23: ='(CFS)'!J28 -> 13 | G23: ='(CFS)'!K28 -> 44 | H23: =G23 -> 44 | I23: =H23 -> 44 | J23: =I23 -> 44 | K23: =J23 -> 44 | L23: =K23 -> 44
B24: Debt proceeds/repayments | C24: =SUM('(CFS)'!G29:G30) -> -2644 | D24: =SUM('(CFS)'!H29:H30) -> -2396 | E24: =SUM('(CFS)'!I29:I30) -> -10171 | F24: =SUM('(CFS)'!J29:J30) -> 453 | G24: =SUM('(CFS)'!K29:K30) -> 330 | H24: =SUM(Drivers!H32:H33)-SUM(Drivers!G32:G33) -> 119.33333 | I24: =SUM(Drivers!I32:I33)-SUM(Drivers!H32:H33) -> 204.44444 | J24: =SUM(Drivers!J32:J33)-SUM(Drivers!I32:I33) -> -338.07407 | K24: =SUM(Drivers!K32:K33)-SUM(Drivers!J32:J33) -> 16.901235 | L24: =SUM(Drivers!L32:L33)-SUM(Drivers!K32:K33) -> 87.223868
B25: Interest paid fin | C25: ='(CFS)'!G31 -> -1950 | D25: ='(CFS)'!H31 -> -1481 | E25: ='(CFS)'!I31 -> -1026 | F25: ='(CFS)'!J31 -> -765 | G25: ='(CFS)'!K31 -> -917 | H25: =-'P&L'!H16 -> -906.28643 | I25: =-'P&L'!I16 -> -911.83891 | J25: =-'P&L'!J16 -> -910.22054 | K25: =-'P&L'!K16 -> -903.29162 | L25: =-'P&L'!L16 -> -920.45913
B26: Dividends paid | C26: ='(CFS)'!G32 -> -380 | D26: ='(CFS)'!H32 -> -375 | E26: ='(CFS)'!I32 -> -1065 | F26: ='(CFS)'!J32 -> -1091 | G26: ='(CFS)'!K32 -> -1094 | H26: =-'P&L'!H20 -> -2271.471 | I26: =-'P&L'!I20 -> -2792.1087 | J26: =-'P&L'!J20 -> -3507.5495 | K26: =-'P&L'!K20 -> -4044.3862 | L26: =-'P&L'!L20 -> -4211.06
B27: Other Financing items | C27: =SUM('(CFS)'!G33:G34) -> -105 | D27: =SUM('(CFS)'!H33:H34) -> -118 | E27: =SUM('(CFS)'!I33:I34) -> -248 | F27: =SUM('(CFS)'!J33:J34) -> -241 | G27: =SUM('(CFS)'!K33:K34) -> -262 | H27: =G27 -> -262 | I27: =H27 -> -262 | J27: =I27 -> -262 | K27: =J27 -> -262 | L27: =K27 -> -262
B28: Net cash inflow(outflow) from Financial Activities | C28: =SUM(C23:C27) -> -5076 | D28: =SUM(D23:D27) -> -4356 | E28: =SUM(E23:E27) -> -12497 | F28: =SUM(F23:F27) -> -1631 | G28: =SUM(G23:G27) -> -1899 | H28: =SUM(H23:H27) -> -3276.4241 | I28: =SUM(I23:I27) -> -3717.5032 | J28: =SUM(J23:J27) -> -4973.8442 | ... L28: =SUM(L23:L27) -> -5262.2953
B30: Net Cash Flow for the year | C30: =C12+C20+C28 -> -296 | D30: =D12+D20+D28 -> -711 | E30: =E12+E20+E28 -> -892 | F30: =F12+F20+F28 -> 252 | G30: =G12+G20+G28 -> 209 | H30: =H12+H20+H28 -> 3854.1043 | I30: =I12+I20+I28 -> 3178.3267 | J30: =J12+J20+J28 -> 2809.5551 | ... L30: =L12+L20+L28 -> 5688.3277

Sheet Cash Flow (A)
B2: Cash Flow Statement | L2: Index
B3: All figures in Rs. Crore
B4: Financial Year | C4: 2020 | D4: 2021 | E4: 2022 | F4: 2023 | G4: 2024 | H4: 2025 | I4: 2026 | J4: 2027 | K4: 2028 | L4: 2029
B5: Cash Flow from Operating Activities
B6: Net Profit | D6: ='P&L'!D19 -> 5461.85 | E6: ='P&L'!E19 -> 7334.26 | F6: ='P&L'!F19 -> 5073.4 | G6: ='P&L'!G19 -> 7003.96 | H6: ='P&L'!H19 -> 10691.038 | I6: ='P&L'!I19 -> 12884.871 | J6: ='P&L'!J19 -> 15022.942 | K6: ='P&L'!K19 -> 17008.084 | L6: ='P&L'!L19 -> 18706.819
B7: Depreciation & Amortization | D7: ='P&L'!D14 -> 2700.23 | E7: ='P&L'!E14 -> 2714.75 | F7: ='P&L'!F14 -> 2887.99 | G7: ='P&L'!G14 -> 3145.3 | H7: ='P&L'!H14 -> 3511.2171 | I7: ='P&L'!I14 -> 3731.6454 | J7: ='P&L'!J14 -> 4048.271 | K7: ='P&L'!K14 -> 4409.7501 | L7: ='P&L'!L14 -> 4793.6613
B8: Change in Working Capital:
B9: Inventories | D9: ='Balance Sheet'!C5-'Balance Sheet'!D5 -> 165 | E9: ='Balance Sheet'!D5-'Balance Sheet'!E5 -> -1578 | F9: ='Balance Sheet'!E5-'Balance Sheet'!F5 -> -1016 | G9: ='Balance Sheet'!F5-'Balance Sheet'!G5 -> -1718 | H9: ='Balance Sheet'!G5-'Balance Sheet'!H5 -> -218.16164 | I9: ='Balance Sheet'!H5-'Balance Sheet'!I5 -> -1427.543 | J9: ='Balance Sheet'!I5-'Balance Sheet'!J5 -> -1566.1856 | K9: ='Balance Sheet'!J5-'Balance Sheet'!K5 -> -1696.6579 | L9: ='Balance Sheet'!K5-'Balance Sheet'!L5 -> -1813.6811
B10: Trade receivables | D10: ='Balance Sheet'!C6-'Balance Sheet'!D6 -> -189 | E10: ='Balance Sheet'!D6-'Balance Sheet'!E6 -> -500 | F10: ='Balance Sheet'!E6-'Balance Sheet'!F6 -> -795 | G10: ='Balance Sheet'!F6-'Balance Sheet'!G6 -> -411 | H10: ='Balance Sheet'!G6-'Balance Sheet'!H6 -> -580.29273 | I10: ='Balance Sheet'!H6-'Balance Sheet'!I6 -> -811.33489 | J10: ='Balance Sheet'!I6-'Balance Sheet'!J6 -> -890.13154 | K10: ='Balance Sheet'!J6-'Balance Sheet'!K6 -> -964.2846 | L10: ='Balance Sheet'!K6-'Balance Sheet'!L6 -> -1030.794
B11: Other asset items | D11: ='Balance Sheet'!C9-'Balance Sheet'!D9 -> -330 | E11: ='Balance Sheet'!D9-'Balance Sheet'!E9 -> 338 | F11: ='Balance Sheet'!E9-'Balance Sheet'!F9 -> -581 | G11: ='Balance Sheet'!F9-'Balance Sheet'!G9 -> -598 | H11: ='Balance Sheet'!G9-'Balance Sheet'!H9 -> 757.8 | I11: ='Balance Sheet'!H9-'Balance Sheet'!I9 -> -82.64 | J11: ='Balance Sheet'!I9-'Balance Sheet'!J9 -> -33.168 | K11: ='Balance Sheet'!J9-'Balance Sheet'!K9 -> -107.4016 | L11: ='Balance Sheet'!K9-'Balance Sheet'!L9 -> -12.68192
B12: Trade Payables | D12: ='Balance Sheet'!D21-'Balance Sheet'!C21 -> 1185 | E12: ='Balance Sheet'!E21-'Balance Sheet'!D21 -> 1315 | F12: ='Balance Sheet'!F21-'Balance Sheet'!E21 -> 1346 | G12: ='Balance Sheet'!G21-'Balance Sheet'!F21 -> 1269 | H12: ='Balance Sheet'!H21-'Balance Sheet'!G21 -> 221.57669 | I12: ='Balance Sheet'!I21-'Balance Sheet'!H21 -> 1452.8293 | J12: ='Balance Sheet'!J21-'Balance Sheet'!I21 -> 1593.9277 | K12: ='Balance Sheet'!K21-'Balance Sheet'!J21 -> 1726.7111 | L12: ='Balance Sheet'!L21-'Balance Sheet'!K21 -> 1845.8071
B13: Advance from Customers | D13: ='Balance Sheet'!D22-'Balance Sheet'!C22 -> -49 | E13: ='Balance Sheet'!E22-'Balance Sheet'!D22 -> 50 | F13: ='Balance Sheet'!F22-'Balance Sheet'!E22 -> -81 | G13: ='Balance Sheet'!G22-'Balance Sheet'!F22 -> 143 | H13: ='Balance Sheet'!H22-'Balance Sheet'!G22 -> 177.35318 | I13: ='Balance Sheet'!I22-'Balance Sheet'!H22 -> 117.62698 | J13: ='Balance Sheet'!J22-'Balance Sheet'!I22 -> 129.05089 | K13: ='Balance Sheet'!K22-'Balance Sheet'!J22 -> 139.80156 | L13: ='Balance Sheet'!L22-'Balance Sheet'!K22 -> 149.44407
B14: Other liability items | D14: ='Balance Sheet'!D23-'Balance Sheet'!C23 -> 1997 | E14: ='Balance Sheet'!E23-'Balance Sheet'!D23 -> 440 | F14: ='Balance Sheet'!F23-'Balance Sheet'!E23 -> 2596 | G14: ='Balance Sheet'!G23-'Balance Sheet'!F23 -> 1757 | H14: ='Balance Sheet'!H23-'Balance Sheet'!G23 -> 0 | I14: ='Balance Sheet'!I23-'Balance Sheet'!H23 -> 0 | J14: ='Balance Sheet'!J23-'Balance Sheet'!I23 -> 0 | K14: ='Balance Sheet'!K23-'Balance Sheet'!J23 -> 0 | L14: ='Balance Sheet'!L23-'Balance Sheet'!K23 -> 0
B15: Net cash inflow(outflow) from Operating Activities | C15: =SUM(C6:C14) -> 0 | D15: =SUM(D6:D14) -> 10941.08 | E15: =SUM(E6:E14) -> 10114.01 | F15: =SUM(F6:F14) -> 9430.39 | G15: =SUM(G6:G14) -> 10591.26 | H15: =SUM(H6:H14) -> 14560.531 | I15: =SUM(I6:I14) -> 15865.455 | J15: =SUM(J6:J14) -> 18304.706 | ... L15: =SUM(L6:L14) -> 22638.574
B17: Cash Flow from Investing Activities
B18: Capex | D18: =-PPE!D6 -> -3271.45 | E18: =-PPE!E6 -> -5084.04 | F18: =-PPE!F6 -> -9259.07 | G18: =-PPE!G6 -> -9313.99 | H18: =-PPE!H6 -> -8093.2473 | I18: =-PPE!I6 -> -9674.4004 | J18: =-PPE!J6 -> -11203.485 | K18: =-PPE!K6 -> -11701.658 | L18: =-PPE!L6 -> -12369.03
B19: Addition | D19: =-PPE!D24 -> 153.22 | E19: =-PPE!E24 -> -202.71 | F19: =-PPE!F24 -> -273.92 | G19: =-PPE!G24 -> -215.31 | H19: =-PPE!H24 -> -137.87559 | I19: =-PPE!I24 -> -206.60006 | J19: =-PPE!J24 -> -206.36191 | K19: =-PPE!K24 -> -188.11298 | L19: =-PPE!L24 -> -179.82373
B20: Capital Work in Progress | D20: ='Balance Sheet'!C13-'Balance Sheet'!D13 -> -767 | E20: ='Balance Sheet'!D13-'Balance Sheet'!E13 -> -3098 | F20: ='Balance Sheet'!E13-'Balance Sheet'!F13 -> 745 | G20: ='Balance Sheet'!F13-'Balance Sheet'!G13 -> -2771 | H20: ='Balance Sheet'!G13-'Balance Sheet'!H13 -> 0 | I20: ='Balance Sheet'!H13-'Balance Sheet'!I13 -> 0 | J20: ='Balance Sheet'!I13-'Balance Sheet'!J13 -> 0 | K20: ='Balance Sheet'!J13-'Balance Sheet'!K13 -> 0 | L20: ='Balance Sheet'!K13-'Balance Sheet'!L13 -> 0
B21: Long Term Investment | D21: =-('Balance Sheet'!D15-'Balance Sheet'!C15) -> -6249 | E21: =-('Balance Sheet'!E15-'Balance Sheet'!D15) -> 5842 | F21: =-('Balance Sheet'!F15-'Balance Sheet'!E15) -> -961 | G21: =-('Balance Sheet'!G15-'Balance Sheet'!F15) -> -952 | H21: =-('Balance Sheet'!H15-'Balance Sheet'!G15) -> 0 | I21: =-('Balance Sheet'!I15-'Balance Sheet'!H15) -> 0 | J21: =-('Balance Sheet'!J15-'Balance Sheet'!I15) -> 0 | K21: =-('Balance Sheet'!K15-'Balance Sheet'!J15) -> 0 | L21: =-('Balance Sheet'!L15-'Balance Sheet'!K15) -> 0
B22: Other Fixed Assets | D22: =-('Balance Sheet'!D16-'Balance Sheet'!C16) -> -362 | E22: =-('Balance Sheet'!E16-'Balance Sheet'!D16) -> -98 | F22: =-('Balance Sheet'!F16-'Balance Sheet'!E16) -> -308 | G22: =-('Balance Sheet'!G16-'Balance Sheet'!F16) -> 58 | H22: =-('Balance Sheet'!H16-'Balance Sheet'!G16) -> 0 | I22: =-('Balance Sheet'!I16-'Balance Sheet'!H16) -> 0 | J22: =-('Balance Sheet'!J16-'Balance Sheet'!I16) -> 0 | K22: =-('Balance Sheet'!K16-'Balance Sheet'!J16) -> 0 | L22: =-('Balance Sheet'!L16-'Balance Sheet'!K16) -> 0
B23: Accumulated Depreciation | D23: ='Balance Sheet'!D17-'Balance Sheet'!C17 -> 2522 | E23: ='Balance Sheet'!E17-'Balance Sheet'!D17 -> 2593 | F23: ='Balance Sheet'!F17-'Balance Sheet'!E17 -> 2864 | G23: ='Balance Sheet'!G17-'Balance Sheet'!F17 -> 3025 | H23: ='Balance Sheet'!H17-'Balance Sheet'!G17 -> 3511.2171 | I23: ='Balance Sheet'!I17-'Balance Sheet'!H17 -> 3731.6454 | J23: ='Balance Sheet'!J17-'Balance Sheet'!I17 -> 4048.271 | K23: ='Balance Sheet'!K17-'Balance Sheet'!J17 -> 4409.7501 | L23: ='Balance Sheet'!L17-'Balance Sheet'!K17 -> 4793.6613
B24: Net cash inflow(outflow) from Investing Activities | C24: =SUM(C18:C23) -> 0 | D24: =SUM(D18:D23) -> -7974.23 | E24: =SUM(E18:E23) -> -47.75 | F24: =SUM(F18:F23) -> -7192.99 | G24: =SUM(G18:G23) -> -10169.3 | H24: =SUM(H18:H23) -> -4719.9058 | I24: =SUM(I18:I23) -> -6149.355 | J24: =SUM(J18:J23) -> -7361.5758 | ... L24: =SUM(L18:L23) -> -7755.1929
B26: Cash Flow from Financing Activities
B27: Divident Paid | D27: =-'P&L'!D20 -> -1068 | E27: =-'P&L'!E20 -> -1096.95 | F27: =-'P&L'!F20 -> -1097.02 | G27: =-'P&L'!G20 -> -2020.83 | H27: =-'P&L'!H20 -> -2271.471 | I27: =-'P&L'!I20 -> -2792.1087 | J27: =-'P&L'!J20 -> -3507.5495 | K27: =-'P&L'!K20 -> -4044.3862 | L27: =-'P&L'!L20 -> -4211.06
B28: Loans n Advances | D28: =('Balance Sheet'!C8-'Balance Sheet'!D8) -> 136 | E28: =('Balance Sheet'!D8-'Balance Sheet'!E8) -> -213 | F28: =('Balance Sheet'!E8-'Balance Sheet'!F8) -> -78 | G28: =('Balance Sheet'!F8-'Balance Sheet'!G8) -> -34 | H28: =('Balance Sheet'!G8-'Balance Sheet'!H8) -> -323.16573 | I28: =('Balance Sheet'!H8-'Balance Sheet'!I8) -> -218.46368 | J28: =('Balance Sheet'!I8-'Balance Sheet'!J8) -> -239.68082 | K28: =('Balance Sheet'!J8-'Balance Sheet'!K8) -> -259.6476 | L28: =('Balance Sheet'!K8-'Balance Sheet'!L8) -> -277.55622
B29: Short term Borrowings | D29: ='Balance Sheet'!D24-'Balance Sheet'!C24 -> 2833 | E29: ='Balance Sheet'!E24-'Balance Sheet'!D24 -> -2039 | F29: ='Balance Sheet'!F24-'Balance Sheet'!E24 -> -356 | G29: ='Balance Sheet'!G24-'Balance Sheet'!F24 -> 447 | H29: ='Balance Sheet'!H24-'Balance Sheet'!G24 -> 105 | I29: ='Balance Sheet'!I24-'Balance Sheet'!H24 -> 198 | J29: ='Balance Sheet'!J24-'Balance Sheet'!I24 -> -329 | K29: ='Balance Sheet'!K24-'Balance Sheet'!J24 -> 13 | L29: ='Balance Sheet'!L24-'Balance Sheet'!K24 -> 86.8
B30: Long term Borrowings | D30: ='Balance Sheet'!D27-'Balance Sheet'!C27 -> -3820 | E30: ='Balance Sheet'!E27-'Balance Sheet'!D27 -> -8245 | F30: ='Balance Sheet'!F27-'Balance Sheet'!E27 -> 53 | G30: ='Balance Sheet'!G27-'Balance Sheet'!F27 -> -48 | H30: ='Balance Sheet'!H27-'Balance Sheet'!G27 -> 14.333333 | I30: ='Balance Sheet'!I27-'Balance Sheet'!H27 -> 6.4444444 | J30: ='Balance Sheet'!J27-'Balance Sheet'!I27 -> -9.0740741 | K30: ='Balance Sheet'!K27-'Balance Sheet'!J27 -> 3.9012346 | L30: ='Balance Sheet'!L27-'Balance Sheet'!K27 -> 0.42386831
B31: Lease Liabilities | D31: ='Balance Sheet'!D28-'Balance Sheet'!C28 -> 1232 | E31: ='Balance Sheet'!E28-'Balance Sheet'!D28 -> -136 | F31: ='Balance Sheet'!F28-'Balance Sheet'!E28 -> 61 | G31: ='Balance Sheet'!G28-'Balance Sheet'!F28 -> -54 | H31: ='Balance Sheet'!H28-'Balance Sheet'!G28 -> 0 | I31: ='Balance Sheet'!I28-'Balance Sheet'!H28 -> 0 | J31: ='Balance Sheet'!J28-'Balance Sheet'!I28 -> 0 | K31: ='Balance Sheet'!K28-'Balance Sheet'!J28 -> 0 | L31: ='Balance Sheet'!L28-'Balance Sheet'!K28 -> 0
B32: Other Borrowings | D32: ='Balance Sheet'!D29-'Balance Sheet'!C29 -> -1545 | E32: ='Balance Sheet'!E29-'Balance Sheet'!D29 -> 0 | F32: ='Balance Sheet'!F29-'Balance Sheet'!E29 -> 0 | G32: ='Balance Sheet'!G29-'Balance Sheet'!F29 -> 0 | H32: ='Balance Sheet'!H29-'Balance Sheet'!G29 -> 0 | I32: ='Balance Sheet'!I29-'Balance Sheet'!H29 -> 0 | J32: ='Balance Sheet'!J29-'Balance Sheet'!I29 -> 0 | K32: ='Balance Sheet'!K29-'Balance Sheet'!J29 -> 0 | L32: ='Balance Sheet'!L29-'Balance Sheet'!K29 -> 0
B33: Equity Capital | D33: ='Balance Sheet'!D33-'Balance Sheet'!C33 -> 0 | E33: ='Balance Sheet'!E33-'Balance Sheet'!D33 -> 0 | F33: ='Balance Sheet'!F33-'Balance Sheet'!E33 -> 0 | G33: ='Balance Sheet'!G33-'Balance Sheet'!F33 -> 0 | H33: ='Balance Sheet'!H33-'Balance Sheet'!G33 -> 0 | I33: ='Balance Sheet'!I33-'Balance Sheet'!H33 -> 0 | J33: ='Balance Sheet'!J33-'Balance Sheet'!I33 -> 0 | K33: ='Balance Sheet'!K33-'Balance Sheet'!J33 -> 0 | L33: ='Balance Sheet'!L33-'Balance Sheet'!K33 -> 0
B34: Minority Interest | D34: ='Balance Sheet'!D35-'Balance Sheet'!C35 -> -4 | E34: ='Balance Sheet'!E35-'Balance Sheet'!D35 -> -9 | F34: ='Balance Sheet'!F35-'Balance Sheet'!E35 -> 58 | G34: ='Balance Sheet'!G35-'Balance Sheet'!F35 -> 1 | H34: ='Balance Sheet'!H35-'Balance Sheet'!G35 -> 0 | I34: ='Balance Sheet'!I35-'Balance Sheet'!H35 -> 0 | J34: ='Balance Sheet'!J35-'Balance Sheet'!I35 -> 0 | K34: ='Balance Sheet'!K35-'Balance Sheet'!J35 -> 0 | L34: ='Balance Sheet'!L35-'Balance Sheet'!K35 -> 0
B35: Adjustment | D35: =Drivers!D58 -> 737.15 | E35: =Drivers!E58 -> 23.69 | F35: =Drivers!F58 -> -87.38 | G35: =Drivers!G58 -> 919.87 | H35: =Drivers!H58 -> 0 | I35: =Drivers!I58 -> 0 | J35: =Drivers!J58 -> 0 | K35: =Drivers!K58 -> 0 | L35: =Drivers!L58 -> 0
B36: Net cash inflow(outflow) from Financial Activities | C36: =SUM(C27:C35) -> 0 | D36: =SUM(D27:D35) -> -1498.85 | E36: =SUM(E27:E35) -> -11715.26 | F36: =SUM(F27:F35) -> -1446.4 | G36: =SUM(G27:G35) -> -788.96 | H36: =SUM(H27:H35) -> -2475.3034 | I36: =SUM(I27:I35) -> -2806.1279 | J36: =SUM(J27:J35) -> -4085.3044 | ... L36: =SUM(L27:L35) -> -4401.3924
B38: Net Cash Flow for the year | D38: =D15+D24+D36 -> 1468 | E38: =E15+E24+E36 -> -1649 | F38: =F15+F24+F36 -> 791 | G38: =G15+G24+G36 -> -367 | H38: =H15+H24+H36 -> 7365.3215 | I38: =I15+I24+I36 -> 6909.9722 | J38: =J15+J24+J36 -> 6857.8261 | K38: =K15+K24+K36 -> 8748.8497 | L38: =L15+L24+L36 -> 10481.989
B39: Opening Balance | D39: =C40 -> 540 | E39: =D40 -> 2008 | F39: =E40 -> 359 | G39: =F40 -> 1150 | H39: =G40 -> 783 | I39: =H40 -> 8148.3215 | J39: =I40 -> 15058.294 | K39: =J40 -> 21916.12 | L39: =K40 -> 30664.969
B40: Closing Balance | C40: ='Balance Sheet'!C7 -> 540 | D40: =D38+D39 -> 2008 | E40: =E38+E39 -> 359 | F40: =F38+F39 -> 1150 | G40: =G38+G39 -> 783 | H40: =H38+H39 -> 8148.3215 | I40: =I38+I39 -> 15058.294 | J40: =J38+J39 -> 21916.12 | K40: =K38+K39 -> 30664.969 | L40: =L38+L39 -> 41146.958

Sheet Valuation >

Sheet WACC
C1: Index
B2: Weighted Average Cost of Capital
B3: All figures in Rs. Crore
B4: Weighted Average Cost of Capital (WACC)
B5: Equity (Cr) | C5: ='Balance Sheet'!G36 -> 60284
B6: Debt (Cr) | C6: =SUM(Drivers!G32:G33) -> 10299
B8: Cost of Debt | C8: ='P&L'!G16/WACC!C6 -> 0.093989708
B9: Tax Rate | C9: =Drivers!H28 -> 0.25
B10: D/(D+E) | C10: =C6/(C6+C5) -> 0.14591332
B11: After tax Cost of Debt | C11: =C8*(1-C9) -> 0.070492281
B13: Risk free rate (10 yr of bond) | C13: 0.069
B14: Expected Market Return | C14: 0.092
B15: Market Risk Premium | C15: =C14-C13 -> 0.023
B16: Beta | C16: 0.56
B17: E/(D+E) | C17: =1-C10 -> 0.85408668
B18: Cost of Equity | C18: =C13+C16*C15 -> 0.08188
B20: WACC | C20: =(C17*C18)+(C10*C11) -> 0.08021838

Sheet DCF
B2: Discounted Cash Flow Model | L2: Index
B3: All figures in Rs. Crore
B4: Unlevered Free Cash Flow | C4: 2020 | D4: 2021 | E4: 2022 | F4: 2023 | G4: 2024 | H4: 2025 | I4: 2026 | J4: 2027 | K4: 2028 | L4: 2029
B5: Unlevered Free Cash Flow | C5: ='Cash Flow'!C12+'Cash Flow'!C15 -> 7207 | D5: ='Cash Flow'!D12+'Cash Flow'!D15 -> 10576 | E5: ='Cash Flow'!E12+'Cash Flow'!E15 -> 3670 | F5: ='Cash Flow'!F12+'Cash Flow'!F15 -> 2870 | G5: ='Cash Flow'!G12+'Cash Flow'!G15 -> 1890 | H5: ='Cash Flow'!H12+'Cash Flow'!H15 -> 6912.5285 | I5: ='Cash Flow'!I12+'Cash Flow'!I15 -> 6677.8299 | J5: ='Cash Flow'!J12+'Cash Flow'!J15 -> 7565.3993 | ... L5: ='Cash Flow'!L12+'Cash Flow'!L15 -> 10732.623
B7: Projection Year | G7: 0 | H7: =G7+1 -> 1 | I7: =H7+1 -> 2 | J7: =I7+1 -> 3 | K7: =J7+1 -> 4 | L7: =K7+1 -> 5
B8: Present Value of Free Cash Flow | H8: =H5/(1+$C$15)^H7 -> 6399.1954 | I8: =I5/(1+$C$15)^I7 -> 5722.8482 | J8: =J5/(1+$C$15)^J7 -> 6002.0163 | K8: =K5/(1+$C$15)^K7 -> 6808.1276 | L8: =L5/(1+$C$15)^L7 -> 7297.0624
B12: Implied Share Price Calculation | F12: Sensitivity Table
B13: Sum of PV of FCF | C13: =SUM(H8:L8) -> 32229.25
B14: Growth Rate | C14: 0.054 | H14: Growth Rate
B15: WACC | C15: =WACC!C20 -> 0.08021838 | G15: =C24 -> 10934.43 | H15: =I15-0.5% -> 0.044 | I15: =J15-0.5% -> 0.049 | J15: 0.054 | K15: =J15+0.5% -> 0.059 | L15: =K15+0.5% -> 0.064
B16: Terminal Value | C16: =L5*(1+C14)/(C15-C14) -> 431460.09 | F16: WACC | G16: =G17-0.5% -> 0.07021838 | H16: 11349.321 | I16: 13893.633 | J16: 18006.728 | K16: 25786.212 | L16: 46076.164
B17: PV of Terminal value | C17: =C16/(1+C15)^L7 -> 293347.79 | G17: =G18-0.5% -> 0.07521838 | H17: 9442.1226 | I17: 11139.487 | J17: 13636.802 | K17: 17673.921 | L17: 25309.706
B18: Enterprice Value | C18: =C13+C17 -> 325577.04 | G18: 0.08021838 | H18: 8062.1495 | I18: 9268.2747 | J18: 10934.43 | K18: 13385.828 | L18: 17348.718
B19: (+) Cash | C19: ='Balance Sheet'!G7 -> 783 | G19: =G18+0.5% -> 0.08521838 | H19: 7017.5225 | I19: 7914.31 | J19: 9098.3601 | K19: 10734.021 | L19: 13140.552
B20: (-) Debt | C20: =WACC!C6 -> 10299 | G20: =G19+0.5% -> 0.09021838 | H20: 6199.3941 | I20: 6889.3454 | J20: 7769.7941 | K20: 8932.2719 | L20: 10538.132
B21: (-) Minority Interest | C21: ='Balance Sheet'!G35 -> 56
B22: Equity Value | C22: =C18+C19-C20-C21 -> 316005.04
B23: Diluted Share Outstanding (Cr) | C23: 28.9
B24: Implied Share Price | C24: =C22/C23 -> 10934.43
B27: Diluted Share Outstanding (Cr) is equity share of the company

Sheet Schedules >

Sheet PPE
B2: Property, Plant & Equipments | L2: Index
B3: All figures in Rs. Crore
B4: Financial Year | C4: 2020 | D4: 2021 | E4: 2022 | F4: 2023 | G4: 2024 | H4: 2025 | I4: 2026 | J4: 2027 | K4: 2028 | L4: 2029
B5: Beginning PPE | C5: - | D5: =C8 -> 53945 | E5: =D8 -> 54668 | F5: =E8 -> 57210 | G5: =F8 -> 63776 | H5: =G8 -> 70143 | I5: =H8 -> 74956.657 | J5: =I8 -> 81135.506 | K5: =J8 -> 88552.56 | L5: =K8 -> 96130.623
B6: Capex | C6: - | D6: =D8-D5+D7 -> 3271.45 | E6: =E8-E5+E7 -> 5084.04 | F6: =F8-F5+F7 -> 9259.07 | G6: =G8-G5+G7 -> 9313.99 | H6: =H11*H5 -> 8093.2473 | I6: =I11*I5 -> 9674.4004 | J6: =J11*J5 -> 11203.485 | K6: =K11*K5 -> 11701.658 | L6: =L11*L5 -> 12369.03
B7: Depreciation | C7: - | D7: =D14 -> 2548.45 | E7: =E14 -> 2542.04 | F7: =F14 -> 2693.07 | G7: =G14 -> 2946.99 | H7: =H10*H5 -> 3279.5902 | I7: =I10*I5 -> 3495.5519 | J7: =J10*J5 -> 3786.4306 | K7: =K10*K5 -> 4123.5942 | L7: =L10*L5 -> 4485.0871
B8: Ending PPE | C8: ='Balance Sheet'!C12 -> 53945 | D8: ='Balance Sheet'!D12 -> 54668 | E8: ='Balance Sheet'!E12 -> 57210 | F8: ='Balance Sheet'!F12 -> 63776 | G8: ='Balance Sheet'!G12 -> 70143 | H8: =H5+H6-H7 -> 74956.657 | I8: =I5+I6-I7 -> 81135.506 | J8: =J5+J6-J7 -> 88552.56 | K8: =K5+K6-K7 -> 96130.623 | L8: =L5+L6-L7 -> 104014.57
B10: Depreciation (% of Beginning PPE) | C10: - | D10: =D7/D5 -> 0.047241635 | E10: =E7/E5 -> 0.046499598 | F10: =F7/F5 -> 0.047073414 | G10: =G7/G5 -> 0.046208448 | H10: =AVERAGE(D10:G10) -> 0.046755774 | I10: =AVERAGE(E10:H10) -> 0.046634308 | J10: =AVERAGE(F10:I10) -> 0.046667986 | K10: =AVERAGE(G10:J10) -> 0.046566629 | L10: =AVERAGE(H10:K10) -> 0.046656174
B11: Capex (% of Beginning PPE) | C11: - | D11: =D6/D5 -> 0.060644175 | E11: =E6/E5 -> 0.092998463 | F11: =F6/F5 -> 0.16184356 | G11: =G6/G5 -> 0.14604224 | H11: =AVERAGE(D11:G11) -> 0.11538211 | I11: =AVERAGE(E11:H11) -> 0.12906659 | J11: =AVERAGE(F11:I11) -> 0.13808363 | K11: =AVERAGE(G11:J11) -> 0.13214364 | L11: =AVERAGE(H11:K11) -> 0.12866899
B13: Depreciation & Amortization
B14: Depreciation | C14: =C16-C15 -> 2506.3 | D14: =D16-D15 -> 2548.45 | E14: =E16-E15 -> 2542.04 | F14: =F16-F15 -> 2693.07 | G14: =G16-G15 -> 2946.99 | H14: =H7 -> 3279.5902 | I14: =I7 -> 3495.5519 | J14: =J7 -> 3786.4306 | K14: =K7 -> 4123.5942 | L14: =L7 -> 4485.0871
B15: Amortization | C15: 216.36 | D15: 151.78 | E15: 172.71 | F15: 194.92 | G15: 198.31 | H15: =H18*H14/H19 -> 231.62691 | I15: =I18*I14/I19 -> 236.09358 | J15: =J18*J14/J19 -> 261.84031 | K15: =K18*K14/K19 -> 286.15585 | L15: =L18*L14/L19 -> 308.57416
B16: Total D&A | C16: ='P&L'!C14 -> 2722.66 | D16: ='P&L'!D14 -> 2700.23 | E16: ='P&L'!E14 -> 2714.75 | F16: ='P&L'!F14 -> 2887.99 | G16: ='P&L'!G14 -> 3145.3 | H16: =H14+H15 -> 3511.2171 | I16: =I14+I15 -> 3731.6454 | J16: =J14+J15 -> 4048.271 | K16: =K14+K15 -> 4409.7501 | L16: =L14+L15 -> 4793.6613
B18: Amortization (% of Total D&A) | C18: =C15/C16 -> 0.079466404 | D18: =D15/D16 -> 0.056210027 | E18: =E15/E16 -> 0.063619118 | F18: =F15/F16 -> 0.067493308 | G18: =G15/G16 -> 0.06304963 | H18: =AVERAGE(C18:G18) -> 0.065967697 | I18: =AVERAGE(D18:H18) -> 0.063267956 | J18: =AVERAGE(E18:I18) -> 0.064679542 | K18: =AVERAGE(F18:J18) -> 0.064891627 | L18: =AVERAGE(G18:K18) -> 0.06437129
H19: =1-H18 -> 0.9340323 | I19: =1-I18 -> 0.93673204 | J19: =1-J18 -> 0.93532046 | K19: =1-K18 -> 0.93510837 | L19: =1-L18 -> 0.93562871
B20: Intangible Assets
B21: All figures in Rs. Crore
B22: Financial Year | C22: 2020 | D22: 2021 | E22: 2022 | F22: 2023 | G22: 2024 | H22: 2025 | I22: 2026 | J22: 2027 | K22: 2028 | L22: 2029
B23: Opening Balance | C23: - | D23: =C26 -> 6680 | E23: =D26 -> 6375 | F23: =E26 -> 6405 | G23: =F26 -> 6484 | H23: =G26 -> 6501 | I23: =H26 -> 6407.2487 | J23: =I26 -> 6377.7552 | K23: =J26 -> 6322.2768 | L23: =K26 -> 6224.2339
B24: Addition | C24: - | D24: =D26-D23+D25 -> -153.22 | E24: =E26-E23+E25 -> 202.71 | F24: =F26-F23+F25 -> 273.92 | G24: =G26-G23+G25 -> 215.31 | H24: =H23*H28 -> 137.87559 | I24: =I23*I28 -> 206.60006 | J24: =J23*J28 -> 206.36191 | K24: =K23*K28 -> 188.11298 | L24: =L23*L28 -> 179.82373
B25: Amortization | C25: - | D25: =D15 -> 151.78 | E25: =E15 -> 172.71 | F25: =F15 -> 194.92 | G25: =G15 -> 198.31 | H25: =H15 -> 231.62691 | I25: =I15 -> 236.09358 | J25: =J15 -> 261.84031 | K25: =K15 -> 286.15585 | L25: =L15 -> 308.57416
B26: Closing Balance | C26: ='Balance Sheet'!C14 -> 6680 | D26: ='Balance Sheet'!D14 -> 6375 | E26: ='Balance Sheet'!E14 -> 6405 | F26: ='Balance Sheet'!F14 -> 6484 | G26: ='Balance Sheet'!G14 -> 6501 | H26: =H23+H24-H25 -> 6407.2487 | I26: =I23+I24-I25 -> 6377.7552 | J26: =J23+J24-J25 -> 6322.2768 | K26: =K23+K24-K25 -> 6224.2339 | L26: =L23+L24-L25 -> 6095.4835
B28: Addition (% of Opening Balance) | C28: - | D28: =D24/D23 -> -0.022937126 | E28: =E24/E23 -> 0.031797647 | F28: =F24/F23 -> 0.042766589 | G28: =G24/G23 -> 0.033206354 | H28: =AVERAGE(D28:G28) -> 0.021208366 | I28: =AVERAGE(E28:H28) -> 0.032244739 | J28: =AVERAGE(F28:I28) -> 0.032356512 | K28: =AVERAGE(G28:J28) -> 0.029753993 | L28: =AVERAGE(H28:K28) -> 0.028890902
M39: 2022 | N39: 2023 | O39: 2024 | P39: 2025 | Q39: 2026 | R39: 2027 | S39: 2028 | T39: 2029
M40: =L43 -> 0 | N40: =M43 -> 0 | O40: =N43 -> 0 | P40: =O43 -> 0 | Q40: =P43 -> 0 | R40: =Q43 -> 0 | S40: =R43 -> 0 | T40: =S43 -> 0
M41: =M43-M40+M42 -> 0 | N41: =N43-N40+N42 -> 0 | O41: =O43-O40+O42 -> 0 | P41: =P46*P40 -> 0 | Q41: =Q46*Q40 -> 0 | R41: =R46*R40 -> 0 | S41: =S46*S40 -> 0 | T41: =T46*T40 -> 0
M42: =M49 -> 0 | N42: =N49 -> 0 | O42: =O49 -> 0 | P42: =P45*P40 -> 0 | Q42: =Q45*Q40 -> 0 | R42: =R45*R40 -> 0 | S42: =S45*S40 -> 0 | T42: =T45*T40 -> 0
M43: ='Balance Sheet'!M40 -> 0 | N43: ='Balance Sheet'!N40 -> 0 | O43: ='Balance Sheet'!O40 -> 0 | P43: =P40+P41-P42 -> 0 | Q43: =Q40+Q41-Q42 -> 0 | R43: =R40+R41-R42 -> 0 | S43: =S40+S41-S42 -> 0 | T43: =T40+T41-T42 -> 0

Sheet WC
B2: Working Capital | L2: Index
B3: All figures in Rs. Crore
B4: Financial Year | C4: 2020 | D4: 2021 | E4: 2022 | F4: 2023 | G4: 2024 | H4: 2025 | I4: 2026 | J4: 2027 | K4: 2028 | L4: 2029
B5: Inventories | C5: ='Balance Sheet'!C5 -> 4183 | D5: ='Balance Sheet'!D5 -> 4018 | E5: ='Balance Sheet'!E5 -> 5596 | F5: ='Balance Sheet'!F5 -> 6612 | G5: ='Balance Sheet'!G5 -> 8330 | H5: =Drivers!H46*Drivers!H53 -> 8548.1616 | I5: =Drivers!I46*Drivers!I53 -> 9975.7046 | J5: =Drivers!J46*Drivers!J53 -> 11541.89 | K5: =Drivers!K46*Drivers!K53 -> 13238.548 | L5: =Drivers!L46*Drivers!L53 -> 15052.229
B6: Trade receivables | C6: ='Balance Sheet'!C6 -> 2383 | D6: ='Balance Sheet'!D6 -> 2572 | E6: ='Balance Sheet'!E6 -> 3072 | F6: ='Balance Sheet'!F6 -> 3867 | G6: ='Balance Sheet'!G6 -> 4278 | H6: =Drivers!H47*Drivers!H52 -> 4858.2927 | I6: =Drivers!I47*Drivers!I52 -> 5669.6276 | J6: =Drivers!J47*Drivers!J52 -> 6559.7592 | K6: =Drivers!K47*Drivers!K52 -> 7524.0437 | L6: =Drivers!L47*Drivers!L52 -> 8554.8377
B7: Loans n Advances | C7: ='Balance Sheet'!C8 -> 796 | D7: ='Balance Sheet'!D8 -> 660 | E7: ='Balance Sheet'!E8 -> 873 | F7: ='Balance Sheet'!F8 -> 951 | G7: ='Balance Sheet'!G8 -> 985 | H7: =Drivers!H48*Drivers!H52 -> 1308.1657 | I7: =Drivers!I48*Drivers!I52 -> 1526.6294 | J7: =Drivers!J48*Drivers!J52 -> 1766.3102 | K7: =Drivers!K48*Drivers!K52 -> 2025.9578 | L7: =Drivers!L48*Drivers!L52 -> 2303.514
B8: Other asset items | C8: ='Balance Sheet'!C9 -> 7312 | D8: ='Balance Sheet'!D9 -> 7642 | E8: ='Balance Sheet'!E9 -> 7304 | F8: ='Balance Sheet'!F9 -> 7885 | G8: ='Balance Sheet'!G9 -> 8483 | H8: =AVERAGE(C8:G8) -> 7725.2 | I8: =AVERAGE(D8:H8) -> 7807.84 | J8: =AVERAGE(E8:I8) -> 7841.008 | K8: =AVERAGE(F8:J8) -> 7948.4096 | L8: =AVERAGE(G8:K8) -> 7961.0915
B9: Current Assets | C9: =SUM(C5:C8) -> 14674 | D9: =SUM(D5:D8) -> 14892 | E9: =SUM(E5:E8) -> 16845 | F9: =SUM(F5:F8) -> 19315 | G9: =SUM(G5:G8) -> 22076 | H9: =SUM(H5:H8) -> 22439.82 | I9: =SUM(I5:I8) -> 24979.802 | J9: =SUM(J5:J8) -> 27708.968 | ... L9: =SUM(L5:L8) -> 33871.673
B11: Trade Payables | C11: ='Balance Sheet'!C21 -> 3363 | D11: ='Balance Sheet'!D21 -> 4548 | E11: ='Balance Sheet'!E21 -> 5863 | F11: ='Balance Sheet'!F21 -> 7209 | G11: ='Balance Sheet'!G21 -> 8478 | H11: =Drivers!H49*Drivers!H53 -> 8699.5767 | I11: =Drivers!I49*Drivers!I53 -> 10152.406 | J11: =Drivers!J49*Drivers!J53 -> 11746.334 | K11: =Drivers!K49*Drivers!K53 -> 13473.045 | L11: =Drivers!L49*Drivers!L53 -> 15318.852
B12: Advance from Customers | C12: ='Balance Sheet'!C22 -> 464 | D12: ='Balance Sheet'!D22 -> 415 | E12: ='Balance Sheet'!E22 -> 465 | F12: ='Balance Sheet'!F22 -> 384 | G12: ='Balance Sheet'!G22 -> 527 | H12: =Drivers!H50*Drivers!H52 -> 704.35318 | I12: =Drivers!I50*Drivers!I52 -> 821.98016 | J12: =Drivers!J50*Drivers!J52 -> 951.03105 | K12: =Drivers!K50*Drivers!K52 -> 1090.8326 | L12: =Drivers!L50*Drivers!L52 -> 1240.2767
B13: Other liability items | C13: ='Balance Sheet'!C23 -> 13316 | D13: ='Balance Sheet'!D23 -> 15313 | E13: ='Balance Sheet'!E23 -> 15753 | F13: ='Balance Sheet'!F23 -> 18349 | G13: ='Balance Sheet'!G23 -> 20106 | H13: =G13 -> 20106 | I13: =H13 -> 20106 | J13: =I13 -> 20106 | K13: =J13 -> 20106 | L13: =K13 -> 20106
B14: Current Liabilities | C14: =SUM(C11:C13) -> 17143 | D14: =SUM(D11:D13) -> 20276 | E14: =SUM(E11:E13) -> 22081 | F14: =SUM(F11:F13) -> 25942 | G14: =SUM(G11:G13) -> 29111 | H14: =SUM(H11:H13) -> 29509.93 | I14: =SUM(I11:I13) -> 31080.386 | J14: =SUM(J11:J13) -> 32803.365 | ... L14: =SUM(L11:L13) -> 36665.129
B16: Working Capital (CA-CL) | C16: =C9-C14 -> -2469 | D16: =D9-D14 -> -5384 | E16: =E9-E14 -> -5236 | F16: =F9-F14 -> -6627 | G16: =G9-G14 -> -7035 | H16: =H9-H14 -> -7070.1098 | I16: =I9-I14 -> -6100.5845 | J16: =J9-J14 -> -5094.3972 | ... L16: =L9-L14 -> -2793.4561
G18: Loans n Advances | H18: =G7-H7 -> -323.16573 | I18: =H7-I7 -> -218.46368 | J18: =I7-J7 -> -239.68082 | K18: =J7-K7 -> -259.6476 | L18: =K7-L7 -> -277.55622
G19: Other asset items | H19: =G8-H8 -> 757.8 | I19: =H8-I8 -> -82.64 | J19: =I8-J8 -> -33.168 | K19: =J8-K8 -> -107.4016 | L19: =K8-L8 -> -12.68192
G20: Advance from Customers | H20: =H12-G12 -> 177.35318 | I20: =I12-H12 -> 117.62698 | J20: =J12-I12 -> 129.05089 | K20: =K12-J12 -> 139.80156 | L20: =L12-K12 -> 149.44407
G21: Other liability items | H21: =H13-G13 -> 0 | I21: =I13-H13 -> 0 | J21: =J13-I13 -> 0 | K21: =K13-J13 -> 0 | L21: =L13-K13 -> 0
H22: =SUM(H18:H21) -> 611.98746 | I22: =SUM(I18:I21) -> -183.47669 | J22: =SUM(J18:J21) -> -143.79793 | K22: =SUM(K18:K21) -> -227.24764 | L22: =SUM(L18:L21) -> -140.79407
M36: 2022 | N36: 2023 | O36: 2024 | P36: 2025 | Q36: 2026 | R36: 2027 | S36: 2028 | T36: 2029
M37: =L40 -> 0 | N37: =M40 -> 0 | O37: =N40 -> 0 | P37: =O40 -> 0 | Q37: =P40 -> 0 | R37: =Q40 -> 0 | S37: =R40 -> 0 | T37: =S40 -> 0
M38: =M40-M37+M39 -> 0 | N38: =N40-N37+N39 -> 0 | O38: =O40-O37+O39 -> 0 | P38: =P43*P37 -> 0 | Q38: =Q43*Q37 -> 0 | R38: =R43*R37 -> 0 | S38: =S43*S37 -> 0 | T38: =T43*T37 -> 0
M39: =M46 -> 0 | N39: =N46 -> 0 | O39: =O46 -> 0 | P39: =P42*P37 -> 0 | Q39: =Q42*Q37 -> 0 | R39: =R42*R37 -> 0 | S39: =S42*S37 -> 0 | T39: =T42*T37 -> 0
M40: ='Balance Sheet'!M40 -> 0 | N40: ='Balance Sheet'!N40 -> 0 | O40: ='Balance Sheet'!O40 -> 0 | P40: =P37+P38-P39 -> 0 | Q40: =Q37+Q38-Q39 -> 0 | R40: =R37+R38-R39 -> 0 | S40: =S37+S38-S39 -> 0 | T40: =T37+T38-T39 -> 0

Sheet Source >

Sheet (IS)
A1: Profit & Loss | K1: Index
B2: 42064 | C2: 42430 | D2: 42795 | E2: 43160 | F2: 43525 | G2: 43891 | H2: 44256 | I2: 44621 | J2: 44986 | K2: 45352
A3: Sales | B3: 23306.19 | C3: 25153.24 | D3: 25374.94 | E3: 30978.62 | F3: 41462.26 | G3: 42429.89 | H3: 44725.8 | I3: 52598.83 | J3: 63239.98 | K3: 70908.14
A4: Raw Material Cost | B4: 4151.05 | C4: 4436.12 | D4: 4416.9 | E4: 5399.98 | F4: 6936.74 | G4: 6875.89 | H4: 6635.66 | I4: 8348.15 | J4: 10233.17 | K4: 11986.27
A5: Change in Inventory | B5: 100.88 | C5: 18.61 | D5: -75.69 | E5: 111.2 | F5: -46.35 | G5: 357.83 | H5: -450.15 | I5: 383.16 | J5: 518.21 | K5: 83.35
A6: Power and Fuel | B6: 5115.68 | C6: 4579.25 | D6: 4271.98 | E6: 6334.07 | F6: 9436.14 | G6: 8516.87 | H6: 8331.18 | I6: 12137.26 | J6: 18491.32 | K6: 18283.32
A7: Other Mfr. Exp | B7: 1908.68 | C7: 1933.88 | D7: 1991.28 | E7: 2289.53 | F7: 3001.06 | G7: 3043.3 | H7: 3067.38 | I7: 3889.67 | J7: 4344.34 | K7: 4898.17
A8: Employee Cost | B8: 1329.76 | C8: 1466.49 | D8: 1547.77 | E8: 1831.81 | F8: 2309.43 | G8: 2522.64 | H8: 2363.33 | I8: 2545 | J8: 2751.31 | K8: 3051.99
A9: Selling and admin | B9: 6944.03 | C9: 7200.47 | D9: 7149.12 | E9: 8320.28 | F9: 11563.8 | G9: 11237.32 | H9: 11266.02 | I9: 13282.22 | J9: 15859.6 | K9: 18066.95
A10: Other Expenses | B10: -467.61 | C10: 654.67 | D10: 709.76 | E10: 769.12 | F10: 821.8 | G10: 1345.73 | H10: 1044.17 | I10: 1265.34 | J10: 1458.6 | K10: 1736.23
A11: Other Income | B11: 350.08 | C11: 463.81 | D11: 648.12 | E11: 241.97 | F11: 350.1 | G11: 651.06 | H11: 618.52 | I11: 669.43 | J11: 507.11 | K11: 566.96
A12: Depreciation | B12: 1203.42 | C12: 1377.17 | D12: 1348.41 | E12: 1847.93 | F12: 2450.73 | G12: 2722.66 | H12: 2700.23 | I12: 2714.75 | J12: 2887.99 | K12: 3145.3
A13: Interest | B13: 586.51 | C13: 566.3 | D13: 640.1 | E13: 1237.6 | F13: 1777.86 | G13: 1991.65 | H13: 1485.65 | I13: 944.71 | J13: 822.72 | K13: 968
A14: Profit before tax | B14: 2985.63 | C14: 3421.31 | D14: 3872.05 | E14: 3301.47 | F14: 3468.45 | G14: 5182.72 | H14: 8000.55 | I14: 8524.32 | J14: 7416.25 | K14: 9422.22
... A17: Dividend Amount | B17: 246.96 | C17: 260.71 | D17: 274.51 | E17: 288.34 | F17: 315.84 | G17: 375.22 | H17: 1068 | I17: 1096.95 | J17: 1097.02 | K17: 2020.83
B20: Weightage | C20: Year | D20: Sales | E20: Growth
B21: 1 | C21: 42064 | D21: 23306.19 | E21: -
B22: =B21+1 -> 2 | C22: 42430 | D22: 25153.24 | E22: =D22/D21-1 -> 0.079251478
B23: =B22+1 -> 3 | C23: 42795 | D23: 25374.94 | E23: =D23/D22-1 -> 0.0088139739
B24: =B23+1 -> 4 | C24: 43160 | D24: 30978.62 | E24: =D24/D23-1 -> 0.2208352
B25: =B24+1 -> 5 | C25: 43525 | D25: 41462.26 | E25: =D25/D24-1 -> 0.33841533
B26: =B25+1 -> 6 | C26: 43891 | D26: 42429.89 | E26: =D26/D25-1 -> 0.023337609
B27: =B26+1 -> 7 | C27: 44256 | D27: 44725.8 | E27: =D27/D26-1 -> 0.054110675
B28: =B27+1 -> 8 | C28: 44621 | D28: 52598.83 | E28: =D28/D27-1 -> 0.17602882
B29: =B28+1 -> 9 | C29: 44986 | D29: 63239.98 | E29: =D29/D28-1 -> 0.20230773
B30: =B29+1 -> 10 | C30: 45352 | D30: 70908.14 | E30: =D30/D29-1 -> 0.12125494
B31: =B30+1 -> 11
B32: =B31+1 -> 12
C34: Arithmetic Mean | D34: =AVERAGE(E21:E30) -> 0.13603953
C35: Geometric Mean | D35: =(D30/D21)^(1/9)-1 -> 0.13159663 | E35: =_xlfn.RRI(9,D21,D30) -> 0.13159663
C36: Regression | D36: =FORECAST(B31,E21:E30,B21:B30) -> 0.16725434 | E36: 0.167

Sheet (BS)
A1: Balance Sheet | K1: Index
B2: 42064 | C2: 42430 | D2: 42795 | E2: 43160 | F2: 43525 | G2: 43891 | H2: 44256 | I2: 44621 | J2: 44986 | K2: 45352
A3: Equity Capital | B3: 274 | C3: 274 | D3: 275 | E3: 275 | F3: 275 | G3: 289 | H3: 289 | I3: 289 | J3: 289 | K3: 289
A4: Reserves | B4: 18767 | C4: 21671 | D4: 24117 | E4: 26107 | F4: 33476 | G4: 38755 | H4: 43886 | I4: 50147 | J4: 54036 | K4: 59939
A6: Borrowings - | B6: 9829 | C6: 10616 | D6: 8474 | E6: 19480 | F6: 25337 | G6: 23019 | H6: 21719 | I6: 11299 | J6: 11058 | K6: 11403
A7: Long term Borrowings | B7: 4993 | C7: 4897 | D7: 6371 | E7: 15863 | F7: 20650 | G7: 17368 | H7: 13548 | I7: 5303 | J7: 5356 | K7: 5308
A8: Short term Borrowings | B8: 2564 | C8: 2476 | D8: 1079 | E8: 2763 | F8: 3668 | G8: 4106 | H8: 6939 | I8: 4900 | J8: 4544 | K8: 4991
A9: Lease Liabilities | B9: 0 | C9: 0 | D9: 0 | E9: 0 | F9: 0 | G9: 0 | H9: 1232 | I9: 1096 | J9: 1157 | K9: 1103
A10: Other Borrowings | B10: 2273 | C10: 3244 | D10: 1024 | E10: 853 | F10: 1018 | G10: 1545 | H10: 0 | I10: 0 | J10: 0 | K10: 0
A12: Other Liabilities - | B12: 9183 | C12: 8631 | D12: 9343 | E12: 11280 | F12: 17438 | G12: 17151 | H12: 20282 | I12: 22077 | J12: 25998 | K12: 29167
A13: Non controlling int | B13: 18 | C13: 15 | D13: 10 | E13: 16 | F13: 12 | G13: 10 | H13: 6 | I13: -3 | J13: 55 | K13: 56
A14: Trade Payables | B14: 1711 | C14: 1717 | D14: 1849 | E14: 2385 | F14: 3160 | G14: 3363 | H14: 4548 | I14: 5863 | J14: 7209 | K14: 8478
A15: Advance from Customers | B15: 0 | C15: 166 | D15: 196 | E15: 305 | F15: 357 | G15: 464 | H15: 415 | I15: 465 | J15: 384 | K15: 527
A16: Other liability items | B16: 7454 | C16: 6733 | D16: 7288 | E16: 8574 | F16: 13909 | G16: 13316 | H16: 15313 | I16: 15753 | J16: 18349 | K16: 20106
... A41: Total Assets | B41: 38053 | C41: 41193 | D41: 42209 | E41: 57141 | F41: 76525 | G41: 79214 | H41: 86176 | I41: 83811 | J41: 91380 | K41: 100797

Sheet (CFS)
A1: Cash Flows | K1: Index
B2: 42064 | C2: 42430 | D2: 42795 | E2: 43160 | F2: 43525 | G2: 43891 | H2: 44256 | I2: 44621 | J2: 44986 | K2: 45352
A3: Cash from Operating Activity - | B3: 4190 | C3: 4526 | D3: 5005 | E3: 3888 | F3: 5956 | G3: 8973 | H3: 12501 | I3: 9283 | J3: 9070 | K3: 10896
A4: Profit from operations | B4: 4464 | C4: 4948 | D4: 5220 | E4: 5986 | F4: 7362 | G4: 9348 | H4: 11465 | I4: 11311 | J4: 10530 | K4: 13029
A5: Receivables | B5: -27 | C5: -287 | D5: 156 | E5: -454 | F5: -279 | G5: 473 | H5: -201 | I5: -495 | J5: -752 | K5: -421
A6: Inventory | B6: -326 | C6: 374 | D6: 54 | E6: -623 | F6: -15 | G6: -64 | H6: 165 | I6: -1579 | J6: -992 | K6: -1712
A7: Payables | B7: 383 | C7: 310 | D7: 482 | E7: 346 | F7: 766 | G7: 279 | H7: 2868 | I7: 2077 | J7: 1869 | K7: 1959
A8: Loans Advances | B8: -135 | C8: 0 | D8: 0 | E8: 0 | F8: 0 | G8: 0 | H8: 0 | I8: 0 | J8: 0 | K8: 0
A9: Other WC items | B9: 0 | C9: 32 | D9: -162 | E9: -525 | F9: -1167 | G9: -172 | H9: -505 | I9: -476 | J9: -461 | K9: -308
A10: Working capital changes | B10: -104 | C10: 429 | D10: 529 | E10: -1255 | F10: -696 | G10: =SUM(G5:G9) -> 516 | H10: =SUM(H5:H9) -> 2327 | I10: =SUM(I5:I9) -> -473 | J10: =SUM(J5:J9) -> -336 | K10: =SUM(K5:K9) -> -482
A11: Direct taxes | B11: -169 | C11: -852 | D11: -744 | E11: -843 | F11: -710 | G11: -891 | H11: -1291 | I11: -1555 | J11: -1124 | K11: -1651
A12: Other operating items | B12: 0 | C12: 0 | D12: 0 | E12: 0 | F12: 0 | G12: 0 | H12: 0 | I12: 0 | J12: 0 | K12: 0
A14: Cash from Investing Activity - | B14: -2144 | C14: -3673 | D14: -2501 | E14: 1866 | F14: 1165 | G14: -4193 | H14: -8856 | I14: 2322 | J14: -7187 | K14: -8788
A15: Fixed assets purchased | B15: -2722 | C15: -2150 | D15: -1402 | E15: -2103 | F15: -1808 | G15: -1766 | H15: -1925 | I15: -5613 | J15: -6200 | K15: -9006
A16: Fixed assets sold | B16: 12 | C16: 18 | D16: 35 | E16: 220 | F16: 160 | G16: 79 | H16: 86 | I16: 73 | J16: 95 | K16: 122
A17: Investments purchased | B17: -602 | C17: -2698 | D17: -3377 | E17: -3960 | F17: -1700 | G17: -6086 | H17: -12689 | I17: -7795 | J17: -7260 | K17: -7750
A18: Investments sold | B18: 1263 | C18: 2948 | D18: 2228 | E18: 5588 | F18: 4478 | G18: 3443 | H18: 7101 | I18: 13965 | J18: 7156 | K18: 7164
A19: Interest received | B19: 35 | C19: 59 | D19: 47 | E19: 67 | F19: 78 | G19: 89 | H19: 77 | I19: 174 | J19: 283 | K19: 161
A20: Dividends received | B20: 0 | C20: 0 | D20: 0 | E20: 0 | F20: 22 | G20: 32 | H20: 0 | I20: 0 | J20: 0 | K20: 0
A21: Invest in subsidiaries | B21: -21 | C21: -13 | D21: 0 | E21: 0 | F21: 0 | G21: 0 | H21: 0 | I21: 0 | J21: 0 | K21: 0
A22: Investment in group cos | B22: 0 | C22: 0 | D22: 0 | E22: -1 | F22: -8 | G22: -6 | H22: -3 | I22: 0 | J22: 0 | K22: 0
A23: Redemp n Canc of Shares | B23: 0 | C23: 0 | D23: 0 | E23: 0 | F23: 0 | G23: 0 | H23: 0 | I23: 0 | J23: 3 | K23: 0
... A36: Net Cash Flow | B36: -63 | C36: 8 | D36: -31 | E36: 18 | F36: 364 | G36: -296 | H36: -711 | I36: -892 | J36: 252 | K36: 183
